Workbook
Name UPDATE: 'Data Sheet'!$E$1

Sheet Coverpage
B18: FINANCIAL MODELLING
B19: & VALUATION REPORT
B20: 2026
B25: Prepared By: Daksh
B37: DISCLAIMER : This Report has been prepared for education purposes only. All the information is sourced from publicly availabe data, and does not constitute investment advice.

Sheet Index
B3: TABLE OF CONTENTS
B7: 1 | C7: One Page Profile
B8: 2 | C8: Historical Financial statement
B9: 3 | C9: Ratio Analysis
B10: 4 | C10: Common Size Statement Analysis
B11: 5 | C11: Forecasting
B12: 6 | C12: Return on Market
B13: 7 | C13: Weighted Average cost of capital
B14: 8 | C14: Intrinsic Growth
B15: 9 | C15: Valuation - Discounted Cashflow
B16: 10 | C16: Valuation - Comparable Company (Relative)
B17: 11 | C17: Value at Risk
B18: 12 | C18: Football Field Analysis
... B20: 14 | C20: Altman's Z Score Analysis

Sheet One Pager
B2: ='Data Sheet'!B1& " - "&"One Page Profile" -> INFOSYS LTD - One Page Profile
C4: Infosys Limited is an Indian multinational technology company that offers information technology, business consulting, and outsourcing services. Founded in 1981 by seven engineers, the company is headquartered in Bengaluru and considered one of the Big Six Indian IT companies.Infosys offers Software development, maintenance, and the independent validation services across industries Such as finance, insurance, manufacturing and among others.
B6: INR(Crs.)
B7: Key Financial Metrics | D7: ='Historical FS'!$H$11 -> 44286 | E7: ='Historical FS'!$I$11 -> 44651 | F7: ='Historical FS'!$J$11 -> 45016 | G7: ='Historical FS'!$K$11 -> 45382 | H7: ='Historical FS'!$L$11 -> 45747 | J7: Share Price - 5 Years
B9: Total Sales | D9: ='Historical FS'!$H$14 -> 100472 | E9: ='Historical FS'!$H$14 -> 100472 | F9: ='Historical FS'!$H$14 -> 100472 | G9: ='Historical FS'!$H$14 -> 100472 | H9: ='Historical FS'!$H$14 -> 100472
B10: Sales Growth (Y-O-Y) | D10: ='Ratio Analysis'!H13 -> 0.10662951 | E10: ='Ratio Analysis'!I13 -> 0.21069552 | F10: ='Ratio Analysis'!J13 -> 0.20655864 | G10: ='Ratio Analysis'!K13 -> 0.047033734 | H10: ='Ratio Analysis'!L13 -> 0.060649444
B11: Gross Profit Margins (%) | D11: ='Ratio Analysis'!H19 -> 0.31831754 | E11: ='Ratio Analysis'!I19 -> 0.30271043 | F11: ='Ratio Analysis'!J19 -> 0.28539794 | G11: ='Ratio Analysis'!K19 -> 0.28398516 | H11: ='Ratio Analysis'!L19 -> 0.28471072
B12: EBITDA Margins (%) | D12: ='Ratio Analysis'!H20 -> 0.27757982 | E12: ='Ratio Analysis'!I20 -> 0.25888475 | F12: ='Ratio Analysis'!J20 -> 0.23935898 | G12: ='Ratio Analysis'!K20 -> 0.2370339 | H12: ='Ratio Analysis'!L20 -> 0.24072642
B13: EBIT Margins (%) | D13: ='Ratio Analysis'!H21 -> 0.2450633 | E13: ='Ratio Analysis'!I21 -> 0.23030886 | F13: ='Ratio Analysis'!J21 -> 0.21057186 | G13: ='Ratio Analysis'!K21 -> 0.20659205 | H13: ='Ratio Analysis'!L21 -> 0.21120314
B14: Net Margin (%) | D14: ='Ratio Analysis'!H23 -> 0.19331754 | E14: ='Ratio Analysis'!I23 -> 0.18206033 | F14: ='Ratio Analysis'!J23 -> 0.16426036 | G14: ='Ratio Analysis'!K23 -> 0.17080757 | H14: ='Ratio Analysis'!L23 -> 0.1641205
B15: Earning Per Share (In Rs.) | D15: ='Historical FS'!$H$52 -> 45.586406 | E15: ='Historical FS'!$H$52 -> 45.586406 | F15: ='Historical FS'!$H$52 -> 45.586406 | G15: ='Historical FS'!$H$52 -> 45.586406 | H15: ='Historical FS'!$H$52 -> 45.586406
B16: EPS Growth (Y-O-Y) | D16: ='Historical FS'!$H$53 -> 1.166852 | E16: ='Historical FS'!$H$53 -> 1.166852 | F16: ='Historical FS'!$H$53 -> 1.166852 | G16: ='Historical FS'!$H$53 -> 1.166852 | H16: ='Historical FS'!$H$53 -> 1.166852
B17: Dividend Per Share (in Rs.) | D17: ='Historical FS'!$H$55 -> 26.91952 | E17: ='Historical FS'!$H$55 -> 26.91952 | F17: ='Historical FS'!$H$55 -> 26.91952 | G17: ='Historical FS'!$H$55 -> 26.91952 | H17: ='Historical FS'!$H$55 -> 26.91952
B18: DPS Growth (Y-O-Y) | D18: ='Ratio Analysis'!H17 -> 0.54369512 | E18: ='Ratio Analysis'!I17 -> 0.14865158 | F18: ='Ratio Analysis'!J17 -> 0.096761529 | G18: ='Ratio Analysis'!K17 -> 0.35349861 | H18: ='Ratio Analysis'!L17 -> -0.064855345
B20: Key Financial Ratios | D20: ='Historical FS'!$H$11 -> 44286 | E20: ='Historical FS'!$I$11 -> 44651 | F20: ='Historical FS'!$J$11 -> 45016 | G20: ='Historical FS'!$K$11 -> 45382 | H20: ='Historical FS'!$L$11 -> 45747 | J20: Volume - 5 Years
B22: Price to Earning Ratio | D22: ='P&L'!G14 -> 30.121702 | E22: ='P&L'!H14 -> 36.280171 | F22: ='P&L'!I14 -> 24.585986 | G22: ='P&L'!J14 -> 23.703944 | H22: ='P&L'!K14 -> 24.420247
B23: EV/ EBITDA | D23: ='Data Sheet'!G101 -> 20.204958 | E23: ='Data Sheet'!H101 -> 25.091505 | F23: ='Data Sheet'!I101 -> 16.752785 | G23: ='Data Sheet'!J101 -> 16.894951 | H23: ='Data Sheet'!K101 -> 16.212409
B24: EV/ Sales | D24: ='Data Sheet'!G102 -> 5.6084886 | E24: ='Data Sheet'!H102 -> 6.4958081 | F24: ='Data Sheet'!I102 -> 4.0099296 | G24: ='Data Sheet'!J102 -> 4.0046761 | H24: ='Data Sheet'!K102 -> 3.9027552
B25: Price to Book Value | D25: ='Data Sheet'!G105 -> 7.634282 | E25: ='Data Sheet'!H105 -> 10.645715 | F25: ='Data Sheet'!I105 -> 7.8560258 | G25: ='Data Sheet'!J105 -> 7.0568974 | H25: ='Data Sheet'!K105 -> 6.8080952
B26: Return on Equity (%) | D26: ='Ratio Analysis'!H31 -> 0.25439091 | E26: ='Ratio Analysis'!I31 -> 0.29390843 | F26: ='Ratio Analysis'!J31 -> 0.31970507 | G26: ='Ratio Analysis'!K31 -> 0.29788007 | H26: ='Ratio Analysis'!L31 -> 0.2791751
B27: Return on Capital Employed (%) | D27: ='Ratio Analysis'!H29 -> 0.34145894 | E27: ='Ratio Analysis'!I29 -> 0.38962437 | F27: ='Ratio Analysis'!J29 -> 0.41968318 | G27: ='Ratio Analysis'!K29 -> 0.37755895 | H27: ='Ratio Analysis'!L29 -> 0.37710606
B29: Top 10 Shareholders | F29: Shares (in Crs.) | G29: Holding (%) | H29: Value (Crs.) | J29: Shareholding Pattern
B31: ='Raw CF'!D31 -> LIFE INSURANCE CORPORATION OF INDIA - ULIF00220091 | F31: ='Raw CF'!E31 -> 41.930862 | G31: ='Raw CF'!F31 -> 0.1128 | H31: ='Raw CF'!G31 -> 54405.293
B32: ='Raw CF'!D32 -> SBI MUTUAL FUND | F32: ='Raw CF'!E32 -> 17.329272 | G32: ='Raw CF'!F32 -> 0.0466 | H32: ='Raw CF'!G32 -> 22484.73
B33: ='Raw CF'!D33 -> ICICI PRUDENTIAL MUTUAL FUND | F33: ='Raw CF'!E33 -> 15.288944 | G33: ='Raw CF'!F33 -> 0.0411 | H33: ='Raw CF'!G33 -> 19837.405
B34: ='Raw CF'!D34 -> National Pension System Trust | F34: ='Raw CF'!E34 -> 10.006455 | G34: ='Raw CF'!F34 -> 0.0269 | H34: ='Raw CF'!G34 -> 12983.375
B35: ='Raw CF'!D35 -> SUDHA GOPALAKRISHNAN | F35: ='Raw CF'!E35 -> 9.5357 | G35: ='Raw CF'!F35 -> 0.0257 | H35: ='Raw CF'!G35 -> 12372.571
B36: ='Raw CF'!D36 -> HDFC MUTUAL FUND | F36: ='Raw CF'!E36 -> 6.8989087 | G36: ='Raw CF'!F36 -> 0.0186 | H36: ='Raw CF'!G36 -> 8951.334
B37: ='Raw CF'!D37 -> UTI MUTUAL FUND | F37: ='Raw CF'!E37 -> 6.7112909 | G37: ='Raw CF'!F37 -> 0.0181 | H37: ='Raw CF'!G37 -> 8707.8999
B38: ='Raw CF'!D38 -> NIPPON LIFE INDIA TRUSTEE | F38: ='Raw CF'!E38 -> 6.5708729 | G38: ='Raw CF'!F38 -> 0.0177 | H38: ='Raw CF'!G38 -> 8525.7076
B39: ='Raw CF'!D39 -> ROHAN MURTY | F39: ='Raw CF'!E39 -> 6.0812892 | G39: ='Raw CF'!F39 -> 0.0164 | H39: ='Raw CF'!G39 -> 7890.4727
B40: ='Raw CF'!D40 -> VANGUARD TOTAL INTERNATIONAL STOCK INDEX FUND | F40: ='Raw CF'!E40 -> 5.139239 | G40: ='Raw CF'!F40 -> 0.0138 | H40: ='Raw CF'!G40 -> 6668.1626
B42: Managerial Remuneration | F42: Designations | G42: Since | H42: Salary (Crs.) | J42: Capital Structure
B44: Salil Parikh | F44: CEO & MD | G44: 2018 | H44: 80.62 | J44: Share Price as on 03/04/2026 | O44: 1300.8
B45: Karmesh Gul Vashwani | E45: Segment Head - CPG, Logistic & Retail | G45: 2003 | H45: 21.64 | J45: No. of Share | O45: ='Data Sheet'!B6 -> 405.53911
B46: Inderpreet Sawhaney | F46: CLO | G46: 2017 | H46: 20.09 | J46: Market Capitalisation | O46: =O44*O45 -> 527525.27
B47: Martha king | F47: CCO | G47: 2020 | H47: 16.08 | J47: less: Cash & Cash equivalents | O47: =-'Data Sheet'!K69 -> -24455
B48: Jasmeet singh | E48: Segment Head - Manufacturing | G48: 2011 | H48: 14.88 | J48: Add: Total Debt | O48: ='Data Sheet'!K59 -> 8227
J49: Add: Minority Interest | O49: 385
J50: Enterprise Value | O50: =SUM(O46:O49) -> 511682.27
B52: Recent Updates
B54: In March 2026, Infosys announced the acquisition of Optimum Healthcare IT ($465 million) and Stratus ($95 million) to expand its US presence in AI-driven healthcare and insurance consulting.
B55: The company expects a ₹1,745 crore tax refund following assessment orders, expected to positively impact future cash positions.
B56: The board announced an interim dividend of ₹23 per share in Q2 FY26 and maintained a share buyback program, highlighting a robust capital allocation policy.
B57: Announced a collaboration with Citizens Bank to launch an AI-first Innovation Hub in Bengaluru and a strategic tie-up with Anthropic to build AI agents for the telecommunications sector.
B60: Notes: All information and the data presented in this summary have been sourced from publicly available data - Screener.in, equity Master.com, invetsing.com and published Annual reports of Infosys.

Sheet  Financials>

Sheet Historical FS
B4: ='Data Sheet'!$B$1 -> INFOSYS LTD
B5: ( NSE: INFY | BSE: 500209)
B6: 1250
B7: 52 Week (High 1728 & Low 1215)
B10: ="Historical Financial Statements" -> Historical Financial Statements
B11: Particulars | C11: ='Data Sheet'!B16 -> 42460 | D11: ='Data Sheet'!C16 -> 42825 | E11: ='Data Sheet'!D16 -> 43190 | F11: ='Data Sheet'!E16 -> 43555 | G11: ='Data Sheet'!F16 -> 43921 | H11: ='Data Sheet'!G16 -> 44286 | I11: ='Data Sheet'!H16 -> 44651 | J11: ='Data Sheet'!I16 -> 45016 | ... L11: ='Data Sheet'!K16 -> 45747 | M11: LTM
A13: # | B13: Income Statement
B14: Sales | C14: =IFERROR('Data Sheet'!B17,"-") -> 62441 | D14: =IFERROR('Data Sheet'!C17,"-") -> 68484 | E14: =IFERROR('Data Sheet'!D17,"-") -> 70522 | F14: =IFERROR('Data Sheet'!E17,"-") -> 82675 | G14: =IFERROR('Data Sheet'!F17,"-") -> 90791 | H14: =IFERROR('Data Sheet'!G17,"-") -> 100472 | I14: =IFERROR('Data Sheet'!H17,"-") -> 121641 | J14: =IFERROR('Data Sheet'!I17,"-") -> 146767 | ... L14: =IFERROR('Data Sheet'!K17,"-") -> 162990 | M14: =IFERROR(SUM('Data Sheet'!H42:K42),"-") -> 173173
B15: Sales Growth % | C15: - | D15: =IFERROR(D14/C14-1,"-") -> 0.09677936 | E15: =IFERROR(E14/D14-1,"-") -> 0.029758776 | F15: =IFERROR(F14/E14-1,"-") -> 0.1723292 | G15: =IFERROR(G14/F14-1,"-") -> 0.098167523 | H15: =IFERROR(H14/G14-1,"-") -> 0.10662951 | I15: =IFERROR(I14/H14-1,"-") -> 0.21069552 | J15: =IFERROR(J14/I14-1,"-") -> 0.20655864 | K15: =IFERROR(K14/J14-1,"-") -> 0.047033734 | ... M15: =IFERROR(M14/L14-1,"-") -> 0.062476226
B17: COGS | C17: =IFERROR(SUM('Data Sheet'!B20:B22),"-") -> 40492 | D17: =IFERROR(SUM('Data Sheet'!C20:C22),"-") -> 44609 | E17: =IFERROR(SUM('Data Sheet'!D20:D22),"-") -> 46395 | F17: =IFERROR(SUM('Data Sheet'!E20:E22),"-") -> 55446 | G17: =IFERROR(SUM('Data Sheet'!F20:F22),"-") -> 62210 | H17: =IFERROR(SUM('Data Sheet'!G20:G22),"-") -> 68490 | I17: =IFERROR(SUM('Data Sheet'!H20:H22),"-") -> 84819 | J17: =IFERROR(SUM('Data Sheet'!I20:I22),"-") -> 104880 | ... L17: =IFERROR(SUM('Data Sheet'!K20:K22),"-") -> 116585 | M17: =IFERROR(SUM('Data Sheet'!H43:K43),"-") -> 132187
B18: COGS % sale | C18: =IFERROR(C17/C14,"-") -> 0.64848417 | D18: =IFERROR(D17/D14,"-") -> 0.65137842 | E18: =IFERROR(E17/E14,"-") -> 0.65787981 | F18: =IFERROR(F17/F14,"-") -> 0.67065014 | G18: =IFERROR(G17/G14,"-") -> 0.68520007 | H18: =IFERROR(H17/H14,"-") -> 0.68168246 | I18: =IFERROR(I17/I14,"-") -> 0.69728957 | J18: =IFERROR(J17/J14,"-") -> 0.71460206 | ... M18: =IFERROR(M17/M14,"-") -> 0.76332338
B20: Gross Profit | C20: =IFERROR(C14-C17,"-") -> 21949 | D20: =IFERROR(D14-D17,"-") -> 23875 | E20: =IFERROR(E14-E17,"-") -> 24127 | F20: =IFERROR(F14-F17,"-") -> 27229 | G20: =IFERROR(G14-G17,"-") -> 28581 | H20: =IFERROR(H14-H17,"-") -> 31982 | I20: =IFERROR(I14-I17,"-") -> 36822 | J20: =IFERROR(J14-J17,"-") -> 41887 | ... M20: =IFERROR(M14-M17,"-") -> 40986
B21: Gross Margin | C21: =IFERROR(C20/C14,"-") -> 0.35151583 | D21: =IFERROR(D20/D14,"-") -> 0.34862158 | E21: =IFERROR(E20/E14,"-") -> 0.34212019 | F21: =IFERROR(F20/F14,"-") -> 0.32934986 | G21: =IFERROR(G20/G14,"-") -> 0.31479993 | H21: =IFERROR(H20/H14,"-") -> 0.31831754 | I21: =IFERROR(I20/I14,"-") -> 0.30271043 | J21: =IFERROR(J20/J14,"-") -> 0.28539794 | ... M21: =IFERROR(M20/M14,"-") -> 0.23667662
B23: Selling, General & Admin. Exp. | C23: =IFERROR(SUM('Data Sheet'!B23:B24),"-") -> 4870 | D23: =IFERROR(SUM('Data Sheet'!C23:C24),"-") -> 5271 | E23: =IFERROR(SUM('Data Sheet'!D23:D24),"-") -> 5305 | F23: =IFERROR(SUM('Data Sheet'!E23:E24),"-") -> 7059 | G23: =IFERROR(SUM('Data Sheet'!F23:F24),"-") -> 6314 | H23: =IFERROR(SUM('Data Sheet'!G23:G24),"-") -> 4093 | I23: =IFERROR(SUM('Data Sheet'!H23:H24),"-") -> 5331 | J23: =IFERROR(SUM('Data Sheet'!I23:I24),"-") -> 6757 | ... L23: =IFERROR(SUM('Data Sheet'!K23:K24),"-") -> 7169
B24: SG&A expense % sale | C24: =IFERROR(C23/C14,"-") -> 0.077993626 | D24: =IFERROR(D23/D14,"-") -> 0.076966883 | E24: =IFERROR(E23/E14,"-") -> 0.075224753 | F24: =IFERROR(F23/F14,"-") -> 0.085382522 | G24: =IFERROR(G23/G14,"-") -> 0.069544338 | H24: =IFERROR(H23/H14,"-") -> 0.040737718 | I24: =IFERROR(I23/I14,"-") -> 0.043825684 | J24: =IFERROR(J23/J14,"-") -> 0.04603896 | ... M24: =IFERROR(M23/M14,"-") -> 0
B26: EBITDA | C26: =IFERROR(C20-C23,"-") -> 17079 | D26: =IFERROR(D20-D23,"-") -> 18604 | E26: =IFERROR(E20-E23,"-") -> 18822 | F26: =IFERROR(F20-F23,"-") -> 20170 | G26: =IFERROR(G20-G23,"-") -> 22267 | H26: =IFERROR(H20-H23,"-") -> 27889 | I26: =IFERROR(I20-I23,"-") -> 31491 | J26: =IFERROR(J20-J23,"-") -> 35130 | ... M26: =IFERROR(M20-M23,"-") -> 40986
B27: EBITDA Margin | C27: =IFERROR(C26/C14,"-") -> 0.2735222 | D27: =IFERROR(D26/D14,"-") -> 0.27165469 | E27: =IFERROR(E26/E14,"-") -> 0.26689544 | F27: =IFERROR(F26/F14,"-") -> 0.24396734 | G27: =IFERROR(G26/G14,"-") -> 0.24525559 | H27: =IFERROR(H26/H14,"-") -> 0.27757982 | I27: =IFERROR(I26/I14,"-") -> 0.25888475 | J27: =IFERROR(J26/J14,"-") -> 0.23935898 | ... M27: =IFERROR(M26/M14,"-") -> 0.23667662
B29: Depreciation | C29: =IFERROR('Data Sheet'!B26,"-") -> 1459 | D29: =IFERROR('Data Sheet'!C26,"-") -> 1703 | E29: =IFERROR('Data Sheet'!D26,"-") -> 1863 | F29: =IFERROR('Data Sheet'!E26,"-") -> 2011 | G29: =IFERROR('Data Sheet'!F26,"-") -> 2893 | H29: =IFERROR('Data Sheet'!G26,"-") -> 3267 | I29: =IFERROR('Data Sheet'!H26,"-") -> 3476 | J29: =IFERROR('Data Sheet'!I26,"-") -> 4225 | ... L29: =IFERROR('Data Sheet'!K26,"-") -> 4812 | M29: =IFERROR(SUM('Data Sheet'!H45:K45),"-") -> 4776
B30: Dep. % Sale | C30: =IFERROR(C29/C14,"-") -> 0.023366058 | D30: =IFERROR(D29/D14,"-") -> 0.024867122 | E30: =IFERROR(E29/E14,"-") -> 0.026417288 | F30: =IFERROR(F29/F14,"-") -> 0.024324161 | G30: =IFERROR(G29/G14,"-") -> 0.031864392 | H30: =IFERROR(H29/H14,"-") -> 0.032516522 | I30: =IFERROR(I29/I14,"-") -> 0.028575891 | J30: =IFERROR(J29/J14,"-") -> 0.028787125 | ... M30: =IFERROR(M29/M14,"-") -> 0.027579357
B32: EBIT | C32: =IFERROR(C26-C29,"-") -> 15620 | D32: =IFERROR(D26-D29,"-") -> 16901 | E32: =IFERROR(E26-E29,"-") -> 16959 | F32: =IFERROR(F26-F29,"-") -> 18159 | G32: =IFERROR(G26-G29,"-") -> 19374 | H32: =IFERROR(H26-H29,"-") -> 24622 | I32: =IFERROR(I26-I29,"-") -> 28015 | J32: =IFERROR(J26-J29,"-") -> 30905 | ... M32: =IFERROR(M26-M29,"-") -> 36210
B33: EBIT Margin | C33: =IFERROR(C32/C14,"-") -> 0.25015615 | D33: =IFERROR(D32/D14,"-") -> 0.24678757 | E33: =IFERROR(E32/E14,"-") -> 0.24047815 | F33: =IFERROR(F32/F14,"-") -> 0.21964318 | G33: =IFERROR(G32/G14,"-") -> 0.2133912 | H33: =IFERROR(H32/H14,"-") -> 0.2450633 | I33: =IFERROR(I32/I14,"-") -> 0.23030886 | J33: =IFERROR(J32/J14,"-") -> 0.21057186 | ... M33: =IFERROR(M32/M14,"-") -> 0.20909726
B35: Other Income | C35: =IFERROR('Data Sheet'!B25,"-") -> 3120 | D35: =IFERROR('Data Sheet'!C25,"-") -> 3050 | E35: =IFERROR('Data Sheet'!D25,"-") -> 3311 | F35: =IFERROR('Data Sheet'!E25,"-") -> 2882 | G35: =IFERROR('Data Sheet'!F25,"-") -> 2803 | H35: =IFERROR('Data Sheet'!G25,"-") -> 2201 | I35: =IFERROR('Data Sheet'!H25,"-") -> 2295 | J35: =IFERROR('Data Sheet'!I25,"-") -> 2701 | ... L35: =IFERROR('Data Sheet'!K25,"-") -> 3600 | M35: =IFERROR(SUM('Data Sheet'!H44:K44),"-") -> 3064
B36: OI % Sale | C36: =IFERROR(C35/C14,"-") -> 0.049967169 | D36: =IFERROR(D35/D14,"-") -> 0.04453595 | E36: =IFERROR(E35/E14,"-") -> 0.046949888 | F36: =IFERROR(F35/F14,"-") -> 0.034859389 | G36: =IFERROR(G35/G14,"-") -> 0.030873104 | H36: =IFERROR(H35/H14,"-") -> 0.021906601 | I36: =IFERROR(I35/I14,"-") -> 0.018866994 | J36: =IFERROR(J35/J14,"-") -> 0.01840332 | ... M36: =IFERROR(M35/M14,"-") -> 0.017693289
B38: Interest | C38: =IFERROR('Data Sheet'!B27,"-") -> 0 | D38: =IFERROR('Data Sheet'!C27,"-") -> 0 | E38: =IFERROR('Data Sheet'!D27,"-") -> 0 | F38: =IFERROR('Data Sheet'!E27,"-") -> 0 | G38: =IFERROR('Data Sheet'!F27,"-") -> 170 | H38: =IFERROR('Data Sheet'!G27,"-") -> 195 | I38: =IFERROR('Data Sheet'!H27,"-") -> 200 | J38: =IFERROR('Data Sheet'!I27,"-") -> 284 | ... L38: =IFERROR('Data Sheet'!K27,"-") -> 416 | M38: =IFERROR(SUM('Data Sheet'!H46:K46),"-") -> 413
B39: Int. % Sale | C39: =IFERROR(C38/C14,"-") -> 0 | D39: =IFERROR(D38/D14,"-") -> 0 | E39: =IFERROR(E38/E14,"-") -> 0 | F39: =IFERROR(F38/F14,"-") -> 0 | G39: =IFERROR(G38/G14,"-") -> 0.0018724323 | H39: =IFERROR(H38/H14,"-") -> 0.0019408392 | I39: =IFERROR(I38/I14,"-") -> 0.0016441825 | J39: =IFERROR(J38/J14,"-") -> 0.0019350399 | ... M39: =IFERROR(M38/M14,"-") -> 0.0023848983
B41: EBT / Profit before tax | C41: =IFERROR(C32+C35-C38,"-") -> 18740 | D41: =IFERROR(D32+D35-D38,"-") -> 19951 | E41: =IFERROR(E32+E35-E38,"-") -> 20270 | F41: =IFERROR(F32+F35-F38,"-") -> 21041 | G41: =IFERROR(G32+G35-G38,"-") -> 22007 | H41: =IFERROR(H32+H35-H38,"-") -> 26628 | I41: =IFERROR(I32+I35-I38,"-") -> 30110 | J41: =IFERROR(J32+J35-J38,"-") -> 33322 | ... M41: =IFERROR(M32+M35-M38,"-") -> 38861
B42: EBT % Margin | C42: =IFERROR(C41/C14,"-") -> 0.30012332 | D42: =IFERROR(D41/D14,"-") -> 0.29132352 | E42: =IFERROR(E41/E14,"-") -> 0.28742804 | F42: =IFERROR(F41/F14,"-") -> 0.25450257 | G42: =IFERROR(G41/G14,"-") -> 0.24239187 | H42: =IFERROR(H41/H14,"-") -> 0.26502906 | I42: =IFERROR(I41/I14,"-") -> 0.24753167 | J42: =IFERROR(J41/J14,"-") -> 0.22704014 | ... M42: =IFERROR(M41/M14,"-") -> 0.22440565
B44: Tax | C44: =IFERROR('Data Sheet'!B29,"-") -> 5251 | D44: =IFERROR('Data Sheet'!C29,"-") -> 5598 | E44: =IFERROR('Data Sheet'!D29,"-") -> 4241 | F44: =IFERROR('Data Sheet'!E29,"-") -> 5631 | G44: =IFERROR('Data Sheet'!F29,"-") -> 5368 | H44: =IFERROR('Data Sheet'!G29,"-") -> 7205 | I44: =IFERROR('Data Sheet'!H29,"-") -> 7964 | J44: =IFERROR('Data Sheet'!I29,"-") -> 9214 | ... L44: =IFERROR('Data Sheet'!K29,"-") -> 10858 | M44: =IFERROR(SUM('Data Sheet'!H48:K48),"-") -> 10858
B45: Effective tax rate | C45: =IFERROR(C44/C41,"-") -> 0.28020277 | D45: =IFERROR(D44/D41,"-") -> 0.28058744 | E45: =IFERROR(E44/E41,"-") -> 0.20922546 | F45: =IFERROR(F44/F41,"-") -> 0.26762036 | G45: =IFERROR(G44/G41,"-") -> 0.24392239 | H45: =IFERROR(H44/H41,"-") -> 0.27057984 | I45: =IFERROR(I44/I41,"-") -> 0.26449684 | J45: =IFERROR(J44/J41,"-") -> 0.27651401 | ... M45: =IFERROR(M44/M41,"-") -> 0.27940609
B47: Net Profit | C47: =IFERROR(C41-C44,"-") -> 13489 | D47: =IFERROR(D41-D44,"-") -> 14353 | E47: =IFERROR(E41-E44,"-") -> 16029 | F47: =IFERROR(F41-F44,"-") -> 15410 | G47: =IFERROR(G41-G44,"-") -> 16639 | H47: =IFERROR(H41-H44,"-") -> 19423 | I47: =IFERROR(I41-I44,"-") -> 22146 | J47: =IFERROR(J41-J44,"-") -> 24108 | ... M47: =IFERROR(M41-M44,"-") -> 28003
B48: Net Margin | C48: =IFERROR(C47/C14,"-") -> 0.21602793 | D48: =IFERROR(D47/D14,"-") -> 0.2095818 | E48: =IFERROR(E47/E14,"-") -> 0.22729077 | F48: =IFERROR(F47/F14,"-") -> 0.1863925 | G48: =IFERROR(G47/G14,"-") -> 0.18326706 | H48: =IFERROR(H47/H14,"-") -> 0.19331754 | I48: =IFERROR(I47/I14,"-") -> 0.18206033 | J48: =IFERROR(J47/J14,"-") -> 0.16426036 | ... M48: =IFERROR(M47/M14,"-") -> 0.16170535
B50: No. of Equity Share (CR.) | C50: =IFERROR('Data Sheet'!B93,"-") -> 459.39 | D50: =IFERROR('Data Sheet'!C93,"-") -> 459.39 | E50: =IFERROR('Data Sheet'!D93,"-") -> 436.82 | F50: =IFERROR('Data Sheet'!E93,"-") -> 436.89 | G50: =IFERROR('Data Sheet'!F93,"-") -> 425.9 | H50: =IFERROR('Data Sheet'!G93,"-") -> 426.07 | I50: =IFERROR('Data Sheet'!H93,"-") -> 420.67 | J50: =IFERROR('Data Sheet'!I93,"-") -> 414.86 | ... L50: =IFERROR('Data Sheet'!K93,"-") -> 415.33
B52: Earning per share | C52: =IFERROR(C47/C50,"-") -> 29.362851 | D52: =IFERROR(D47/D50,"-") -> 31.243606 | E52: =IFERROR(E47/E50,"-") -> 36.694748 | F52: =IFERROR(F47/F50,"-") -> 35.272036 | G52: =IFERROR(G47/G50,"-") -> 39.067856 | H52: =IFERROR(H47/H50,"-") -> 45.586406 | I52: =IFERROR(I47/I50,"-") -> 52.644591 | J52: =IFERROR(J47/J50,"-") -> 58.11117 | ... L52: =IFERROR(L47/L50,"-") -> 64.406616
B53: EPS growth % | C53: - | D53: =IFERROR(D52/C52,"-") -> 1.0640522 | E53: =IFERROR(E52/D52,"-") -> 1.1744723 | F53: =IFERROR(F52/E52,"-") -> 0.96122846 | G53: =IFERROR(G52/F52,"-") -> 1.1076156 | H53: =IFERROR(H52/G52,"-") -> 1.166852 | I53: =IFERROR(I52/H52,"-") -> 1.1548309 | J53: =IFERROR(J52/I52,"-") -> 1.1038393 | K53: =IFERROR(K52/J52,"-") -> 1.0881639 | L53: =IFERROR(L52/K52,"-") -> 1.0185364
B55: Dividend per share | C55: =IFERROR('Data Sheet'!B31/C50,"-") -> 12.077755 | D55: =IFERROR('Data Sheet'!C31/D50,"-") -> 12.824833 | E55: =IFERROR('Data Sheet'!D31/E50,"-") -> 21.669337 | F55: =IFERROR('Data Sheet'!E31/F50,"-") -> 21.109433 | G55: =IFERROR('Data Sheet'!F31/G50,"-") -> 17.438366 | H55: =IFERROR('Data Sheet'!G31/H50,"-") -> 26.91952 | I55: =IFERROR('Data Sheet'!H31/I50,"-") -> 30.92115 | J55: =IFERROR('Data Sheet'!I31/J50,"-") -> 33.913127 | ... L55: =IFERROR('Data Sheet'!K31/L50,"-") -> 42.924422
B56: Dividend Payout ratio | C56: =IFERROR(C55/C52,"-") -> 0.41132775 | D56: =IFERROR(D55/D52,"-") -> 0.41047865 | E56: =IFERROR(E55/E52,"-") -> 0.59052966 | F56: =IFERROR(F55/F52,"-") -> 0.59847502 | G56: =IFERROR(G55/G52,"-") -> 0.44636096 | H56: =IFERROR(H55/H52,"-") -> 0.5905164 | I56: =IFERROR(I55/I52,"-") -> 0.58735663 | J56: =IFERROR(J55/J52,"-") -> 0.58359051 | ... L56: =IFERROR(L55/L52,"-") -> 0.66645981
B58: Retained Earnings | C58: =IFERROR(IF(C52>C55,1-C56,0),"-") -> 0.58867225 | D58: =IFERROR(IF(D52>D55,1-D56,0),"-") -> 0.58952135 | E58: =IFERROR(IF(E52>E55,1-E56,0),"-") -> 0.40947034 | F58: =IFERROR(IF(F52>F55,1-F56,0),"-") -> 0.40152498 | G58: =IFERROR(IF(G52>G55,1-G56,0),"-") -> 0.55363904 | H58: =IFERROR(IF(H52>H55,1-H56,0),"-") -> 0.4094836 | I58: =IFERROR(IF(I52>I55,1-I56,0),"-") -> 0.41264337 | J58: =IFERROR(IF(J52>J55,1-J56,0),"-") -> 0.41640949 | ... L58: =IFERROR(IF(L52>L55,1-L56,0),"-") -> 0.33354019
A63: # | B63: Balance Sheet
B64: Equity Share Capital | C64: =IFERROR('Data Sheet'!B57,"-") -> 1144 | D64: =IFERROR('Data Sheet'!C57,"-") -> 1144 | E64: =IFERROR('Data Sheet'!D57,"-") -> 1088 | F64: =IFERROR('Data Sheet'!E57,"-") -> 2170 | G64: =IFERROR('Data Sheet'!F57,"-") -> 2122 | H64: =IFERROR('Data Sheet'!G57,"-") -> 2124 | I64: =IFERROR('Data Sheet'!H57,"-") -> 2098 | J64: =IFERROR('Data Sheet'!I57,"-") -> 2069 | ... L64: =IFERROR('Data Sheet'!K57,"-") -> 2073
B65: Reserves | C65: =IFERROR('Data Sheet'!B58,"-") -> 60600 | D65: =IFERROR('Data Sheet'!C58,"-") -> 67838 | E65: =IFERROR('Data Sheet'!D58,"-") -> 63835 | F65: =IFERROR('Data Sheet'!E58,"-") -> 62778 | G65: =IFERROR('Data Sheet'!F58,"-") -> 63328 | H65: =IFERROR('Data Sheet'!G58,"-") -> 74227 | I65: =IFERROR('Data Sheet'!H58,"-") -> 73252 | J65: =IFERROR('Data Sheet'!I58,"-") -> 73338 | ... L65: =IFERROR('Data Sheet'!K58,"-") -> 93745
B66: Borrowings | C66: =IFERROR('Data Sheet'!B59,"-") -> 0 | D66: =IFERROR('Data Sheet'!C59,"-") -> 0 | E66: =IFERROR('Data Sheet'!D59,"-") -> 0 | F66: =IFERROR('Data Sheet'!E59,"-") -> 0 | G66: =IFERROR('Data Sheet'!F59,"-") -> 4633 | H66: =IFERROR('Data Sheet'!G59,"-") -> 5325 | I66: =IFERROR('Data Sheet'!H59,"-") -> 5474 | J66: =IFERROR('Data Sheet'!I59,"-") -> 8299 | ... L66: =IFERROR('Data Sheet'!K59,"-") -> 8227
B67: Other Liabilities | C67: =IFERROR('Data Sheet'!B60,"-") -> 13354 | D67: =IFERROR('Data Sheet'!C60,"-") -> 14166 | E67: =IFERROR('Data Sheet'!D60,"-") -> 14426 | F67: =IFERROR('Data Sheet'!E60,"-") -> 19118 | G67: =IFERROR('Data Sheet'!F60,"-") -> 21717 | H67: =IFERROR('Data Sheet'!G60,"-") -> 25835 | I67: =IFERROR('Data Sheet'!H60,"-") -> 35905 | J67: =IFERROR('Data Sheet'!I60,"-") -> 40890 | ... L67: =IFERROR('Data Sheet'!K60,"-") -> 43750
B68: Total Liabilities | C68: =IFERROR('Data Sheet'!B61,"-") -> 75098 | D68: =IFERROR('Data Sheet'!C61,"-") -> 83148 | E68: =IFERROR('Data Sheet'!D61,"-") -> 79349 | F68: =IFERROR('Data Sheet'!E61,"-") -> 84066 | G68: =IFERROR('Data Sheet'!F61,"-") -> 91800 | H68: =IFERROR('Data Sheet'!G61,"-") -> 107511 | I68: =IFERROR('Data Sheet'!H61,"-") -> 116729 | J68: =IFERROR('Data Sheet'!I61,"-") -> 124596 | ... L68: =IFERROR('Data Sheet'!K61,"-") -> 147795
B70: Fixed Assests Net Block | C70: =IFERROR('Data Sheet'!B62,"-") -> 13386 | D70: =IFERROR('Data Sheet'!C62,"-") -> 14179 | E70: =IFERROR('Data Sheet'!D62,"-") -> 12574 | F70: =IFERROR('Data Sheet'!E62,"-") -> 15710 | G70: =IFERROR('Data Sheet'!F62,"-") -> 23789 | H70: =IFERROR('Data Sheet'!G62,"-") -> 25505 | I70: =IFERROR('Data Sheet'!H62,"-") -> 25800 | J70: =IFERROR('Data Sheet'!I62,"-") -> 29225 | ... L70: =IFERROR('Data Sheet'!K62,"-") -> 30961
B71: Capital Work in Progress | C71: =IFERROR('Data Sheet'!B63,"-") -> 960 | D71: =IFERROR('Data Sheet'!C63,"-") -> 1365 | E71: =IFERROR('Data Sheet'!D63,"-") -> 1606 | F71: =IFERROR('Data Sheet'!E63,"-") -> 1388 | G71: =IFERROR('Data Sheet'!F63,"-") -> 954 | H71: =IFERROR('Data Sheet'!G63,"-") -> 922 | I71: =IFERROR('Data Sheet'!H63,"-") -> 416 | J71: =IFERROR('Data Sheet'!I63,"-") -> 288 | ... L71: =IFERROR('Data Sheet'!K63,"-") -> 814
B72: Investments | C72: =IFERROR('Data Sheet'!B64,"-") -> 1892 | D72: =IFERROR('Data Sheet'!C64,"-") -> 16423 | E72: =IFERROR('Data Sheet'!D64,"-") -> 12163 | F72: =IFERROR('Data Sheet'!E64,"-") -> 11261 | G72: =IFERROR('Data Sheet'!F64,"-") -> 8792 | H72: =IFERROR('Data Sheet'!G64,"-") -> 14205 | I72: =IFERROR('Data Sheet'!H64,"-") -> 20324 | J72: =IFERROR('Data Sheet'!I64,"-") -> 19478 | ... L72: =IFERROR('Data Sheet'!K64,"-") -> 23541
B73: Total Non-Current Assests | C73: =IFERROR(SUM(C70:C72),"-") -> 16238 | D73: =IFERROR(SUM(D70:D72),"-") -> 31967 | E73: =IFERROR(SUM(E70:E72),"-") -> 26343 | F73: =IFERROR(SUM(F70:F72),"-") -> 28359 | G73: =IFERROR(SUM(G70:G72),"-") -> 33535 | H73: =IFERROR(SUM(H70:H72),"-") -> 40632 | I73: =IFERROR(SUM(I70:I72),"-") -> 46540 | J73: =IFERROR(SUM(J70:J72),"-") -> 48991 | ... L73: =IFERROR(SUM(L70:L72),"-") -> 55316
B75: Receivables | C75: =IFERROR('Data Sheet'!B67,"-") -> 11330 | D75: =IFERROR('Data Sheet'!C67,"-") -> 12322 | E75: =IFERROR('Data Sheet'!D67,"-") -> 13142 | F75: =IFERROR('Data Sheet'!E67,"-") -> 14827 | G75: =IFERROR('Data Sheet'!F67,"-") -> 18487 | H75: =IFERROR('Data Sheet'!G67,"-") -> 19294 | I75: =IFERROR('Data Sheet'!H67,"-") -> 22698 | J75: =IFERROR('Data Sheet'!I67,"-") -> 25424 | ... L75: =IFERROR('Data Sheet'!K67,"-") -> 31158
B76: Inventory | C76: =IFERROR('Data Sheet'!B68,"-") -> 0 | D76: =IFERROR('Data Sheet'!C68,"-") -> 0 | E76: =IFERROR('Data Sheet'!D68,"-") -> 0 | F76: =IFERROR('Data Sheet'!E68,"-") -> 0 | G76: =IFERROR('Data Sheet'!F68,"-") -> 0 | H76: =IFERROR('Data Sheet'!G68,"-") -> 0 | I76: =IFERROR('Data Sheet'!H68,"-") -> 0 | J76: =IFERROR('Data Sheet'!I68,"-") -> 0 | ... L76: =IFERROR('Data Sheet'!K68,"-") -> 0
B77: Cash & Bank | C77: =IFERROR('Data Sheet'!B69,"-") -> 32697 | D77: =IFERROR('Data Sheet'!C69,"-") -> 22625 | E77: =IFERROR('Data Sheet'!D69,"-") -> 19818 | F77: =IFERROR('Data Sheet'!E69,"-") -> 19568 | G77: =IFERROR('Data Sheet'!F69,"-") -> 18649 | H77: =IFERROR('Data Sheet'!G69,"-") -> 24714 | I77: =IFERROR('Data Sheet'!H69,"-") -> 17472 | J77: =IFERROR('Data Sheet'!I69,"-") -> 12173 | ... L77: =IFERROR('Data Sheet'!K69,"-") -> 24455
B78: Other Assets | C78: =IFERROR('Data Sheet'!B65-('Data Sheet'!B67+'Data Sheet'!B68+'Data Sheet'!B69),"-") -> 14833 | D78: =IFERROR('Data Sheet'!C65-('Data Sheet'!C67+'Data Sheet'!C68+'Data Sheet'!C69),"-") -> 16234 | E78: =IFERROR('Data Sheet'!D65-('Data Sheet'!D67+'Data Sheet'!D68+'Data Sheet'!D69),"-") -> 20046 | F78: =IFERROR('Data Sheet'!E65-('Data Sheet'!E67+'Data Sheet'!E68+'Data Sheet'!E69),"-") -> 21312 | G78: =IFERROR('Data Sheet'!F65-('Data Sheet'!F67+'Data Sheet'!F68+'Data Sheet'!F69),"-") -> 21129 | H78: =IFERROR('Data Sheet'!G65-('Data Sheet'!G67+'Data Sheet'!G68+'Data Sheet'!G69),"-") -> 22871 | I78: =IFERROR('Data Sheet'!H65-('Data Sheet'!H67+'Data Sheet'!H68+'Data Sheet'!H69),"-") -> 30019 | J78: =IFERROR('Data Sheet'!I65-('Data Sheet'!I67+'Data Sheet'!I68+'Data Sheet'!I69),"-") -> 38008 | ... L78: =IFERROR('Data Sheet'!K65-('Data Sheet'!K67+'Data Sheet'!K68+'Data Sheet'!K69),"-") -> 36866
B79: Total Current Assests | C79: =IFERROR(SUM(C75:C78),"-") -> 58860 | D79: =IFERROR(SUM(D75:D78),"-") -> 51181 | E79: =IFERROR(SUM(E75:E78),"-") -> 53006 | F79: =IFERROR(SUM(F75:F78),"-") -> 55707 | G79: =IFERROR(SUM(G75:G78),"-") -> 58265 | H79: =IFERROR(SUM(H75:H78),"-") -> 66879 | I79: =IFERROR(SUM(I75:I78),"-") -> 70189 | J79: =IFERROR(SUM(J75:J78),"-") -> 75605 | ... L79: =IFERROR(SUM(L75:L78),"-") -> 92479
B81: Total Assests | C81: =IFERROR(SUM(C73,C79),"-") -> 75098 | D81: =IFERROR(SUM(D73,D79),"-") -> 83148 | E81: =IFERROR(SUM(E73,E79),"-") -> 79349 | F81: =IFERROR(SUM(F73,F79),"-") -> 84066 | G81: =IFERROR(SUM(G73,G79),"-") -> 91800 | H81: =IFERROR(SUM(H73,H79),"-") -> 107511 | I81: =IFERROR(SUM(I73,I79),"-") -> 116729 | J81: =IFERROR(SUM(J73,J79),"-") -> 124596 | ... L81: =IFERROR(SUM(L73,L79),"-") -> 147795
B83: Check | C83: =C81=C68 -> TRUE | D83: =D81=D68 -> TRUE | E83: =E81=E68 -> TRUE | F83: =F81=F68 -> TRUE | G83: =G81=G68 -> TRUE | H83: =H81=H68 -> TRUE | I83: =I81=I68 -> TRUE | J83: =J81=J68 -> TRUE | ... L83: =L81=L68 -> TRUE
A85: # | B85: Cash Flow Statement
B86: OPERATING ACTIVITIES
B87: Profit from operations | C87: =IFERROR(SUM('Raw CF'!E4),"-") -> 17839 | D87: =IFERROR(SUM('Raw CF'!F4),"-") -> 19340 | E87: =IFERROR(SUM('Raw CF'!G4),"-") -> 19963 | F87: =IFERROR(SUM('Raw CF'!H4),"-") -> 22126 | G87: =IFERROR(SUM('Raw CF'!I4),"-") -> 23920 | H87: =IFERROR(SUM('Raw CF'!J4),"-") -> 28845 | I87: =IFERROR(SUM('Raw CF'!K4),"-") -> 32921 | J87: =IFERROR(SUM('Raw CF'!L4),"-") -> 37605 | ... L87: =IFERROR(SUM('Raw CF'!N4),"-") -> 41591
B88: Receivables | C88: =IFERROR(SUM('Raw CF'!E5),"-") -> -1654 | D88: =IFERROR(SUM('Raw CF'!F5),"-") -> -1743 | E88: =IFERROR(SUM('Raw CF'!G5),"-") -> -1523 | F88: =IFERROR(SUM('Raw CF'!H5),"-") -> -2881 | G88: =IFERROR(SUM('Raw CF'!I5),"-") -> -3861 | H88: =IFERROR(SUM('Raw CF'!J5),"-") -> -1835 | I88: =IFERROR(SUM('Raw CF'!K5),"-") -> -7937 | J88: =IFERROR(SUM('Raw CF'!L5),"-") -> -7076 | ... L88: =IFERROR(SUM('Raw CF'!N5),"-") -> -1769
B89: Payables | C89: =IFERROR(SUM('Raw CF'!E6),"-") -> 242 | D89: =IFERROR(SUM('Raw CF'!F6),"-") -> -19 | E89: =IFERROR(SUM('Raw CF'!G6),"-") -> 328 | F89: =IFERROR(SUM('Raw CF'!H6),"-") -> 916 | G89: =IFERROR(SUM('Raw CF'!I6),"-") -> -373 | H89: =IFERROR(SUM('Raw CF'!J6),"-") -> -245 | I89: =IFERROR(SUM('Raw CF'!K6),"-") -> 1489 | J89: =IFERROR(SUM('Raw CF'!L6),"-") -> -279 | ... L89: =IFERROR(SUM('Raw CF'!N6),"-") -> 176
B90: Loans Advances | C90: =IFERROR(SUM('Raw CF'!E7),"-") -> -1134 | D90: =IFERROR(SUM('Raw CF'!F7),"-") -> 0 | E90: =IFERROR(SUM('Raw CF'!G7),"-") -> 0 | F90: =IFERROR(SUM('Raw CF'!H7),"-") -> 0 | G90: =IFERROR(SUM('Raw CF'!I7),"-") -> 0 | H90: =IFERROR(SUM('Raw CF'!J7),"-") -> -534 | I90: =IFERROR(SUM('Raw CF'!K7),"-") -> -1914 | J90: =IFERROR(SUM('Raw CF'!L7),"-") -> -3108 | ... L90: =IFERROR(SUM('Raw CF'!N7),"-") -> -1024
B91: Other WC items | C91: =IFERROR(SUM('Raw CF'!E8),"-") -> 600 | D91: =IFERROR(SUM('Raw CF'!F8),"-") -> -394 | E91: =IFERROR(SUM('Raw CF'!G8),"-") -> 1279 | F91: =IFERROR(SUM('Raw CF'!H8),"-") -> 1512 | G91: =IFERROR(SUM('Raw CF'!I8),"-") -> 1867 | H91: =IFERROR(SUM('Raw CF'!J8),"-") -> 3382 | I91: =IFERROR(SUM('Raw CF'!K8),"-") -> 6938 | J91: =IFERROR(SUM('Raw CF'!L8),"-") -> 4119 | ... L91: =IFERROR(SUM('Raw CF'!N8),"-") -> 2322
B92: Working capital changes | C92: =IFERROR(SUM('Raw CF'!E9),"-") -> -1946 | D92: =IFERROR(SUM('Raw CF'!F9),"-") -> -2156 | E92: =IFERROR(SUM('Raw CF'!G9),"-") -> 84 | F92: =IFERROR(SUM('Raw CF'!H9),"-") -> -453 | G92: =IFERROR(SUM('Raw CF'!I9),"-") -> -2367 | H92: =IFERROR(SUM('Raw CF'!J9),"-") -> 768 | I92: =IFERROR(SUM('Raw CF'!K9),"-") -> -1424 | J92: =IFERROR(SUM('Raw CF'!L9),"-") -> -6344 | ... L92: =IFERROR(SUM('Raw CF'!N9),"-") -> -295
B93: Direct taxes | C93: =IFERROR(SUM('Raw CF'!E10),"-") -> -5865 | D93: =IFERROR(SUM('Raw CF'!F10),"-") -> -5653 | E93: =IFERROR(SUM('Raw CF'!G10),"-") -> -6829 | F93: =IFERROR(SUM('Raw CF'!H10),"-") -> -6832 | G93: =IFERROR(SUM('Raw CF'!I10),"-") -> -4550 | H93: =IFERROR(SUM('Raw CF'!J10),"-") -> -6389 | I93: =IFERROR(SUM('Raw CF'!K10),"-") -> -7612 | J93: =IFERROR(SUM('Raw CF'!L10),"-") -> -8794 | ... L93: =IFERROR(SUM('Raw CF'!N10),"-") -> -5602
B94: Cash from Operating Activity | C94: =IFERROR('Raw CF'!E3,"-") -> 10028 | D94: =IFERROR('Raw CF'!F3,"-") -> 11531 | E94: =IFERROR('Raw CF'!G3,"-") -> 13218 | F94: =IFERROR('Raw CF'!H3,"-") -> 14841 | G94: =IFERROR('Raw CF'!I3,"-") -> 17003 | H94: =IFERROR('Raw CF'!J3,"-") -> 23224 | I94: =IFERROR('Raw CF'!K3,"-") -> 23885 | J94: =IFERROR('Raw CF'!L3,"-") -> 22467 | ... L94: =IFERROR('Raw CF'!N3,"-") -> 35694
B97: INVESTING ACTIVITIES
B98: Fixed assets purchased | C98: =IFERROR('Raw CF'!E12,"-") -> -2723 | D98: =IFERROR('Raw CF'!F12,"-") -> -2760 | E98: =IFERROR('Raw CF'!G12,"-") -> -1998 | F98: =IFERROR('Raw CF'!H12,"-") -> -2445 | G98: =IFERROR('Raw CF'!I12,"-") -> -3307 | H98: =IFERROR('Raw CF'!J12,"-") -> -2107 | I98: =IFERROR('Raw CF'!K12,"-") -> -2161 | J98: =IFERROR('Raw CF'!L12,"-") -> -2579 | ... L98: =IFERROR('Raw CF'!N12,"-") -> -2237
B99: Fixed assets sold | C99: =IFERROR('Raw CF'!E13,"-") -> 0 | D99: =IFERROR('Raw CF'!F13,"-") -> 0 | E99: =IFERROR('Raw CF'!G13,"-") -> 0 | F99: =IFERROR('Raw CF'!H13,"-") -> 0 | G99: =IFERROR('Raw CF'!I13,"-") -> 0 | H99: =IFERROR('Raw CF'!J13,"-") -> 0 | I99: =IFERROR('Raw CF'!K13,"-") -> 0 | J99: =IFERROR('Raw CF'!L13,"-") -> 0 | ... L99: =IFERROR('Raw CF'!N13,"-") -> 0
B100: Investments purchased | C100: =IFERROR('Raw CF'!E14,"-") -> -24577 | D100: =IFERROR('Raw CF'!F14,"-") -> -66410 | E100: =IFERROR('Raw CF'!G14,"-") -> -69159 | F100: =IFERROR('Raw CF'!H14,"-") -> -79410 | G100: =IFERROR('Raw CF'!I14,"-") -> -37482 | H100: =IFERROR('Raw CF'!J14,"-") -> -46738 | I100: =IFERROR('Raw CF'!K14,"-") -> -59951 | J100: =IFERROR('Raw CF'!L14,"-") -> -75800 | ... L100: =IFERROR('Raw CF'!N14,"-") -> -82753
B101: Investments sold | C101: =IFERROR('Raw CF'!E15,"-") -> 24980 | D101: =IFERROR('Raw CF'!F15,"-") -> 52048 | E101: =IFERROR('Raw CF'!G15,"-") -> 74003 | F101: =IFERROR('Raw CF'!H15,"-") -> 78098 | G101: =IFERROR('Raw CF'!I15,"-") -> 38861 | H101: =IFERROR('Raw CF'!J15,"-") -> 40381 | I101: =IFERROR('Raw CF'!K15,"-") -> 57356 | J101: =IFERROR('Raw CF'!L15,"-") -> 76722 | ... L101: =IFERROR('Raw CF'!N15,"-") -> 84888
B102: Interest received | C102: =IFERROR('Raw CF'!E16,"-") -> 2383 | D102: =IFERROR('Raw CF'!F16,"-") -> 0 | E102: =IFERROR('Raw CF'!G16,"-") -> 0 | F102: =IFERROR('Raw CF'!H16,"-") -> 0 | G102: =IFERROR('Raw CF'!I16,"-") -> 0 | H102: =IFERROR('Raw CF'!J16,"-") -> 0 | I102: =IFERROR('Raw CF'!K16,"-") -> 0 | J102: =IFERROR('Raw CF'!L16,"-") -> 0 | ... L102: =IFERROR('Raw CF'!N16,"-") -> 0
B103: Dividends received | C103: =IFERROR('Raw CF'!E17,"-") -> 0 | D103: =IFERROR('Raw CF'!F17,"-") -> 2753 | E103: =IFERROR('Raw CF'!G17,"-") -> 1768 | F103: =IFERROR('Raw CF'!H17,"-") -> 1557 | G103: =IFERROR('Raw CF'!I17,"-") -> 1929 | H103: =IFERROR('Raw CF'!J17,"-") -> 1418 | I103: =IFERROR('Raw CF'!K17,"-") -> 1898 | J103: =IFERROR('Raw CF'!L17,"-") -> 1525 | ... L103: =IFERROR('Raw CF'!N17,"-") -> 2040
B104: Acquisition of companies | C104: =IFERROR('Raw CF'!E18,"-") -> -747 | D104: =IFERROR('Raw CF'!F18,"-") -> 0 | E104: =IFERROR('Raw CF'!G18,"-") -> 0 | F104: =IFERROR('Raw CF'!H18,"-") -> 0 | G104: =IFERROR('Raw CF'!I18,"-") -> 0 | H104: =IFERROR('Raw CF'!J18,"-") -> 0 | I104: =IFERROR('Raw CF'!K18,"-") -> 0 | J104: =IFERROR('Raw CF'!L18,"-") -> 0 | ... L104: =IFERROR('Raw CF'!N18,"-") -> 0
B105: Inter corporate deposits | C105: =IFERROR('Raw CF'!E19,"-") -> -142 | D105: =IFERROR('Raw CF'!F19,"-") -> -164 | E105: =IFERROR('Raw CF'!G19,"-") -> -130 | F105: =IFERROR('Raw CF'!H19,"-") -> -24 | G105: =IFERROR('Raw CF'!I19,"-") -> -108 | H105: =IFERROR('Raw CF'!J19,"-") -> 0 | I105: =IFERROR('Raw CF'!K19,"-") -> 0 | J105: =IFERROR('Raw CF'!L19,"-") -> 0 | ... L105: =IFERROR('Raw CF'!N19,"-") -> 0
B106: Other investing items | C106: =IFERROR('Raw CF'!E20,"-") -> -59 | D106: =IFERROR('Raw CF'!F20,"-") -> -131 | E106: =IFERROR('Raw CF'!G20,"-") -> 49 | F106: =IFERROR('Raw CF'!H20,"-") -> 1592 | G106: =IFERROR('Raw CF'!I20,"-") -> -224 | H106: =IFERROR('Raw CF'!J20,"-") -> -327 | I106: =IFERROR('Raw CF'!K20,"-") -> -3627 | J106: =IFERROR('Raw CF'!L20,"-") -> -939 | ... L106: =IFERROR('Raw CF'!N20,"-") -> -3802
B107: Cash from Investing Activity | C107: =IFERROR(SUM(C98:C106),0) -> -885 | D107: =IFERROR(SUM(D98:D106),0) -> -14664 | E107: =IFERROR(SUM(E98:E106),0) -> 4533 | F107: =IFERROR(SUM(F98:F106),0) -> -632 | G107: =IFERROR(SUM(G98:G106),0) -> -331 | H107: =IFERROR(SUM(H98:H106),0) -> -7373 | I107: =IFERROR(SUM(I98:I106),0) -> -6485 | J107: =IFERROR(SUM(J98:J106),0) -> -1071 | ... L107: =IFERROR(SUM(L98:L106),0) -> -1864
B110: FINANCING ACTIVITIES
B111: Proceeds from shares | C111: =IFERROR('Raw CF'!E22,"-") -> 0 | D111: =IFERROR('Raw CF'!F22,"-") -> 0 | E111: =IFERROR('Raw CF'!G22,"-") -> 5 | F111: =IFERROR('Raw CF'!H22,"-") -> 6 | G111: =IFERROR('Raw CF'!I22,"-") -> 6 | H111: =IFERROR('Raw CF'!J22,"-") -> 15 | I111: =IFERROR('Raw CF'!K22,"-") -> 21 | J111: =IFERROR('Raw CF'!L22,"-") -> 35 | ... L111: =IFERROR('Raw CF'!N22,"-") -> 6
B112: Repayment of borrowings | C112: =IFERROR('Raw CF'!E23,"-") -> 0 | D112: =IFERROR('Raw CF'!F23,"-") -> 0 | E112: =IFERROR('Raw CF'!G23,"-") -> 0 | F112: =IFERROR('Raw CF'!H23,"-") -> 0 | G112: =IFERROR('Raw CF'!I23,"-") -> 0 | H112: =IFERROR('Raw CF'!J23,"-") -> 0 | I112: =IFERROR('Raw CF'!K23,"-") -> 0 | J112: =IFERROR('Raw CF'!L23,"-") -> 0 | ... L112: =IFERROR('Raw CF'!N23,"-") -> -985
B113: Dividends paid | C113: =IFERROR('Raw CF'!E24,"-") -> -6813 | D113: =IFERROR('Raw CF'!F24,"-") -> -6939 | E113: =IFERROR('Raw CF'!G24,"-") -> -7464 | F113: =IFERROR('Raw CF'!H24,"-") -> -13705 | G113: =IFERROR('Raw CF'!I24,"-") -> -9548 | H113: =IFERROR('Raw CF'!J24,"-") -> -9137 | I113: =IFERROR('Raw CF'!K24,"-") -> -12731 | J113: =IFERROR('Raw CF'!L24,"-") -> -13653 | ... L113: =IFERROR('Raw CF'!N24,"-") -> -20289
B114: Financial liabilities | C114: =IFERROR('Raw CF'!E25,"-") -> 0 | D114: =IFERROR('Raw CF'!F25,"-") -> 0 | E114: =IFERROR('Raw CF'!G25,"-") -> 0 | F114: =IFERROR('Raw CF'!H25,"-") -> 0 | G114: =IFERROR('Raw CF'!I25,"-") -> -571 | H114: =IFERROR('Raw CF'!J25,"-") -> -698 | I114: =IFERROR('Raw CF'!K25,"-") -> -915 | J114: =IFERROR('Raw CF'!L25,"-") -> -1231 | ... L114: =IFERROR('Raw CF'!N25,"-") -> -2355
B115: Other financing items | C115: =IFERROR('Raw CF'!E26,"-") -> 0 | D115: =IFERROR('Raw CF'!F26,"-") -> 0 | E115: =IFERROR('Raw CF'!G26,"-") -> -13046 | F115: =IFERROR('Raw CF'!H26,"-") -> -813 | G115: =IFERROR('Raw CF'!I26,"-") -> -7478 | H115: =IFERROR('Raw CF'!J26,"-") -> 34 | I115: =IFERROR('Raw CF'!K26,"-") -> -11017 | J115: =IFERROR('Raw CF'!L26,"-") -> -11846 | ... L115: =IFERROR('Raw CF'!N26,"-") -> -538
B116: Cash from Financing Activity | C116: =IFERROR(SUM(C111:C115),0) -> -6813 | D116: =IFERROR(SUM(D111:D115),0) -> -6939 | E116: =IFERROR(SUM(E111:E115),0) -> -20505 | F116: =IFERROR(SUM(F111:F115),0) -> -14512 | G116: =IFERROR(SUM(G111:G115),0) -> -17591 | H116: =IFERROR(SUM(H111:H115),0) -> -9786 | I116: =IFERROR(SUM(I111:I115),0) -> -24642 | J116: =IFERROR(SUM(J111:J115),0) -> -26695 | ... L116: =IFERROR(SUM(L111:L115),0) -> -24161
B119: Net Cash Flow | C119: =IFERROR(SUM(C94,C107,C116),0) -> 2330 | D119: =IFERROR(SUM(D94,D107,D116),0) -> -10072 | E119: =IFERROR(SUM(E94,E107,E116),0) -> -2754 | F119: =IFERROR(SUM(F94,F107,F116),0) -> -303 | G119: =IFERROR(SUM(G94,G107,G116),0) -> -919 | H119: =IFERROR(SUM(H94,H107,H116),0) -> 6065 | I119: =IFERROR(SUM(I94,I107,I116),0) -> -7242 | J119: =IFERROR(SUM(J94,J107,J116),0) -> -5299 | ... L119: =IFERROR(SUM(L94,L107,L116),0) -> 9669

Sheet Ratio Analysis
B4: ='Data Sheet'!$B$1 -> INFOSYS LTD
B5: ( NSE: INFY | BSE: 500209)
B6: 1250
B7: 52 Week (High 1728 & Low 1215)
B10: ="Ratio Analysis" -> Ratio Analysis
B11: Particulars | C11: ='Data Sheet'!B16 -> 42460 | D11: ='Data Sheet'!C16 -> 42825 | E11: ='Data Sheet'!D16 -> 43190 | F11: ='Data Sheet'!E16 -> 43555 | G11: ='Data Sheet'!F16 -> 43921 | H11: ='Data Sheet'!G16 -> 44286 | I11: ='Data Sheet'!H16 -> 44651 | J11: ='Data Sheet'!I16 -> 45016 | ... L11: ='Data Sheet'!K16 -> 45747 | M11: Trend | N11: Mean | O11: Median
B13: Sales Growth | C13: - | D13: ='Historical FS'!D15 -> 0.09677936 | E13: ='Historical FS'!E15 -> 0.029758776 | F13: ='Historical FS'!F15 -> 0.1723292 | G13: ='Historical FS'!G15 -> 0.098167523 | H13: ='Historical FS'!H15 -> 0.10662951 | I13: ='Historical FS'!I15 -> 0.21069552 | J13: ='Historical FS'!J15 -> 0.20655864 | K13: ='Historical FS'!K15 -> 0.047033734 | L13: ='Historical FS'!L15 -> 0.060649444 | N13: =IFERROR(AVERAGE(D13:L13),"-") -> 0.11428908 | O13: =IFERROR(MEDIAN(C13:L13),"-") -> 0.098167523
B14: EBITDA Growth | C14: - | D14: =IFERROR('Historical FS'!D26/'Historical FS'!C26-1,"-") -> 0.089290942 | E14: =IFERROR('Historical FS'!E26/'Historical FS'!D26-1,"-") -> 0.01171791 | F14: =IFERROR('Historical FS'!F26/'Historical FS'!E26-1,"-") -> 0.071618319 | G14: =IFERROR('Historical FS'!G26/'Historical FS'!F26-1,"-") -> 0.10396629 | H14: =IFERROR('Historical FS'!H26/'Historical FS'!G26-1,"-") -> 0.25248125 | I14: =IFERROR('Historical FS'!I26/'Historical FS'!H26-1,"-") -> 0.12915486 | J14: =IFERROR('Historical FS'!J26/'Historical FS'!I26-1,"-") -> 0.11555683 | K14: =IFERROR('Historical FS'!K26/'Historical FS'!J26-1,"-") -> 0.03686308 | L14: =IFERROR('Historical FS'!L26/'Historical FS'!K26-1,"-") -> 0.077172272 | N14: =IFERROR(AVERAGE(D14:L14),"-") -> 0.098646861 | O14: =IFERROR(MEDIAN(C14:L14),"-") -> 0.089290942
B15: EBIT Growth | C15: - | D15: =IFERROR('Historical FS'!D32/'Historical FS'!C32-1,"-") -> 0.082010243 | E15: =IFERROR('Historical FS'!E32/'Historical FS'!D32-1,"-") -> 0.0034317496 | F15: =IFERROR('Historical FS'!F32/'Historical FS'!E32-1,"-") -> 0.070758889 | G15: =IFERROR('Historical FS'!G32/'Historical FS'!F32-1,"-") -> 0.066908971 | H15: =IFERROR('Historical FS'!H32/'Historical FS'!G32-1,"-") -> 0.2708785 | I15: =IFERROR('Historical FS'!I32/'Historical FS'!H32-1,"-") -> 0.13780359 | J15: =IFERROR('Historical FS'!J32/'Historical FS'!I32-1,"-") -> 0.10315902 | K15: =IFERROR('Historical FS'!K32/'Historical FS'!J32-1,"-") -> 0.027244782 | L15: =IFERROR('Historical FS'!L32/'Historical FS'!K32-1,"-") -> 0.084322928 | N15: =IFERROR(AVERAGE(D15:L15),"-") -> 0.09405763 | O15: =IFERROR(MEDIAN(C15:L15),"-") -> 0.082010243
B16: Net Profit Growth | C16: - | D16: =IFERROR('Historical FS'!D47/'Historical FS'!C47-1,"-") -> 0.064052191 | E16: =IFERROR('Historical FS'!E47/'Historical FS'!D47-1,"-") -> 0.11677001 | F16: =IFERROR('Historical FS'!F47/'Historical FS'!E47-1,"-") -> -0.038617506 | G16: =IFERROR('Historical FS'!G47/'Historical FS'!F47-1,"-") -> 0.079753407 | H16: =IFERROR('Historical FS'!H47/'Historical FS'!G47-1,"-") -> 0.16731775 | I16: =IFERROR('Historical FS'!I47/'Historical FS'!H47-1,"-") -> 0.14019461 | J16: =IFERROR('Historical FS'!J47/'Historical FS'!I47-1,"-") -> 0.088593877 | K16: =IFERROR('Historical FS'!K47/'Historical FS'!J47-1,"-") -> 0.088767214 | L16: =IFERROR('Historical FS'!L47/'Historical FS'!K47-1,"-") -> 0.019125267 | N16: =IFERROR(AVERAGE(D16:L16),"-") -> 0.080661869 | O16: =IFERROR(MEDIAN(C16:L16),"-") -> 0.088593877
B17: Dividend Growth | C17: - | D17: =IFERROR('Historical FS'!D55/'Historical FS'!C55-1,"-") -> 0.06185567 | E17: =IFERROR('Historical FS'!E55/'Historical FS'!D55-1,"-") -> 0.68963897 | F17: =IFERROR('Historical FS'!F55/'Historical FS'!E55-1,"-") -> -0.02583858 | G17: =IFERROR('Historical FS'!G55/'Historical FS'!F55-1,"-") -> -0.17390646 | H17: =IFERROR('Historical FS'!H55/'Historical FS'!G55-1,"-") -> 0.54369512 | I17: =IFERROR('Historical FS'!I55/'Historical FS'!H55-1,"-") -> 0.14865158 | J17: =IFERROR('Historical FS'!J55/'Historical FS'!I55-1,"-") -> 0.096761529 | K17: =IFERROR('Historical FS'!K55/'Historical FS'!J55-1,"-") -> 0.35349861 | L17: =IFERROR('Historical FS'!L55/'Historical FS'!K55-1,"-") -> -0.064855345 | N17: =IFERROR(AVERAGE(D17:L17),"-") -> 0.18105568 | O17: =IFERROR(MEDIAN(C17:L17),"-") -> 0.096761529
B19: Gross Margin | C19: ='Historical FS'!C21 -> 0.35151583 | D19: ='Historical FS'!D21 -> 0.34862158 | E19: ='Historical FS'!E21 -> 0.34212019 | F19: ='Historical FS'!F21 -> 0.32934986 | G19: ='Historical FS'!G21 -> 0.31479993 | H19: ='Historical FS'!H21 -> 0.31831754 | I19: ='Historical FS'!I21 -> 0.30271043 | J19: ='Historical FS'!J21 -> 0.28539794 | ... L19: ='Historical FS'!L21 -> 0.28471072 | N19: =IFERROR(AVERAGE(C19:L19),"-") -> 0.31615292 | O19: =IFERROR(MEDIAN(C19:L19),"-") -> 0.31655873
B20: EBITDA Margin | C20: ='Historical FS'!C27 -> 0.2735222 | D20: ='Historical FS'!D27 -> 0.27165469 | E20: ='Historical FS'!E27 -> 0.26689544 | F20: ='Historical FS'!F27 -> 0.24396734 | G20: ='Historical FS'!G27 -> 0.24525559 | H20: ='Historical FS'!H27 -> 0.27757982 | I20: ='Historical FS'!I27 -> 0.25888475 | J20: ='Historical FS'!J27 -> 0.23935898 | ... L20: ='Historical FS'!L27 -> 0.24072642 | N20: =IFERROR(AVERAGE(C20:L20),"-") -> 0.25548792 | O20: =IFERROR(MEDIAN(C20:L20),"-") -> 0.25207017
B21: EBIT Margin | C21: ='Historical FS'!C33 -> 0.25015615 | D21: ='Historical FS'!D33 -> 0.24678757 | E21: ='Historical FS'!E33 -> 0.24047815 | F21: ='Historical FS'!F33 -> 0.21964318 | G21: ='Historical FS'!G33 -> 0.2133912 | H21: ='Historical FS'!H33 -> 0.2450633 | I21: ='Historical FS'!I33 -> 0.23030886 | J21: ='Historical FS'!J33 -> 0.21057186 | ... L21: ='Historical FS'!L33 -> 0.21120314 | N21: =IFERROR(AVERAGE(C21:L21),"-") -> 0.22741955 | O21: =IFERROR(MEDIAN(C21:L21),"-") -> 0.22497602
B22: EBT Margin | C22: ='Historical FS'!C42 -> 0.30012332 | D22: ='Historical FS'!D42 -> 0.29132352 | E22: ='Historical FS'!E42 -> 0.28742804 | F22: ='Historical FS'!F42 -> 0.25450257 | G22: ='Historical FS'!G42 -> 0.24239187 | H22: ='Historical FS'!H42 -> 0.26502906 | I22: ='Historical FS'!I42 -> 0.24753167 | J22: ='Historical FS'!J42 -> 0.22704014 | ... L22: ='Historical FS'!L42 -> 0.23073808 | N22: =IFERROR(AVERAGE(C22:L22),"-") -> 0.25802984 | O22: =IFERROR(MEDIAN(C22:L22),"-") -> 0.25101712
B23: Net Profit Margin | C23: ='Historical FS'!C48 -> 0.21602793 | D23: ='Historical FS'!D48 -> 0.2095818 | E23: ='Historical FS'!E48 -> 0.22729077 | F23: ='Historical FS'!F48 -> 0.1863925 | G23: ='Historical FS'!G48 -> 0.18326706 | H23: ='Historical FS'!H48 -> 0.19331754 | I23: ='Historical FS'!I48 -> 0.18206033 | J23: ='Historical FS'!J48 -> 0.16426036 | ... L23: ='Historical FS'!L48 -> 0.1641205 | N23: =IFERROR(AVERAGE(C23:L23),"-") -> 0.18971264 | O23: =IFERROR(MEDIAN(C23:L23),"-") -> 0.18482978
B25: Sales Expense % Sales | C25: ='Historical FS'!C24 -> 0.077993626 | D25: ='Historical FS'!D24 -> 0.076966883 | E25: ='Historical FS'!E24 -> 0.075224753 | F25: ='Historical FS'!F24 -> 0.085382522 | G25: ='Historical FS'!G24 -> 0.069544338 | H25: ='Historical FS'!H24 -> 0.040737718 | I25: ='Historical FS'!I24 -> 0.043825684 | J25: ='Historical FS'!J24 -> 0.04603896 | ... L25: ='Historical FS'!L24 -> 0.043984294 | N25: =IFERROR(AVERAGE(C25:L25),"-") -> 0.060665004 | O25: =IFERROR(MEDIAN(C25:L25),"-") -> 0.058247799
B26: Depreciation % Sales | C26: ='Historical FS'!C30 -> 0.023366058 | D26: ='Historical FS'!D30 -> 0.024867122 | E26: ='Historical FS'!E30 -> 0.026417288 | F26: ='Historical FS'!F30 -> 0.024324161 | G26: ='Historical FS'!G30 -> 0.031864392 | H26: ='Historical FS'!H30 -> 0.032516522 | I26: ='Historical FS'!I30 -> 0.028575891 | J26: ='Historical FS'!J30 -> 0.028787125 | ... L26: ='Historical FS'!L30 -> 0.029523284 | N26: =IFERROR(AVERAGE(C26:L26),"-") -> 0.02806837 | O26: =IFERROR(MEDIAN(C26:L26),"-") -> 0.028681508
B27: Operating Income % sales | C27: ='Historical FS'!C27 -> 0.2735222 | D27: ='Historical FS'!D27 -> 0.27165469 | E27: ='Historical FS'!E27 -> 0.26689544 | F27: ='Historical FS'!F27 -> 0.24396734 | G27: ='Historical FS'!G27 -> 0.24525559 | H27: ='Historical FS'!H27 -> 0.27757982 | I27: ='Historical FS'!I27 -> 0.25888475 | J27: ='Historical FS'!J27 -> 0.23935898 | ... L27: ='Historical FS'!L27 -> 0.24072642 | N27: =IFERROR(AVERAGE(C27:L27),"-") -> 0.25548792 | O27: =IFERROR(MEDIAN(C27:L27),"-") -> 0.25207017
B29: Return on Capital Employed | C29: =IFERROR('Historical FS'!C26/SUM('Historical FS'!C64:C66),"-") -> 0.27660987 | D29: =IFERROR('Historical FS'!D26/SUM('Historical FS'!D64:D66),"-") -> 0.26969354 | E29: =IFERROR('Historical FS'!E26/SUM('Historical FS'!E64:E66),"-") -> 0.28991267 | F29: =IFERROR('Historical FS'!F26/SUM('Historical FS'!F64:F66),"-") -> 0.31055614 | G29: =IFERROR('Historical FS'!G26/SUM('Historical FS'!G64:G66),"-") -> 0.31772327 | H29: =IFERROR('Historical FS'!H26/SUM('Historical FS'!H64:H66),"-") -> 0.34145894 | I29: =IFERROR('Historical FS'!I26/SUM('Historical FS'!I64:I66),"-") -> 0.38962437 | J29: =IFERROR('Historical FS'!J26/SUM('Historical FS'!J64:J66),"-") -> 0.41968318 | ... L29: =IFERROR('Historical FS'!L26/SUM('Historical FS'!L64:L66),"-") -> 0.37710606 | N29: =IFERROR(AVERAGE(C29:L29),"-") -> 0.3369927 | O29: =IFERROR(MEDIAN(C29:L29),"-") -> 0.3295911
B30: Retained Earning % | C30: ='Historical FS'!C58 -> 0.58867225 | D30: ='Historical FS'!D58 -> 0.58952135 | E30: ='Historical FS'!E58 -> 0.40947034 | F30: ='Historical FS'!F58 -> 0.40152498 | G30: ='Historical FS'!G58 -> 0.55363904 | H30: ='Historical FS'!H58 -> 0.4094836 | I30: ='Historical FS'!I58 -> 0.41264337 | J30: ='Historical FS'!J58 -> 0.41640949 | ... L30: ='Historical FS'!L58 -> 0.33354019 | N30: =IFERROR(AVERAGE(C30:L30),"-") -> 0.43890131 | O30: =IFERROR(MEDIAN(C30:L30),"-") -> 0.41106348
B31: Return on Equity % | C31: =IFERROR('Historical FS'!C47/SUM('Historical FS'!C64:C65),"-") -> 0.21846657 | D31: =IFERROR('Historical FS'!D47/SUM('Historical FS'!D64:D65),"-") -> 0.20806877 | E31: =IFERROR('Historical FS'!E47/SUM('Historical FS'!E64:E65),"-") -> 0.24689247 | F31: =IFERROR('Historical FS'!F47/SUM('Historical FS'!F64:F65),"-") -> 0.23726674 | G31: =IFERROR('Historical FS'!G47/SUM('Historical FS'!G64:G65),"-") -> 0.2542246 | H31: =IFERROR('Historical FS'!H47/SUM('Historical FS'!H64:H65),"-") -> 0.25439091 | I31: =IFERROR('Historical FS'!I47/SUM('Historical FS'!I64:I65),"-") -> 0.29390843 | J31: =IFERROR('Historical FS'!J47/SUM('Historical FS'!J64:J65),"-") -> 0.31970507 | ... L31: =IFERROR('Historical FS'!L47/SUM('Historical FS'!L64:L65),"-") -> 0.2791751 | N31: =IFERROR(AVERAGE(C31:L31),"-") -> 0.26099787 | O31: =IFERROR(MEDIAN(C31:L31),"-") -> 0.25430775
B32: Self Sustained Growth Rate | C32: =IFERROR(C31*C30,"-") -> 0.12860521 | D32: =IFERROR(D31*D30,"-") -> 0.12266098 | E32: =IFERROR(E31*E30,"-") -> 0.10109514 | F32: =IFERROR(F31*F30,"-") -> 0.095268523 | G32: =IFERROR(G31*G30,"-") -> 0.14074866 | H32: =IFERROR(H31*H30,"-") -> 0.1041689 | I32: =IFERROR(I31*I30,"-") -> 0.12127936 | J32: =IFERROR(J31*J30,"-") -> 0.13312822 | ... L32: =IFERROR(L31*L30,"-") -> 0.093116116 | N32: =IFERROR(AVERAGE(C32:L32),"-") -> 0.11217226 | O32: =IFERROR(MEDIAN(C32:L32),"-") -> 0.11272413
B33: Interest Coverage Ratio | C33: =IFERROR('Historical FS'!C26/'Historical FS'!C38,"-") -> - | D33: =IFERROR('Historical FS'!D26/'Historical FS'!D38,"-") -> - | E33: =IFERROR('Historical FS'!E26/'Historical FS'!E38,"-") -> - | F33: =IFERROR('Historical FS'!F26/'Historical FS'!F38,"-") -> - | G33: =IFERROR('Historical FS'!G26/'Historical FS'!G38,"-") -> 130.98235 | H33: =IFERROR('Historical FS'!H26/'Historical FS'!H38,"-") -> 143.02051 | I33: =IFERROR('Historical FS'!I26/'Historical FS'!I38,"-") -> 157.455 | J33: =IFERROR('Historical FS'!J26/'Historical FS'!J38,"-") -> 123.69718 | ... L33: =IFERROR('Historical FS'!L26/'Historical FS'!L38,"-") -> 94.317308 | N33: =IFERROR(AVERAGE(C33:L33),"-") -> 121.16206 | O33: =IFERROR(MEDIAN(C33:L33),"-") -> 127.33977
B35: Debtor Turnover ratio | C35: =IFERROR('Historical FS'!C14/'Historical FS'!C75,"-") -> 5.5111209 | D35: =IFERROR('Historical FS'!D14/'Historical FS'!D75,"-") -> 5.557864 | E35: =IFERROR('Historical FS'!E14/'Historical FS'!E75,"-") -> 5.3661543 | F35: =IFERROR('Historical FS'!F14/'Historical FS'!F75,"-") -> 5.5759763 | G35: =IFERROR('Historical FS'!G14/'Historical FS'!G75,"-") -> 4.9110726 | H35: =IFERROR('Historical FS'!H14/'Historical FS'!H75,"-") -> 5.207422 | I35: =IFERROR('Historical FS'!I14/'Historical FS'!I75,"-") -> 5.3591065 | J35: =IFERROR('Historical FS'!J14/'Historical FS'!J75,"-") -> 5.7727738 | ... L35: =IFERROR('Historical FS'!L14/'Historical FS'!L75,"-") -> 5.2310803 | N35: =IFERROR(AVERAGE(C35:L35),"-") -> 5.3582161 | O35: =IFERROR(MEDIAN(C35:L35),"-") -> 5.3626304
B36: Creditor turnover ratio | C36: =IFERROR('Historical FS'!C14/'Historical FS'!C67,"-") -> 4.6758275 | D36: =IFERROR('Historical FS'!D14/'Historical FS'!D67,"-") -> 4.8343922 | E36: =IFERROR('Historical FS'!E14/'Historical FS'!E67,"-") -> 4.8885346 | F36: =IFERROR('Historical FS'!F14/'Historical FS'!F67,"-") -> 4.3244586 | G36: =IFERROR('Historical FS'!G14/'Historical FS'!G67,"-") -> 4.1806419 | H36: =IFERROR('Historical FS'!H14/'Historical FS'!H67,"-") -> 3.8889878 | I36: =IFERROR('Historical FS'!I14/'Historical FS'!I67,"-") -> 3.3878568 | J36: =IFERROR('Historical FS'!J14/'Historical FS'!J67,"-") -> 3.5893128 | ... L36: =IFERROR('Historical FS'!L14/'Historical FS'!L67,"-") -> 3.7254857 | N36: =IFERROR(AVERAGE(C36:L36),"-") -> 4.1254089 | O36: =IFERROR(MEDIAN(C36:L36),"-") -> 4.0348149
B37: Inventory turnover ratio | C37: =IFERROR('Historical FS'!C14/'Historical FS'!C76,"-") -> - | D37: =IFERROR('Historical FS'!D14/'Historical FS'!D76,"-") -> - | E37: =IFERROR('Historical FS'!E14/'Historical FS'!E76,"-") -> - | F37: =IFERROR('Historical FS'!F14/'Historical FS'!F76,"-") -> - | G37: =IFERROR('Historical FS'!G14/'Historical FS'!G76,"-") -> - | H37: =IFERROR('Historical FS'!H14/'Historical FS'!H76,"-") -> - | I37: =IFERROR('Historical FS'!I14/'Historical FS'!I76,"-") -> - | J37: =IFERROR('Historical FS'!J14/'Historical FS'!J76,"-") -> - | ... L37: =IFERROR('Historical FS'!L14/'Historical FS'!L76,"-") -> - | N37: =IFERROR(AVERAGE(C37:L37),"-") -> - | O37: =IFERROR(MEDIAN(C37:L37),"-") -> -
B38: Fixed Assets Turnover ratio | C38: =IFERROR('Historical FS'!C14/'Historical FS'!C70,"-") -> 4.6646496 | D38: =IFERROR('Historical FS'!D14/'Historical FS'!D70,"-") -> 4.8299598 | E38: =IFERROR('Historical FS'!E14/'Historical FS'!E70,"-") -> 5.6085573 | F38: =IFERROR('Historical FS'!F14/'Historical FS'!F70,"-") -> 5.2625716 | G38: =IFERROR('Historical FS'!G14/'Historical FS'!G70,"-") -> 3.8165118 | H38: =IFERROR('Historical FS'!H14/'Historical FS'!H70,"-") -> 3.939306 | I38: =IFERROR('Historical FS'!I14/'Historical FS'!I70,"-") -> 4.7147674 | J38: =IFERROR('Historical FS'!J14/'Historical FS'!J70,"-") -> 5.0219675 | ... L38: =IFERROR('Historical FS'!L14/'Historical FS'!L70,"-") -> 5.2643648 | N38: =IFERROR(AVERAGE(C38:L38),"-") -> 4.8685975 | O38: =IFERROR(MEDIAN(C38:L38),"-") -> 4.9259636
B39: Capital turnover ratio | C39: =IFERROR('Historical FS'!C14/SUM('Historical FS'!C64:C65),"-") -> 1.0112885 | D39: =IFERROR('Historical FS'!D14/SUM('Historical FS'!D64:D65),"-") -> 0.99278073 | E39: =IFERROR('Historical FS'!E14/SUM('Historical FS'!E64:E65),"-") -> 1.0862406 | F39: =IFERROR('Historical FS'!F14/SUM('Historical FS'!F64:F65),"-") -> 1.2729414 | G39: =IFERROR('Historical FS'!G14/SUM('Historical FS'!G64:G65),"-") -> 1.3871811 | H39: =IFERROR('Historical FS'!H14/SUM('Historical FS'!H64:H65),"-") -> 1.3159225 | I39: =IFERROR('Historical FS'!I14/SUM('Historical FS'!I64:I65),"-") -> 1.6143464 | J39: =IFERROR('Historical FS'!J14/SUM('Historical FS'!J64:J65),"-") -> 1.9463312 | ... L39: =IFERROR('Historical FS'!L14/SUM('Historical FS'!L64:L65),"-") -> 1.7010374 | N39: =IFERROR(AVERAGE(C39:L39),"-") -> 1.4072021 | O39: =IFERROR(MEDIAN(C39:L39),"-") -> 1.3515518
B41: Debtor Days | C41: =IFERROR(365/C35,"-") -> 66.229721 | D41: =IFERROR(365/D35,"-") -> 65.672712 | E41: =IFERROR(365/E35,"-") -> 68.018916 | F41: =IFERROR(365/F35,"-") -> 65.459389 | G41: =IFERROR(365/G35,"-") -> 74.321849 | H41: =IFERROR(365/H35,"-") -> 70.092265 | I41: =IFERROR(365/I35,"-") -> 68.108368 | J41: =IFERROR(365/J35,"-") -> 63.227837 | ... L41: =IFERROR(365/L35,"-") -> 69.775262 | N41: =IFERROR(AVERAGE(C41:L41),"-") -> 68.262133 | O41: =IFERROR(MEDIAN(C41:L41),"-") -> 68.063642
B42: Creditor Days | C42: =IFERROR(365/C36,"-") -> 78.06105 | D42: =IFERROR(365/D36,"-") -> 75.500701 | E42: =IFERROR(365/E36,"-") -> 74.664502 | F42: =IFERROR(365/F36,"-") -> 84.403629 | G42: =IFERROR(365/G36,"-") -> 87.307167 | H42: =IFERROR(365/H36,"-") -> 93.854756 | I42: =IFERROR(365/I36,"-") -> 107.73773 | J42: =IFERROR(365/J36,"-") -> 101.69078 | ... L42: =IFERROR(365/L36,"-") -> 97.973802 | N42: =IFERROR(AVERAGE(C42:L42),"-") -> 89.830496 | O42: =IFERROR(MEDIAN(C42:L42),"-") -> 90.580961
B43: Inventory Days | C43: =IFERROR(365/C37,"-") -> - | D43: =IFERROR(365/D37,"-") -> - | E43: =IFERROR(365/E37,"-") -> - | F43: =IFERROR(365/F37,"-") -> - | G43: =IFERROR(365/G37,"-") -> - | H43: =IFERROR(365/H37,"-") -> - | I43: =IFERROR(365/I37,"-") -> - | J43: =IFERROR(365/J37,"-") -> - | ... L43: =IFERROR(365/L37,"-") -> - | N43: =IFERROR(AVERAGE(C43:L43),"-") -> - | O43: =IFERROR(MEDIAN(C43:L43),"-") -> -
B44: Cash Conversion Cycle (CCC) | C44: =IFERROR(SUM(C41,C43)-C42,"-") -> -11.831329 | D44: =IFERROR(SUM(D41,D43)-D42,"-") -> -9.827989 | E44: =IFERROR(SUM(E41,E43)-E42,"-") -> -6.6455858 | F44: =IFERROR(SUM(F41,F43)-F42,"-") -> -18.944239 | G44: =IFERROR(SUM(G41,G43)-G42,"-") -> -12.985318 | H44: =IFERROR(SUM(H41,H43)-H42,"-") -> -23.762491 | I44: =IFERROR(SUM(I41,I43)-I42,"-") -> -39.62936 | J44: =IFERROR(SUM(J41,J43)-J42,"-") -> -38.462938 | ... L44: =IFERROR(SUM(L41,L43)-L42,"-") -> -28.19854 | N44: =IFERROR(AVERAGE(C44:L44),"-") -> -21.568364 | O44: =IFERROR(MEDIAN(C44:L44),"-") -> -21.353365
B46: CFO / Sales | C46: =IFERROR('Historical FS'!C94/'Historical FS'!C14,"-") -> 0.16059961 | D46: =IFERROR('Historical FS'!D94/'Historical FS'!D14,"-") -> 0.16837509 | E46: =IFERROR('Historical FS'!E94/'Historical FS'!E14,"-") -> 0.18743087 | F46: =IFERROR('Historical FS'!F94/'Historical FS'!F14,"-") -> 0.17951013 | G46: =IFERROR('Historical FS'!G94/'Historical FS'!G14,"-") -> 0.18727627 | H46: =IFERROR('Historical FS'!H94/'Historical FS'!H14,"-") -> 0.23114898 | I46: =IFERROR('Historical FS'!I94/'Historical FS'!I14,"-") -> 0.19635649 | J46: =IFERROR('Historical FS'!J94/'Historical FS'!J14,"-") -> 0.15307937 | ... L46: =IFERROR('Historical FS'!L94/'Historical FS'!L14,"-") -> 0.21899503 | N46: =IFERROR(AVERAGE(C46:L46),"-") -> 0.18468247 | O46: =IFERROR(MEDIAN(C46:L46),"-") -> 0.1833932
B47: CFO / Total Assets | C47: =IFERROR('Historical FS'!C94/'Historical FS'!C81,"-") -> 0.13353218 | D47: =IFERROR('Historical FS'!D94/'Historical FS'!D81,"-") -> 0.13868043 | E47: =IFERROR('Historical FS'!E94/'Historical FS'!E81,"-") -> 0.16658055 | F47: =IFERROR('Historical FS'!F94/'Historical FS'!F81,"-") -> 0.17653986 | G47: =IFERROR('Historical FS'!G94/'Historical FS'!G81,"-") -> 0.18521786 | H47: =IFERROR('Historical FS'!H94/'Historical FS'!H81,"-") -> 0.21601511 | I47: =IFERROR('Historical FS'!I94/'Historical FS'!I81,"-") -> 0.20461925 | J47: =IFERROR('Historical FS'!J94/'Historical FS'!J81,"-") -> 0.18031879 | ... L47: =IFERROR('Historical FS'!L94/'Historical FS'!L81,"-") -> 0.2415102 | N47: =IFERROR(AVERAGE(C47:L47),"-") -> 0.18265466 | O47: =IFERROR(MEDIAN(C47:L47),"-") -> 0.18192556
B48: CFO / Total Debt | C48: =IFERROR('Historical FS'!C94/SUM('Historical FS'!C66+'Historical FS'!C67),"-") -> 0.75093605 | D48: =IFERROR('Historical FS'!D94/SUM('Historical FS'!D66+'Historical FS'!D67),"-") -> 0.81399125 | E48: =IFERROR('Historical FS'!E94/SUM('Historical FS'!E66+'Historical FS'!E67),"-") -> 0.9162623 | F48: =IFERROR('Historical FS'!F94/SUM('Historical FS'!F66+'Historical FS'!F67),"-") -> 0.77628413 | G48: =IFERROR('Historical FS'!G94/SUM('Historical FS'!G66+'Historical FS'!G67),"-") -> 0.64527514 | H48: =IFERROR('Historical FS'!H94/SUM('Historical FS'!H66+'Historical FS'!H67),"-") -> 0.74531451 | I48: =IFERROR('Historical FS'!I94/SUM('Historical FS'!I66+'Historical FS'!I67),"-") -> 0.57722516 | J48: =IFERROR('Historical FS'!J94/SUM('Historical FS'!J66+'Historical FS'!J67),"-") -> 0.45674846 | ... L48: =IFERROR('Historical FS'!L94/SUM('Historical FS'!L66+'Historical FS'!L67),"-") -> 0.68672682 | N48: =IFERROR(AVERAGE(C48:L48),"-") -> 0.68807044 | O48: =IFERROR(MEDIAN(C48:L48),"-") -> 0.71602066

Sheet Common size 
B4: ='Data Sheet'!$B$1 -> INFOSYS LTD
B5: ( NSE: INFY | BSE: 500209)
B6: 1250
B7: 52 Week (High 1728 & Low 1215)
B10: ="Common Size Statements" -> Common Size Statements
B11: Particulars | C11: ='Data Sheet'!B16 -> 42460 | D11: ='Data Sheet'!C16 -> 42825 | E11: ='Data Sheet'!D16 -> 43190 | F11: ='Data Sheet'!E16 -> 43555 | G11: ='Data Sheet'!F16 -> 43921 | H11: ='Data Sheet'!G16 -> 44286 | I11: ='Data Sheet'!H16 -> 44651 | J11: ='Data Sheet'!I16 -> 45016 | ... L11: ='Data Sheet'!K16 -> 45747
A13: # | B13: Income Statement
B14: ='Data Sheet'!A17 -> Sales | C14: =IFERROR('Data Sheet'!B17/'Data Sheet'!B$17,"-") -> 1 | D14: =IFERROR('Data Sheet'!C17/'Data Sheet'!C$17,"-") -> 1 | E14: =IFERROR('Data Sheet'!D17/'Data Sheet'!D$17,"-") -> 1 | F14: =IFERROR('Data Sheet'!E17/'Data Sheet'!E$17,"-") -> 1 | G14: =IFERROR('Data Sheet'!F17/'Data Sheet'!F$17,"-") -> 1 | H14: =IFERROR('Data Sheet'!G17/'Data Sheet'!G$17,"-") -> 1 | I14: =IFERROR('Data Sheet'!H17/'Data Sheet'!H$17,"-") -> 1 | J14: =IFERROR('Data Sheet'!I17/'Data Sheet'!I$17,"-") -> 1 | ... L14: =IFERROR('Data Sheet'!K17/'Data Sheet'!K$17,"-") -> 1
B15: ='Data Sheet'!A18 -> Raw Material Cost | C15: =IFERROR('Data Sheet'!B18/'Data Sheet'!B$17,"-") -> 0 | D15: =IFERROR('Data Sheet'!C18/'Data Sheet'!C$17,"-") -> 0 | E15: =IFERROR('Data Sheet'!D18/'Data Sheet'!D$17,"-") -> 0 | F15: =IFERROR('Data Sheet'!E18/'Data Sheet'!E$17,"-") -> 0 | G15: =IFERROR('Data Sheet'!F18/'Data Sheet'!F$17,"-") -> 0 | H15: =IFERROR('Data Sheet'!G18/'Data Sheet'!G$17,"-") -> 0 | I15: =IFERROR('Data Sheet'!H18/'Data Sheet'!H$17,"-") -> 0 | J15: =IFERROR('Data Sheet'!I18/'Data Sheet'!I$17,"-") -> 0 | ... L15: =IFERROR('Data Sheet'!K18/'Data Sheet'!K$17,"-") -> 0
B16: ='Data Sheet'!A19 -> Change in Inventory | C16: =IFERROR('Data Sheet'!B19/'Data Sheet'!B$17,"-") -> 0 | D16: =IFERROR('Data Sheet'!C19/'Data Sheet'!C$17,"-") -> 0 | E16: =IFERROR('Data Sheet'!D19/'Data Sheet'!D$17,"-") -> 0 | F16: =IFERROR('Data Sheet'!E19/'Data Sheet'!E$17,"-") -> 0 | G16: =IFERROR('Data Sheet'!F19/'Data Sheet'!F$17,"-") -> 0 | H16: =IFERROR('Data Sheet'!G19/'Data Sheet'!G$17,"-") -> 0 | I16: =IFERROR('Data Sheet'!H19/'Data Sheet'!H$17,"-") -> 0 | J16: =IFERROR('Data Sheet'!I19/'Data Sheet'!I$17,"-") -> 0 | ... L16: =IFERROR('Data Sheet'!K19/'Data Sheet'!K$17,"-") -> 0
B17: ='Data Sheet'!A20 -> Power and Fuel | C17: =IFERROR('Data Sheet'!B20/'Data Sheet'!B$17,"-") -> 0.0034752807 | D17: =IFERROR('Data Sheet'!C20/'Data Sheet'!C$17,"-") -> 0.0033292448 | E17: =IFERROR('Data Sheet'!D20/'Data Sheet'!D$17,"-") -> 0.0029352542 | F17: =IFERROR('Data Sheet'!E20/'Data Sheet'!E$17,"-") -> 0.0026731176 | G17: =IFERROR('Data Sheet'!F20/'Data Sheet'!F$17,"-") -> 0.0025222764 | H17: =IFERROR('Data Sheet'!G20/'Data Sheet'!G$17,"-") -> 0.0014232821 | I17: =IFERROR('Data Sheet'!H20/'Data Sheet'!H$17,"-") -> 0.0010851604 | J17: =IFERROR('Data Sheet'!I20/'Data Sheet'!I$17,"-") -> 0.0011991797 | ... L17: =IFERROR('Data Sheet'!K20/'Data Sheet'!K$17,"-") -> 0.0013620468
B18: ='Data Sheet'!A21 -> Other Mfr. Exp | C18: =IFERROR('Data Sheet'!B21/'Data Sheet'!B$17,"-") -> 0.093848593 | D18: =IFERROR('Data Sheet'!C21/'Data Sheet'!C$17,"-") -> 0.098008294 | E18: =IFERROR('Data Sheet'!D21/'Data Sheet'!D$17,"-") -> 0.10331528 | F18: =IFERROR('Data Sheet'!E21/'Data Sheet'!E$17,"-") -> 0.11977018 | G18: =IFERROR('Data Sheet'!F21/'Data Sheet'!F$17,"-") -> 0.12210461 | H18: =IFERROR('Data Sheet'!G21/'Data Sheet'!G$17,"-") -> 0.12739868 | I18: =IFERROR('Data Sheet'!H21/'Data Sheet'!H$17,"-") -> 0.17009068 | J18: =IFERROR('Data Sheet'!I21/'Data Sheet'!I$17,"-") -> 0.1794 | ... L18: =IFERROR('Data Sheet'!K21/'Data Sheet'!K$17,"-") -> 0.18648383
B19: ='Data Sheet'!A22 -> Employee Cost | C19: =IFERROR('Data Sheet'!B22/'Data Sheet'!B$17,"-") -> 0.5511603 | D19: =IFERROR('Data Sheet'!C22/'Data Sheet'!C$17,"-") -> 0.55004089 | E19: =IFERROR('Data Sheet'!D22/'Data Sheet'!D$17,"-") -> 0.55162928 | F19: =IFERROR('Data Sheet'!E22/'Data Sheet'!E$17,"-") -> 0.54820683 | G19: =IFERROR('Data Sheet'!F22/'Data Sheet'!F$17,"-") -> 0.56057318 | H19: =IFERROR('Data Sheet'!G22/'Data Sheet'!G$17,"-") -> 0.5528605 | I19: =IFERROR('Data Sheet'!H22/'Data Sheet'!H$17,"-") -> 0.52611373 | J19: =IFERROR('Data Sheet'!I22/'Data Sheet'!I$17,"-") -> 0.53400288 | ... L19: =IFERROR('Data Sheet'!K22/'Data Sheet'!K$17,"-") -> 0.5274434
B20: ='Data Sheet'!A23 -> Selling and admin | C20: =IFERROR('Data Sheet'!B23/'Data Sheet'!B$17,"-") -> 0.07112314 | D20: =IFERROR('Data Sheet'!C23/'Data Sheet'!C$17,"-") -> 0.066935343 | E20: =IFERROR('Data Sheet'!D23/'Data Sheet'!D$17,"-") -> 0.065015173 | F20: =IFERROR('Data Sheet'!E23/'Data Sheet'!E$17,"-") -> 0.067166616 | G20: =IFERROR('Data Sheet'!F23/'Data Sheet'!F$17,"-") -> 0.059201903 | H20: =IFERROR('Data Sheet'!G23/'Data Sheet'!G$17,"-") -> 0.031789951 | I20: =IFERROR('Data Sheet'!H23/'Data Sheet'!H$17,"-") -> 0.035391028 | J20: =IFERROR('Data Sheet'!I23/'Data Sheet'!I$17,"-") -> 0.03611166 | ... L20: =IFERROR('Data Sheet'!K23/'Data Sheet'!K$17,"-") -> 0.037051353
B21: ='Data Sheet'!A24 -> Other Expenses | C21: =IFERROR('Data Sheet'!B24/'Data Sheet'!B$17,"-") -> 0.0068704857 | D21: =IFERROR('Data Sheet'!C24/'Data Sheet'!C$17,"-") -> 0.01003154 | E21: =IFERROR('Data Sheet'!D24/'Data Sheet'!D$17,"-") -> 0.01020958 | F21: =IFERROR('Data Sheet'!E24/'Data Sheet'!E$17,"-") -> 0.018215906 | G21: =IFERROR('Data Sheet'!F24/'Data Sheet'!F$17,"-") -> 0.010342435 | H21: =IFERROR('Data Sheet'!G24/'Data Sheet'!G$17,"-") -> 0.0089477665 | I21: =IFERROR('Data Sheet'!H24/'Data Sheet'!H$17,"-") -> 0.0084346561 | J21: =IFERROR('Data Sheet'!I24/'Data Sheet'!I$17,"-") -> 0.0099272997 | ... L21: =IFERROR('Data Sheet'!K24/'Data Sheet'!K$17,"-") -> 0.0069329407
B22: ='Data Sheet'!A25 -> Other Income | C22: =IFERROR('Data Sheet'!B25/'Data Sheet'!B$17,"-") -> 0.049967169 | D22: =IFERROR('Data Sheet'!C25/'Data Sheet'!C$17,"-") -> 0.04453595 | E22: =IFERROR('Data Sheet'!D25/'Data Sheet'!D$17,"-") -> 0.046949888 | F22: =IFERROR('Data Sheet'!E25/'Data Sheet'!E$17,"-") -> 0.034859389 | G22: =IFERROR('Data Sheet'!F25/'Data Sheet'!F$17,"-") -> 0.030873104 | H22: =IFERROR('Data Sheet'!G25/'Data Sheet'!G$17,"-") -> 0.021906601 | I22: =IFERROR('Data Sheet'!H25/'Data Sheet'!H$17,"-") -> 0.018866994 | J22: =IFERROR('Data Sheet'!I25/'Data Sheet'!I$17,"-") -> 0.01840332 | ... L22: =IFERROR('Data Sheet'!K25/'Data Sheet'!K$17,"-") -> 0.022087245
B23: ='Data Sheet'!A26 -> Depreciation | C23: =IFERROR('Data Sheet'!B26/'Data Sheet'!B$17,"-") -> 0.023366058 | D23: =IFERROR('Data Sheet'!C26/'Data Sheet'!C$17,"-") -> 0.024867122 | E23: =IFERROR('Data Sheet'!D26/'Data Sheet'!D$17,"-") -> 0.026417288 | F23: =IFERROR('Data Sheet'!E26/'Data Sheet'!E$17,"-") -> 0.024324161 | G23: =IFERROR('Data Sheet'!F26/'Data Sheet'!F$17,"-") -> 0.031864392 | H23: =IFERROR('Data Sheet'!G26/'Data Sheet'!G$17,"-") -> 0.032516522 | I23: =IFERROR('Data Sheet'!H26/'Data Sheet'!H$17,"-") -> 0.028575891 | J23: =IFERROR('Data Sheet'!I26/'Data Sheet'!I$17,"-") -> 0.028787125 | ... L23: =IFERROR('Data Sheet'!K26/'Data Sheet'!K$17,"-") -> 0.029523284
B24: ='Data Sheet'!A27 -> Interest | C24: =IFERROR('Data Sheet'!B27/'Data Sheet'!B$17,"-") -> 0 | D24: =IFERROR('Data Sheet'!C27/'Data Sheet'!C$17,"-") -> 0 | E24: =IFERROR('Data Sheet'!D27/'Data Sheet'!D$17,"-") -> 0 | F24: =IFERROR('Data Sheet'!E27/'Data Sheet'!E$17,"-") -> 0 | G24: =IFERROR('Data Sheet'!F27/'Data Sheet'!F$17,"-") -> 0.0018724323 | H24: =IFERROR('Data Sheet'!G27/'Data Sheet'!G$17,"-") -> 0.0019408392 | I24: =IFERROR('Data Sheet'!H27/'Data Sheet'!H$17,"-") -> 0.0016441825 | J24: =IFERROR('Data Sheet'!I27/'Data Sheet'!I$17,"-") -> 0.0019350399 | ... L24: =IFERROR('Data Sheet'!K27/'Data Sheet'!K$17,"-") -> 0.0025523038
B25: ='Data Sheet'!A28 -> Profit before tax | C25: =IFERROR('Data Sheet'!B28/'Data Sheet'!B$17,"-") -> 0.30012332 | D25: =IFERROR('Data Sheet'!C28/'Data Sheet'!C$17,"-") -> 0.29132352 | E25: =IFERROR('Data Sheet'!D28/'Data Sheet'!D$17,"-") -> 0.28742804 | F25: =IFERROR('Data Sheet'!E28/'Data Sheet'!E$17,"-") -> 0.25450257 | G25: =IFERROR('Data Sheet'!F28/'Data Sheet'!F$17,"-") -> 0.24239187 | H25: =IFERROR('Data Sheet'!G28/'Data Sheet'!G$17,"-") -> 0.26502906 | I25: =IFERROR('Data Sheet'!H28/'Data Sheet'!H$17,"-") -> 0.24753167 | J25: =IFERROR('Data Sheet'!I28/'Data Sheet'!I$17,"-") -> 0.22704014 | ... L25: =IFERROR('Data Sheet'!K28/'Data Sheet'!K$17,"-") -> 0.23073808
... B29: ='Data Sheet'!A32 -> EBITDA | C29: =IFERROR('Data Sheet'!B32/'Data Sheet'!B$17,"-") -> 0.2735222 | D29: =IFERROR('Data Sheet'!C32/'Data Sheet'!C$17,"-") -> 0.27165469 | E29: =IFERROR('Data Sheet'!D32/'Data Sheet'!D$17,"-") -> 0.26689544 | F29: =IFERROR('Data Sheet'!E32/'Data Sheet'!E$17,"-") -> 0.24396734 | G29: =IFERROR('Data Sheet'!F32/'Data Sheet'!F$17,"-") -> 0.24525559 | H29: =IFERROR('Data Sheet'!G32/'Data Sheet'!G$17,"-") -> 0.27757982 | I29: =IFERROR('Data Sheet'!H32/'Data Sheet'!H$17,"-") -> 0.25888475 | J29: =IFERROR('Data Sheet'!I32/'Data Sheet'!I$17,"-") -> 0.23935898 | ... L29: =IFERROR('Data Sheet'!K32/'Data Sheet'!K$17,"-") -> 0.24072642
A31: # | B31: Balance Sheet
B32: ='Data Sheet'!A61 & " Liabilities " -> Total Liabilities | C32: =IFERROR('Data Sheet'!B61/'Data Sheet'!B61,"-") -> 1 | D32: =IFERROR('Data Sheet'!C61/'Data Sheet'!C61,"-") -> 1 | E32: =IFERROR('Data Sheet'!D61/'Data Sheet'!D61,"-") -> 1 | F32: =IFERROR('Data Sheet'!E61/'Data Sheet'!E61,"-") -> 1 | G32: =IFERROR('Data Sheet'!F61/'Data Sheet'!F61,"-") -> 1 | H32: =IFERROR('Data Sheet'!G61/'Data Sheet'!G61,"-") -> 1 | I32: =IFERROR('Data Sheet'!H61/'Data Sheet'!H61,"-") -> 1 | J32: =IFERROR('Data Sheet'!I61/'Data Sheet'!I61,"-") -> 1 | ... L32: =IFERROR('Data Sheet'!K61/'Data Sheet'!K61,"-") -> 1
B33: ='Data Sheet'!A57 -> Equity Share Capital | C33: =IFERROR('Data Sheet'!B57/'Data Sheet'!B$61,"-") -> 0.015233428 | D33: =IFERROR('Data Sheet'!C57/'Data Sheet'!C$61,"-") -> 0.013758599 | E33: =IFERROR('Data Sheet'!D57/'Data Sheet'!D$61,"-") -> 0.013711578 | F33: =IFERROR('Data Sheet'!E57/'Data Sheet'!E$61,"-") -> 0.025813052 | G33: =IFERROR('Data Sheet'!F57/'Data Sheet'!F$61,"-") -> 0.023115468 | H33: =IFERROR('Data Sheet'!G57/'Data Sheet'!G$61,"-") -> 0.019756118 | I33: =IFERROR('Data Sheet'!H57/'Data Sheet'!H$61,"-") -> 0.017973254 | J33: =IFERROR('Data Sheet'!I57/'Data Sheet'!I$61,"-") -> 0.01660567 | ... L33: =IFERROR('Data Sheet'!K57/'Data Sheet'!K$61,"-") -> 0.014026185
B34: ='Data Sheet'!A58 -> Reserves | C34: =IFERROR('Data Sheet'!B58/'Data Sheet'!B$61,"-") -> 0.80694559 | D34: =IFERROR('Data Sheet'!C58/'Data Sheet'!C$61,"-") -> 0.8158705 | E34: =IFERROR('Data Sheet'!D58/'Data Sheet'!D$61,"-") -> 0.80448399 | F34: =IFERROR('Data Sheet'!E58/'Data Sheet'!E$61,"-") -> 0.74677039 | G34: =IFERROR('Data Sheet'!F58/'Data Sheet'!F$61,"-") -> 0.68984749 | H34: =IFERROR('Data Sheet'!G58/'Data Sheet'!G$61,"-") -> 0.69041307 | I34: =IFERROR('Data Sheet'!H58/'Data Sheet'!H$61,"-") -> 0.627539 | J34: =IFERROR('Data Sheet'!I58/'Data Sheet'!I$61,"-") -> 0.58860638 | ... L34: =IFERROR('Data Sheet'!K58/'Data Sheet'!K$61,"-") -> 0.63429074
B35: ='Data Sheet'!A59 -> Borrowings | C35: =IFERROR('Data Sheet'!B59/'Data Sheet'!B$61,"-") -> 0 | D35: =IFERROR('Data Sheet'!C59/'Data Sheet'!C$61,"-") -> 0 | E35: =IFERROR('Data Sheet'!D59/'Data Sheet'!D$61,"-") -> 0 | F35: =IFERROR('Data Sheet'!E59/'Data Sheet'!E$61,"-") -> 0 | G35: =IFERROR('Data Sheet'!F59/'Data Sheet'!F$61,"-") -> 0.05046841 | H35: =IFERROR('Data Sheet'!G59/'Data Sheet'!G$61,"-") -> 0.049529816 | I35: =IFERROR('Data Sheet'!H59/'Data Sheet'!H$61,"-") -> 0.046894945 | J35: =IFERROR('Data Sheet'!I59/'Data Sheet'!I$61,"-") -> 0.066607275 | ... L35: =IFERROR('Data Sheet'!K59/'Data Sheet'!K$61,"-") -> 0.055664941
B36: ='Data Sheet'!A60 -> Other Liabilities | C36: =IFERROR('Data Sheet'!B60/'Data Sheet'!B$61,"-") -> 0.17782098 | D36: =IFERROR('Data Sheet'!C60/'Data Sheet'!C$61,"-") -> 0.1703709 | E36: =IFERROR('Data Sheet'!D60/'Data Sheet'!D$61,"-") -> 0.18180443 | F36: =IFERROR('Data Sheet'!E60/'Data Sheet'!E$61,"-") -> 0.22741655 | G36: =IFERROR('Data Sheet'!F60/'Data Sheet'!F$61,"-") -> 0.23656863 | H36: =IFERROR('Data Sheet'!G60/'Data Sheet'!G$61,"-") -> 0.24030099 | I36: =IFERROR('Data Sheet'!H60/'Data Sheet'!H$61,"-") -> 0.3075928 | J36: =IFERROR('Data Sheet'!I60/'Data Sheet'!I$61,"-") -> 0.32818068 | ... L36: =IFERROR('Data Sheet'!K60/'Data Sheet'!K$61,"-") -> 0.29601813
B38: ='Data Sheet'!A66 & " Assets " -> Total Assets | C38: =IFERROR('Data Sheet'!B66/'Data Sheet'!B66,"-") -> 1 | D38: =IFERROR('Data Sheet'!C66/'Data Sheet'!C66,"-") -> 1 | E38: =IFERROR('Data Sheet'!D66/'Data Sheet'!D66,"-") -> 1 | F38: =IFERROR('Data Sheet'!E66/'Data Sheet'!E66,"-") -> 1 | G38: =IFERROR('Data Sheet'!F66/'Data Sheet'!F66,"-") -> 1 | H38: =IFERROR('Data Sheet'!G66/'Data Sheet'!G66,"-") -> 1 | I38: =IFERROR('Data Sheet'!H66/'Data Sheet'!H66,"-") -> 1 | J38: =IFERROR('Data Sheet'!I66/'Data Sheet'!I66,"-") -> 1 | ... L38: =IFERROR('Data Sheet'!K66/'Data Sheet'!K66,"-") -> 1
B39: ="Fixed Assets" & " - " & 'Data Sheet'!A62 -> Fixed Assets - Net Block | C39: =IFERROR('Data Sheet'!B62/'Data Sheet'!B$66,"-") -> 0.17824709 | D39: =IFERROR('Data Sheet'!C62/'Data Sheet'!C$66,"-") -> 0.17052725 | E39: =IFERROR('Data Sheet'!D62/'Data Sheet'!D$66,"-") -> 0.1584645 | F39: =IFERROR('Data Sheet'!E62/'Data Sheet'!E$66,"-") -> 0.18687698 | G39: =IFERROR('Data Sheet'!F62/'Data Sheet'!F$66,"-") -> 0.25913943 | H39: =IFERROR('Data Sheet'!G62/'Data Sheet'!G$66,"-") -> 0.23723154 | I39: =IFERROR('Data Sheet'!H62/'Data Sheet'!H$66,"-") -> 0.22102477 | J39: =IFERROR('Data Sheet'!I62/'Data Sheet'!I$66,"-") -> 0.23455809 | ... L39: =IFERROR('Data Sheet'!K62/'Data Sheet'!K$66,"-") -> 0.20948611
B40: ='Data Sheet'!A63 -> Capital Work in Progress | C40: =IFERROR('Data Sheet'!B63/'Data Sheet'!B$66,"-") -> 0.012783296 | D40: =IFERROR('Data Sheet'!C63/'Data Sheet'!C$66,"-") -> 0.01641651 | E40: =IFERROR('Data Sheet'!D63/'Data Sheet'!D$66,"-") -> 0.020239701 | F40: =IFERROR('Data Sheet'!E63/'Data Sheet'!E$66,"-") -> 0.016510837 | G40: =IFERROR('Data Sheet'!F63/'Data Sheet'!F$66,"-") -> 0.010392157 | H40: =IFERROR('Data Sheet'!G63/'Data Sheet'!G$66,"-") -> 0.0085758667 | I40: =IFERROR('Data Sheet'!H63/'Data Sheet'!H$66,"-") -> 0.0035638102 | J40: =IFERROR('Data Sheet'!I63/'Data Sheet'!I$66,"-") -> 0.0023114707 | ... L40: =IFERROR('Data Sheet'!K63/'Data Sheet'!K$66,"-") -> 0.0055076288
B41: ='Data Sheet'!A64 -> Investments | C41: =IFERROR('Data Sheet'!B64/'Data Sheet'!B$66,"-") -> 0.025193747 | D41: =IFERROR('Data Sheet'!C64/'Data Sheet'!C$66,"-") -> 0.19751527 | E41: =IFERROR('Data Sheet'!D64/'Data Sheet'!D$66,"-") -> 0.15328486 | F41: =IFERROR('Data Sheet'!E64/'Data Sheet'!E$66,"-") -> 0.13395427 | G41: =IFERROR('Data Sheet'!F64/'Data Sheet'!F$66,"-") -> 0.09577342 | H41: =IFERROR('Data Sheet'!G64/'Data Sheet'!G$66,"-") -> 0.13212602 | I41: =IFERROR('Data Sheet'!H64/'Data Sheet'!H$66,"-") -> 0.17411269 | J41: =IFERROR('Data Sheet'!I64/'Data Sheet'!I$66,"-") -> 0.15632926 | ... L41: =IFERROR('Data Sheet'!K64/'Data Sheet'!K$66,"-") -> 0.15928144
B42: ='Data Sheet'!A65 -> Other Assets | C42: =IFERROR('Data Sheet'!B74/'Data Sheet'!B$66,"-") -> 0.19751525 | D42: =IFERROR('Data Sheet'!C74/'Data Sheet'!C$66,"-") -> 0.19524222 | E42: =IFERROR('Data Sheet'!D74/'Data Sheet'!D$66,"-") -> 0.25263078 | F42: =IFERROR('Data Sheet'!E74/'Data Sheet'!E$66,"-") -> 0.2535151 | G42: =IFERROR('Data Sheet'!F74/'Data Sheet'!F$66,"-") -> 0.2301634 | H42: =IFERROR('Data Sheet'!G74/'Data Sheet'!G$66,"-") -> 0.21273172 | I42: =IFERROR('Data Sheet'!H74/'Data Sheet'!H$66,"-") -> 0.25716831 | J42: =IFERROR('Data Sheet'!I74/'Data Sheet'!I$66,"-") -> 0.30504992 | ... L42: =IFERROR('Data Sheet'!K74/'Data Sheet'!K$66,"-") -> 0.2494401
B43: ='Data Sheet'!A67 -> Receivables | C43: =IFERROR('Data Sheet'!B67/'Data Sheet'!B$66,"-") -> 0.15086953 | D43: =IFERROR('Data Sheet'!C67/'Data Sheet'!C$66,"-") -> 0.14819358 | E43: =IFERROR('Data Sheet'!D67/'Data Sheet'!D$66,"-") -> 0.16562276 | F43: =IFERROR('Data Sheet'!E67/'Data Sheet'!E$66,"-") -> 0.17637333 | G43: =IFERROR('Data Sheet'!F67/'Data Sheet'!F$66,"-") -> 0.20138344 | H43: =IFERROR('Data Sheet'!G67/'Data Sheet'!G$66,"-") -> 0.17946071 | I43: =IFERROR('Data Sheet'!H67/'Data Sheet'!H$66,"-") -> 0.19445039 | J43: =IFERROR('Data Sheet'!I67/'Data Sheet'!I$66,"-") -> 0.20405149 | ... L43: =IFERROR('Data Sheet'!K67/'Data Sheet'!K$66,"-") -> 0.21081904
B44: ='Data Sheet'!A68 -> Inventory | C44: =IFERROR('Data Sheet'!B68/'Data Sheet'!B$66,"-") -> 0 | D44: =IFERROR('Data Sheet'!C68/'Data Sheet'!C$66,"-") -> 0 | E44: =IFERROR('Data Sheet'!D68/'Data Sheet'!D$66,"-") -> 0 | F44: =IFERROR('Data Sheet'!E68/'Data Sheet'!E$66,"-") -> 0 | G44: =IFERROR('Data Sheet'!F68/'Data Sheet'!F$66,"-") -> 0 | H44: =IFERROR('Data Sheet'!G68/'Data Sheet'!G$66,"-") -> 0 | I44: =IFERROR('Data Sheet'!H68/'Data Sheet'!H$66,"-") -> 0 | J44: =IFERROR('Data Sheet'!I68/'Data Sheet'!I$66,"-") -> 0 | ... L44: =IFERROR('Data Sheet'!K68/'Data Sheet'!K$66,"-") -> 0
B45: ='Data Sheet'!A69 -> Cash & Bank | C45: =IFERROR('Data Sheet'!B69/'Data Sheet'!B$66,"-") -> 0.43539109 | D45: =IFERROR('Data Sheet'!C69/'Data Sheet'!C$66,"-") -> 0.27210516 | E45: =IFERROR('Data Sheet'!D69/'Data Sheet'!D$66,"-") -> 0.2497574 | F45: =IFERROR('Data Sheet'!E69/'Data Sheet'!E$66,"-") -> 0.23276949 | G45: =IFERROR('Data Sheet'!F69/'Data Sheet'!F$66,"-") -> 0.20314815 | H45: =IFERROR('Data Sheet'!G69/'Data Sheet'!G$66,"-") -> 0.22987415 | I45: =IFERROR('Data Sheet'!H69/'Data Sheet'!H$66,"-") -> 0.14968003 | J45: =IFERROR('Data Sheet'!I69/'Data Sheet'!I$66,"-") -> 0.097699766 | ... L45: =IFERROR('Data Sheet'!K69/'Data Sheet'!K$66,"-") -> 0.16546568

Sheet Forcasting
B4: ='Data Sheet'!$B$1 -> INFOSYS LTD
B5: ( NSE: INFY | BSE: 500209)
B6: 1250
B7: 52 Week (High 1728 & Low 1215)
B10: ="Forecasting" -> Forecasting
B12: ='Data Sheet'!$B$1& " - "& " Sales Forecasting" -> INFOSYS LTD - Sales Forecasting
B13: Year Weights | C13: Year | D13: Sales | E13: Sales Growth
B14: 1 | C14: 2016 | D14: {=IFERROR(TRANSPOSE('Data Sheet'!B17:K17),"-")} -> 62441 | E14: -
B15: 2 | C15: 2017 | D15: 68484 | E15: =IFERROR(D15/D14-1,"-") -> 0.09677936
B16: 3 | C16: 2018 | D16: 70522 | E16: =IFERROR(D16/D15-1,"-") -> 0.029758776
B17: 4 | C17: 2019 | D17: 82675 | E17: =IFERROR(D17/D16-1,"-") -> 0.1723292
B18: 5 | C18: 2020 | D18: 90791 | E18: =IFERROR(D18/D17-1,"-") -> 0.098167523
B19: 6 | C19: 2021 | D19: 100472 | E19: =IFERROR(D19/D18-1,"-") -> 0.10662951
B20: 7 | C20: 2022 | D20: 121641 | E20: =IFERROR(D20/D19-1,"-") -> 0.21069552
B21: 8 | C21: 2023 | D21: 146767 | E21: =IFERROR(D21/D20-1,"-") -> 0.20655864
B22: 9 | C22: 2024 | D22: 153670 | E22: =IFERROR(D22/D21-1,"-") -> 0.047033734
B23: 10 | C23: 2025 | D23: 162990 | E23: =IFERROR(D23/D22-1,"-") -> 0.060649444
B24: 11 | C24: 2026 | D24: =_xlfn.FORECAST.LINEAR(B24,$D$14:$D$23,$B$14:$B$23) -> 173013.53 | E24: =IFERROR(D24/D23-1,"-") -> 0.061497842
B25: 12 | C25: 2027 | D25: =_xlfn.FORECAST.LINEAR(B25,$D$14:$D$23,$B$14:$B$23) -> 185189.58 | E25: =IFERROR(D25/D24-1,"-") -> 0.070376243
B26: 13 | C26: 2028 | D26: =_xlfn.FORECAST.LINEAR(B26,$D$14:$D$23,$B$14:$B$23) -> 197365.62 | E26: =IFERROR(D26/D25-1,"-") -> 0.06574907
B27: 14 | C27: 2029 | D27: =_xlfn.FORECAST.LINEAR(B27,$D$14:$D$23,$B$14:$B$23) -> 209541.66 | E27: =IFERROR(D27/D26-1,"-") -> 0.061692824
B28: 15 | C28: 2030 | D28: =_xlfn.FORECAST.LINEAR(B28,$D$14:$D$23,$B$14:$B$23) -> 221717.7 | E28: =IFERROR(D28/D27-1,"-") -> 0.058107979
B30: ='Data Sheet'!$B$1& " - "& " EBITDA Forecasting" -> INFOSYS LTD - EBITDA Forecasting
B31: Year Weights | C31: Year | D31: EBITDA | E31: EBITDA Growth
B32: 1 | C32: 2016 | D32: {=IFERROR(TRANSPOSE('Data Sheet'!B32:K32),"-")} -> 17079 | E32: -
B33: 2 | C33: 2017 | D33: 18604 | E33: =IFERROR(D33/D32-1,"-") -> 0.089290942
B34: 3 | C34: 2018 | D34: 18822 | E34: =IFERROR(D34/D33-1,"-") -> 0.01171791
B35: 4 | C35: 2019 | D35: 20170 | E35: =IFERROR(D35/D34-1,"-") -> 0.071618319
B36: 5 | C36: 2020 | D36: 22267 | E36: =IFERROR(D36/D35-1,"-") -> 0.10396629
B37: 6 | C37: 2021 | D37: 27889 | E37: =IFERROR(D37/D36-1,"-") -> 0.25248125
B38: 7 | C38: 2022 | D38: 31491 | E38: =IFERROR(D38/D37-1,"-") -> 0.12915486
B39: 8 | C39: 2023 | D39: 35130 | E39: =IFERROR(D39/D38-1,"-") -> 0.11555683
B40: 9 | C40: 2024 | D40: 36425 | E40: =IFERROR(D40/D39-1,"-") -> 0.03686308
B41: 10 | C41: 2025 | D41: 39236 | E41: =IFERROR(D41/D40-1,"-") -> 0.077172272
B42: 11 | C42: 2026 | D42: =_xlfn.FORECAST.LINEAR(B42,$D$32:$D$41,$B$32:$B$41) -> 41554.133 | E42: =IFERROR(D42/D41-1,"-") -> 0.059081796
B43: 12 | C43: 2027 | D43: =_xlfn.FORECAST.LINEAR(B43,$D$32:$D$41,$B$32:$B$41) -> 44252.83 | E43: =IFERROR(D43/D42-1,"-") -> 0.064944128
B44: 13 | C44: 2028 | D44: =_xlfn.FORECAST.LINEAR(B44,$D$32:$D$41,$B$32:$B$41) -> 46951.527 | E44: =IFERROR(D44/D43-1,"-") -> 0.060983602
B45: 14 | C45: 2029 | D45: =_xlfn.FORECAST.LINEAR(B45,$D$32:$D$41,$B$32:$B$41) -> 49650.224 | E45: =IFERROR(D45/D44-1,"-") -> 0.057478364
B46: 15 | C46: 2030 | D46: =_xlfn.FORECAST.LINEAR(B46,$D$32:$D$41,$B$32:$B$41) -> 52348.921 | E46: =IFERROR(D46/D45-1,"-") -> 0.054354175
B48: ='Data Sheet'!$B$1& " - "& " EPS Forecasting" -> INFOSYS LTD - EPS Forecasting
B49: Year Weights | C49: Year | D49: EPS | E49: EPS Growth
B50: 1 | C50: 2016 | D50: {=IFERROR(TRANSPOSE('Historical FS'!C52:L52),"-")} -> 29.362851 | E50: -
B51: 2 | C51: 2017 | D51: 31.243606 | E51: =IFERROR(D51/D50-1,"-") -> 0.064052191
B52: 3 | C52: 2018 | D52: 36.694748 | E52: =IFERROR(D52/D51-1,"-") -> 0.17447227
B53: 4 | C53: 2019 | D53: 35.272036 | E53: =IFERROR(D53/D52-1,"-") -> -0.038771542
B54: 5 | C54: 2020 | D54: 39.067856 | E54: =IFERROR(D54/D53-1,"-") -> 0.10761556
B55: 6 | C55: 2021 | D55: 45.586406 | E55: =IFERROR(D55/D54-1,"-") -> 0.16685199
B56: 7 | C56: 2022 | D56: 52.644591 | E56: =IFERROR(D56/D55-1,"-") -> 0.15483091
B57: 8 | C57: 2023 | D57: 58.11117 | E57: =IFERROR(D57/D56-1,"-") -> 0.10383933
B58: 9 | C58: 2024 | D58: 63.234479 | E58: =IFERROR(D58/D57-1,"-") -> 0.088163932
B59: 10 | C59: 2025 | D59: 64.406616 | E59: =IFERROR(D59/D58-1,"-") -> 0.018536361
B60: 11 | C60: 2026 | D60: =_xlfn.FORECAST.LINEAR(B60,$D$50:$D$59,$B$50:$B$59) -> 69.064047 | E60: =IFERROR(D60/D59-1,"-") -> 0.07231292
B61: 12 | C61: 2027 | D61: =_xlfn.FORECAST.LINEAR(B61,$D$50:$D$59,$B$50:$B$59) -> 73.337067 | E61: =IFERROR(D61/D60-1,"-") -> 0.061870399
B62: 13 | C62: 2028 | D62: =_xlfn.FORECAST.LINEAR(B62,$D$50:$D$59,$B$50:$B$59) -> 77.610087 | E62: =IFERROR(D62/D61-1,"-") -> 0.05826549
B63: 14 | C63: 2029 | D63: =_xlfn.FORECAST.LINEAR(B63,$D$50:$D$59,$B$50:$B$59) -> 81.883107 | E63: =IFERROR(D63/D62-1,"-") -> 0.055057536
B64: 15 | C64: 2030 | D64: =_xlfn.FORECAST.LINEAR(B64,$D$50:$D$59,$B$50:$B$59) -> 86.156128 | E64: =IFERROR(D64/D63-1,"-") -> 0.052184392
B68: Notes:
B69: 1. All data presented in this forecasting sheet has been derived from historical income statement, based on previously reported data sourced from screener.in. except for 2026E to 2030E.
B70: 2. the FORECAST.LINEAR (linear regression) function was used to project future values based on historical trends.

Sheet Rm
B4: ='Data Sheet'!$B$1 -> INFOSYS LTD
B5: ( NSE: INFY | BSE: 500209)
B6: 1250
B7: 52 Week (High 1728 & Low 1215)
B10: Return on Markets
B12: Year | C12: Annual
B13: 2000 | C13: -0.1465
B14: 2001 | C14: -0.1618 | F14: Average Return | G14: =AVERAGE(C13:C38) -> 0.15149231
B15: 2002 | C15: 0.0325 | F15: Dividend Yield | G15: 1.28%1
B16: 2003 | C16: 0.719 | F16: Total Market Return | G16: =SUM(G14:G15) -> 0.15149231
B17: 2004 | C17: 0.1068
B18: 2005 | C18: 0.3634
B19: 2006 | C19: 0.3983
B20: 2007 | C20: 0.5477
B21: 2008 | C21: -0.5179
B22: 2009 | C22: 0.7576
B23: 2010 | C23: 0.1795
B24: 2011 | C24: -0.2462
B25: 2012 | C25: 0.277
B26: 2013 | C26: 0.0676
B27: 2014 | C27: 0.3139
B28: 2015 | C28: -0.0406
... B38: 2025 | C38: 0.1051
B42: Sources : Primeinvestor.in

Sheet WACC
B4: ='Data Sheet'!$B$1 -> INFOSYS LTD
B5: ( NSE: INFY | BSE: 500209)
B6: 1250
B7: 52 Week (High 1728 & Low 1215)
B10: ="Weighhted Average Cost of Capital" -> Weighhted Average Cost of Capital
B12: All figures are in INR unless stated otherwise.
B14: Peer Comps.
G15: Debt / | H15: Debt / | I15: Levered | J15: Unlevered
B16: Name of the Company | C16: Country | D16: Total Debt | E16: Total Equity | F16: Tax rate1 | G16: Equity | H16: Capital | I16: Beta2 | J16: Beta3
B18: TCS | C18: India | D18: 10932 | E18: 871979.34 | F18: 0.2517 | G18: =D18/E18 -> 0.012536994 | H18: =D18/(D18+E18) -> 0.012381764 | I18: 0.9 | J18: =I18/(1+(1-F18)*G18) -> 0.89163518
B19: Infosys | C19: India | D19: 8796 | E19: 506214.48 | F19: 0.2517 | G19: =D19/E19 -> 0.017376034 | H19: =D19/(D19+E19) -> 0.017079264 | I19: 0.85 | J19: =I19/(1+(1-F19)*G19) -> 0.83908975
B20: HCL Technologies | C20: India | D20: 6780 | E20: 359576.51 | F20: 0.2517 | G20: =D20/E20 -> 0.018855514 | H20: =D20/(D20+E20) -> 0.018506563 | I20: 1.01 | J20: =I20/(1+(1-F20)*G20) -> 0.9959476
B21: Wipro | C21: India | D21: 16163.7 | E21: 207335.47 | F21: 0.2517 | G21: =D21/E21 -> 0.077959164 | H21: =D21/(D21+E21) -> 0.072321074 | I21: 0.9 | J21: =I21/(1+(1-F21)*G21) -> 0.85039088
B22: Tech Mahindra | C22: India | D22: 1954.4 | E22: 130551.18 | F22: 0.2517 | G22: =D22/E22 -> 0.014970374 | H22: =D22/(D22+E22) -> 0.014749568 | I22: 0.92 | J22: =I22/(1+(1-F22)*G22) -> 0.90980803
E24: Average | F24: =AVERAGE(F18:F22) -> 0.2517 | G24: =AVERAGE(G18:G22) -> 0.028339616 | H24: =AVERAGE(H18:H22) -> 0.027007647 | I24: =AVERAGE(I18:I22) -> 0.916 | J24: =AVERAGE(J18:J22) -> 0.89737429
E25: Median | F25: =MEDIAN(F18:F22) -> 0.2517 | G25: =MEDIAN(G18:G22) -> 0.017376034 | H25: =MEDIAN(H18:H22) -> 0.017079264 | I25: =MEDIAN(I18:I22) -> 0.9 | J25: =MEDIAN(J18:J22) -> 0.89163518
B28: Cost of Debt | G28: Cost of Equity
B30: Pre-Tax Cost of Debt | E30: ='Historical FS'!L38/WACC!D19 -> 0.047294225 | G30: Risk Free Rate | J30: 0.0673
B31: Tax-rate | E31: =F19 -> 0.2517 | G31: Risk Premium | J31: =Rm!G16-WACC!J30 -> 0.084192308
B32: Post-Tax Cost of Debt | E32: =E30*(1-E31) -> 0.035390268 | G32: Leverage Beta4 | J32: =J41 -> 0.91015515
G33: Cost of Equity | J33: =J30+(J32*J31) -> 0.14392806
B36: Capital Structure | G36: Levered Beta
D38: Current | E38: Target | G38: Comps. Median Unlevered Beta | J38: =J25 -> 0.89163518
B39: Total Debt | C39: =D19 -> 8796 | D39: =C39/$C$41 -> 0.017079264 | E39: =H24 -> 0.027007647 | G39: Target Debt / Equity | J39: =E43 -> 0.027757306
B40: Market Capitilization | C40: =E19 -> 506214.48 | D40: =C40/$C$41 -> 0.98292074 | E40: =D41-E39 -> 0.97299235 | G40: Tax-rate | J40: =F19 -> 0.2517
B41: Total Capitalization | C41: =SUM(C39:C40) -> 515010.48 | D41: =SUM(D39:D40) -> 1 | E41: =SUM(E39:E40) -> 1 | G41: Levered Beta | J41: =J38*(1+(1-J40)*J39) -> 0.91015515
B43: Debt / Equity | D43: =D39/D40 -> 0.017376034 | E43: =E39/E40 -> 0.027757306
G45: Weighted Average Cost of Capital
G47: Cost of Equity | J47: =J33 -> 0.14392806
G48: Equity Weight | J48: =E40 -> 0.97299235
G50: Cost of Debt | J50: =E32 -> 0.035390268
G51: Debt Weight | J51: =E39 -> 0.027007647
G53: WACC | J53: =J47*J48+J50*J51 -> 0.14099671
B57: Notes:
B58: 1. Tax rate considered as Marginal Tax Rate for the country
B59: 2. Risk-free rate is based on Annualised yield of 10 years G-sec Bonds sourced from Rbi.org.in
B60: 3. Levered Beta is based on 5 years monthly data
B61: 4. Unlevered Beta = Levered Beta/(1+(1-Tax rate)*Debt/Equity)
B62: 5. Levered Beta = Unlevered Beta*(1+(1-Tax rate)*Debt/Equity)

Sheet Intrinsic value
B4: ='Data Sheet'!$B$1 -> INFOSYS LTD
B5: ( NSE: INFY | BSE: 500209)
B6: 1250
B7: 52 Week (High 1728 & Low 1215)
B10: ="Intrinsic Growth" -> Intrinsic Growth
B12: Calculation of ROIC | C12: ='Raw BS'!$H$3 -> 44256 | D12: ='Raw BS'!$I$3 -> 44621 | E12: ='Raw BS'!$J$3 -> 44986 | F12: ='Raw BS'!$K$3 -> 45352 | G12: ='Raw BS'!$L$3 -> 45717
B14: Current Assets
B15: ='Raw BS'!B37 -> Trade receivables | C15: ='Raw BS'!H37 -> 19294 | D15: ='Raw BS'!I37 -> 22698 | E15: ='Raw BS'!J37 -> 25424 | F15: ='Raw BS'!K37 -> 30193 | G15: ='Raw BS'!L37 -> 31158
B16: ='Raw BS'!B39 -> Loans n Advances | C16: ='Raw BS'!H39 -> 1460 | D16: ='Raw BS'!I39 -> 2491 | E16: ='Raw BS'!J39 -> 3242 | F16: ='Raw BS'!K39 -> 10330 | G16: ='Raw BS'!L39 -> 6717
B17: ='Raw BS'!B40 -> Other asset items | C17: - | D17: ='Raw BS'!I40 -> 27528 | E17: ='Raw BS'!J40 -> 34766 | F17: ='Raw BS'!K40 -> 29513 | G17: ='Raw BS'!L40 -> 30149
B18: Total Current Assets | C18: =SUM(C15:C17) -> 20754 | D18: =SUM(D15:D17) -> 52717 | E18: =SUM(E15:E17) -> 63432 | F18: =SUM(F15:F17) -> 70036 | G18: =SUM(G15:G17) -> 68024
B20: Current Liabilities
B21: ='Raw BS'!B13 -> Trade Payables | C21: ='Raw BS'!H13 -> 2645 | D21: ='Raw BS'!I13 -> 4134 | E21: ='Raw BS'!J13 -> 3865 | F21: ='Raw BS'!K13 -> 3956 | G21: ='Raw BS'!L13 -> 4164
B22: ='Raw BS'!B14 -> Advance from Customers | C22: ='Raw BS'!H14 -> 0 | D22: ='Raw BS'!I14 -> 0 | E22: ='Raw BS'!J14 -> 0 | F22: ='Raw BS'!K14 -> 0 | G22: ='Raw BS'!L14 -> 0
B23: ='Raw BS'!B15 -> Other liability items | C23: ='Raw BS'!H15 -> 22759 | D23: ='Raw BS'!I15 -> 31385 | E23: ='Raw BS'!J15 -> 36637 | F23: ='Raw BS'!K15 -> 36584 | G23: ='Raw BS'!L15 -> 39201
B24: Total Current Liabilities | C24: =SUM(C21:C23) -> 25404 | D24: =SUM(D21:D23) -> 35519 | E24: =SUM(E21:E23) -> 40502 | F24: =SUM(F21:F23) -> 40540 | G24: =SUM(G21:G23) -> 43365
A26: # | B26: Net Working Capital | C26: =C18-C24 -> -4650 | D26: =D18-D24 -> 17198 | E26: =E18-E24 -> 22930 | F26: =F18-F24 -> 29496 | G26: =G18-G24 -> 24659
B28: Non-Current Assets
B29: ='Raw BS'!B19 -> Land | C29: ='Raw BS'!H19 -> 2036 | D29: ='Raw BS'!I19 -> 2065 | E29: ='Raw BS'!J19 -> 2054 | F29: ='Raw BS'!K19 -> 2037 | G29: ='Raw BS'!L19 -> 2079
B30: ='Raw BS'!B20 -> Building | C30: ='Raw BS'!H20 -> 16328 | D30: ='Raw BS'!I20 -> 16761 | E30: ='Raw BS'!J20 -> 16903 | F30: ='Raw BS'!K20 -> 16515 | G30: ='Raw BS'!L20 -> 16376
B31: ='Raw BS'!B21 -> Plant Machinery | C31: ='Raw BS'!H21 -> 3296 | D31: ='Raw BS'!I21 -> 3210 | E31: ='Raw BS'!J21 -> 3302 | F31: ='Raw BS'!K21 -> 3428 | G31: ='Raw BS'!L21 -> 3461
B32: ='Raw BS'!B22 -> Equipments | C32: ='Raw BS'!H22 -> 1371 | D32: ='Raw BS'!I22 -> 1427 | E32: ='Raw BS'!J22 -> 1482 | F32: ='Raw BS'!K22 -> 1528 | G32: ='Raw BS'!L22 -> 1628
B33: ='Raw BS'!B23 -> Computers | C33: ='Raw BS'!H23 -> 8650 | D33: ='Raw BS'!I23 -> 9936 | E33: ='Raw BS'!J23 -> 11898 | F33: ='Raw BS'!K23 -> 12353 | G33: ='Raw BS'!L23 -> 12925
B34: ='Raw BS'!B24 -> Furniture n fittings | C34: ='Raw BS'!H24 -> 2149 | D34: ='Raw BS'!I24 -> 2279 | E34: ='Raw BS'!J24 -> 2303 | F34: ='Raw BS'!K24 -> 2326 | G34: ='Raw BS'!L24 -> 2340
B35: ='Raw BS'!B25 -> Vehicles | C35: ='Raw BS'!H25 -> 74 | D35: ='Raw BS'!I25 -> 71 | E35: ='Raw BS'!J25 -> 60 | F35: ='Raw BS'!K25 -> 62 | G35: ='Raw BS'!L25 -> 72
B36: ='Raw BS'!B26 -> Intangible Assets | C36: ='Raw BS'!H26 -> 6372 | D36: ='Raw BS'!I26 -> 6495 | E36: ='Raw BS'!J26 -> 7594 | F36: ='Raw BS'!K26 -> 7653 | G36: ='Raw BS'!L26 -> 10626
B37: ='Raw BS'!B27 -> Other fixed assets | C37: ='Raw BS'!H27 -> 2730 | D37: ='Raw BS'!I27 -> 2766 | E37: ='Raw BS'!J27 -> 3281 | F37: ='Raw BS'!K27 -> 3294 | G37: ='Raw BS'!L27 -> 5184
B38: Gross Block | C38: =SUM(C29:C37) -> 43006 | D38: =SUM(D29:D37) -> 45010 | E38: =SUM(E29:E37) -> 48877 | F38: =SUM(F29:F37) -> 49196 | G38: =SUM(G29:G37) -> 54691
B39: ='Raw BS'!B31 -> Accumulated Depreciation | C39: =-'Raw BS'!H31 -> -17501 | D39: =-'Raw BS'!I31 -> -19210 | E39: =-'Raw BS'!J31 -> -19652 | F39: =-'Raw BS'!K31 -> -21574 | G39: =-'Raw BS'!L31 -> -23730
A40: # | B40: Net Block | C40: =SUM(C38:C39) -> 25505 | D40: =SUM(D38:D39) -> 25800 | E40: =SUM(E38:E39) -> 29225 | F40: =SUM(F38:F39) -> 27622 | G40: =SUM(G38:G39) -> 30961
A42: # | B42: Invested Capital | C42: =C26+C40 -> 20855 | D42: =D26+D40 -> 42998 | E42: =E26+E40 -> 52155 | F42: =F26+F40 -> 57118 | G42: =G26+G40 -> 55620
B43: EBIT | C43: ='Historical FS'!H32 -> 24622 | D43: ='Historical FS'!I32 -> 28015 | E43: ='Historical FS'!J32 -> 30905 | F43: ='Historical FS'!K32 -> 31747 | G43: ='Historical FS'!L32 -> 34424
A45: # | B45: ROIC | C45: =C43/C42 -> 1.1806281 | D45: =D43/D42 -> 0.65154193 | E45: =E43/E42 -> 0.59256064 | F45: =F43/F42 -> 0.55581428 | G45: =G43/G42 -> 0.61891406
B48: Calculation of Reinvestment Rate | C48: ='Raw BS'!$H$3 -> 44256 | D48: ='Raw BS'!$I$3 -> 44621 | E48: ='Raw BS'!$J$3 -> 44986 | F48: ='Raw BS'!$K$3 -> 45352 | G48: ='Raw BS'!$L$3 -> 45717
B50: Net Capex | C50: =-SUM('Raw CF'!J12:J13) -> 2107 | D50: =-SUM('Raw CF'!K12:K13) -> 2161 | E50: =-SUM('Raw CF'!L12:L13) -> 2579 | F50: =-SUM('Raw CF'!M12:M13) -> 2201 | G50: =-SUM('Raw CF'!N12:N13) -> 2237
B51: Change In Working Capital | C51: - | D51: =D26-C26 -> 21848 | E51: =E26-D26 -> 5732 | F51: =F26-E26 -> 6566 | G51: =G26-F26 -> -4837
B53: EBIT | C53: =C43 -> 24622 | D53: =D43 -> 28015 | E53: =E43 -> 30905 | F53: =F43 -> 31747 | G53: =G43 -> 34424
B54: Marginal Tax Rate | C54: 0.2517 | D54: 0.2517 | E54: 0.2517 | F54: 0.2517 | G54: 0.2517
B55: EBIT(1-Tax) | C55: =C53*(1-C54) -> 18424.643 | D55: =D53*(1-D54) -> 20963.624 | E55: =E53*(1-E54) -> 23126.211 | F55: =F53*(1-F54) -> 23756.28 | G55: =G53*(1-G54) -> 25759.479
B57: Reinvestment | C57: - | D57: =SUM(D50:D51) -> 24009 | E57: =SUM(E50:E51) -> 8311 | F57: =SUM(F50:F51) -> 8767 | G57: =SUM(G50:G51) -> -2600
A59: # | B59: Reinvestment rate | D59: =D57/D55 -> 1.1452695 | E59: =E57/E55 -> 0.35937577 | F59: =F57/F55 -> 0.36903926 | G59: =G57/G55 -> -0.10093372
F61: 4 year Average | G61: =AVERAGE(D59:G59) -> 0.44318771
F62: 4 year Median | G62: =MEDIAN(D59:G59) -> 0.36420751
B64: Calculation of Intrinsic Growth Rate | C64: ='Raw BS'!$H$3 -> 44256 | D64: ='Raw BS'!$I$3 -> 44621 | E64: ='Raw BS'!$J$3 -> 44986 | F64: ='Raw BS'!$K$3 -> 45352 | G64: ='Raw BS'!$L$3 -> 45717
B66: =B59 -> Reinvestment rate | D66: =D59 -> 1.1452695 | E66: =E59 -> 0.35937577 | F66: =F59 -> 0.36903926 | G66: =G59 -> -0.10093372
B67: =B45 -> ROIC | D67: =D45 -> 0.65154193 | E67: =E45 -> 0.59256064 | F67: =F45 -> 0.55581428 | G67: =G45 -> 0.61891406
B69: Intrinsic Growth | D69: =D66*D67 -> 0.74619111 | E69: =E66*E67 -> 0.21295193 | F69: =F66*F67 -> 0.20511729 | G69: =G66*G67 -> -0.062469297
F71: 4 year Average | G71: =AVERAGE(D69:G69) -> 0.27544776
F72: 4 year Median | G72: =MEDIAN(D69:G69) -> 0.20903461

Sheet DCF
B4: ='Data Sheet'!$B$1 -> INFOSYS LTD
B5: ( NSE: INFY | BSE: 500209)
B6: 1250
B7: 52 Week (High 1728 & Low 1215)
B10: ="Discounting CashFlow " -> Discounting CashFlow
B12: Calculation of PV of FCFF | D12: ='Intrinsic value'!G12 -> 45717 | E12: =D12+365 -> 46082 | F12: =E12+365 -> 46447 | G12: =F12+366 -> 46813 | H12: =G12+365 -> 47178 | I12: =H12+365 -> 47543
B14: EBIT | D14: ='Historical FS'!L32 -> 34424 | E14: =D14*(1+$C$25) -> 41619.807 | F14: =E14*(1+$C$25) -> 50319.788 | G14: =F14*(1+$C$25) -> 60838.365 | H14: =G14*(1+$C$25) -> 73555.689 | I14: =H14*(1+$C$25) -> 88931.374
B15: Tax-Rate | D15: 0.2517 | E15: 0.2517 | F15: 0.2517 | G15: 0.2517 | H15: 0.2517 | I15: 0.2517
B16: EBIT(1-T) | D16: =D14*(1-D15) -> 25759.479 | E16: =E14*(1-E15) -> 31144.102 | F16: =F14*(1-F15) -> 37654.297 | G16: =G14*(1-G15) -> 45525.349 | H16: =H14*(1-H15) -> 55041.722 | I16: =I14*(1-I15) -> 66547.347
B17: Less: Reinvestment Rate | D17: ='Intrinsic value'!G62 -> 0.36420751 | E17: 0.24165236 | F17: 0.24165236 | G17: 0.24165236 | H17: 0.24165236 | I17: 0.24165236
B18: Free Cash flow to firm (FCFF) | D18: =D16*(1-D17) -> 16377.683 | E18: =E16*(1-E17) -> 23618.056 | F18: =F16*(1-F17) -> 28555.047 | G18: =G16*(1-G17) -> 34524.041 | H18: =H16*(1-H17) -> 41740.76 | I18: =I16*(1-I17) -> 50466.024
B20: Mid Year conversion | E20: 0.5 | F20: =E20+1 -> 1.5 | G20: =F20+1 -> 2.5 | H20: =G20+1 -> 3.5 | I20: =H20+1 -> 4.5
B21: Discounting factor | E21: =1/(1+$C$27)^E20 -> 0.93617665 | F21: =1/(1+$C$27)^F20 -> 0.82049022 | G21: =1/(1+$C$27)^G20 -> 0.71909955 | H21: =1/(1+$C$27)^H20 -> 0.63023806 | I21: =1/(1+$C$27)^I20 -> 0.55235747
B23: PV of FCFF | E23: =E18*E21 -> 22110.673 | F23: =F18*F21 -> 23429.137 | G23: =G18*G21 -> 24826.222 | H23: =H18*H21 -> 26306.616 | I23: =I18*I21 -> 27875.285
B25: Expected Growth | C25: ='Intrinsic value'!G72 -> 0.20903461
B26: Terminal Growth | C26: 0.045
B27: WACC | C27: =WACC!J53 -> 0.14099671
B29: Calculation of Terminal Value | E29: Senstivity Analysis - Terminal Value
E30: =C35 -> 635596.45 | F30: 0.13 | G30: 0.141 | H30: 0.15 | I30: 0.16
B31: FCFF (n+1) | C31: =I18*(1+C25) -> 61015.169 | E31: 0.02 | F31: 554683.36 | G31: 504257.6 | H31: 469347.46 | I31: 435822.64
B32: WACC | C32: =C27 -> 0.14099671 | E32: 0.03 | F32: 610151.69 | G32: 549686.21 | H32: 508459.74 | I32: 469347.46
B33: Terminal Growth Rate | C33: =C26 -> 0.045 | E33: 0.045 | F33: 717825.52 | G33: 635574.68 | H33: 581096.85 | I33: 530566.69
E34: 0.05 | F34: 762689.62 | G34: 670496.37 | H34: 610151.69 | I34: 554683.36
B35: Terminal Value | C35: =C31/(C32-C33) -> 635596.45 | E35: 0.06 | F35: 871645.28 | G35: 753273.7 | H35: 677946.33 | I35: 610151.69
B37: Calculation of Enterprise Value | E37: Senstivity Analysis - EPS
E38: =C53 -> 1104.9548 | F38: 0.13 | G38: 0.141 | H38: 0.15 | I38: 0.16
B39: PV of FCFF | C39: =SUM(E23:I23) -> 124547.93 | E39: 0.02 | F39: 994.74852 | G39: 926.06699 | H39: 878.51824 | I39: 832.85635
B40: Terminal Value | C40: =C35 -> 635596.45 | E40: 0.03 | F40: 1070.2982 | G40: 987.94224 | H40: 931.79045 | I40: 878.51824
B41: PV of Terminal Value | C41: =C40*I21 -> 351076.45 | E41: 0.045 | F41: 1216.9535 | G41: 1104.9251 | H41: 1030.7246 | I41: 961.90083
E42: 0.05 | F42: 1278.0598 | G42: 1152.4896 | H42: 1070.2982 | I42: 994.74852
B43: Enterprise Value | C43: =SUM(C39,C41) -> 475624.38 | E43: 0.06 | F43: 1426.461 | G43: 1265.235 | H43: 1162.6367 | I43: 1070.2982
B45: Calculation of Equity Per Share Value
B47: =B43 -> Enterprise Value | C47: =C43 -> 475624.38
B48: ="Add:"&'Data Sheet'!A69 -> Add:Cash & Bank | C48: ='Data Sheet'!K69 -> 24455
B49: ="Less:"& "Debt" -> Less:Debt | C49: =SUM('Data Sheet'!K59:K60) -> 51977
B50: Equity Value | C50: =SUM(C47,C48)-C49 -> 448102.38
B52: No. of Equity Share | C52: ='Data Sheet'!B6 -> 405.53911
B53: Equity Per share Value | C53: =C50/C52 -> 1104.9548
B55: Current Share price | C55: 1250
B56: Discount/Premium | C56: =C53-C55 -> -145.04522
B60: Notes:
B61: 1. Tax rate considered as Marginal Tax Rate for the country
B62: 2. Discounting Factor = 1/(1+WACC)^Mid year Conversion
B63: 3. The Terminal Growth rate has been assumed to be 4.50%, reflecting long-term Nominal GDP expectations.
B64: 4. The mid year Conversion is used to reflect the timming of cashflows, assuming they are received evenly throughout the year rather than all at year-end.

Sheet Comps_Val.
B4: ='Data Sheet'!$B$1 -> INFOSYS LTD
B5: ( NSE: INFY | BSE: 500209)
B6: 1250
B7: 52 Week (High 1728 & Low 1215)
B10: ="Comparable Company Valuation" -> Comparable Company Valuation
B11: (Figures in Crores)
D13: Market Data | J13: Financials | N13: Valuation
B14: Company | C14: Ticker | D14: Share Price | E14: Share Outstanding | F14: Equity Value | G14: Net Debt | H14: Enterprise Value | J14: Revenue | K14: EBITDA | L14: Net Income | N14: EV/Revenue | O14: EV/EBITDA | P14: P/E
B16: ='Raw Comp_val.'!C4 -> Infosys | C16: INFY | D16: ='Raw Comp_val.'!D4 -> 1255.9 | E16: ='Raw Comp_val.'!E4 -> 405.54 | F16: =D16*E16 -> 509317.69 | G16: ='Raw Comp_val.'!I4 -> -15659 | H16: =F16+G16 -> 493658.69 | J16: ='Raw Comp_val.'!K4 -> 173173 | K16: ='Raw Comp_val.'!M4 -> 44918.898 | L16: ='Raw Comp_val.'!N4 -> 28003 | N16: =$H$16/J16 -> 2.8506677 | O16: =$H$16/K16 -> 10.99 | P16: =F16/L16 -> 18.187969
A17: i | B17: ='Raw Comp_val.'!C3 -> TCS | C17: TCS | D17: ='Raw Comp_val.'!D3 -> 2390.6 | E17: ='Raw Comp_val.'!E3 -> 361.81 | F17: =D17*E17 -> 864942.99 | G17: ='Raw Comp_val.'!I3 -> -4531 | H17: =F17+G17 -> 860411.99 | J17: ='Raw Comp_val.'!K3 -> 260802 | K17: ='Raw Comp_val.'!M3 -> 74688.54 | L17: ='Raw Comp_val.'!N3 -> 47963 | N17: =$H$16/J17 -> 1.8928485 | O17: =$H$16/K17 -> 6.609564 | P17: =F17/L17 -> 18.033546
B18: ='Raw Comp_val.'!C5 -> HCL Technologies | C18: HCLTECH | D18: ='Raw Comp_val.'!D5 -> 1333.7 | E18: ='Raw Comp_val.'!E5 -> 271.37 | F18: =D18*E18 -> 361926.17 | G18: ='Raw Comp_val.'!I5 -> -14509 | H18: =F18+G18 -> 347417.17 | J18: ='Raw Comp_val.'!K5 -> 126409 | K18: ='Raw Comp_val.'!M5 -> 28383.756 | L18: ='Raw Comp_val.'!N5 -> 16471 | N18: =$H$16/J18 -> 3.9052495 | O18: =$H$16/K18 -> 17.392296 | P18: =F18/L18 -> 21.973539
B19: ='Raw Comp_val.'!C6 -> Wipro | C19: WIPRO | D19: ='Raw Comp_val.'!D6 -> 190.9 | E19: ='Raw Comp_val.'!E6 -> 1048.84 | F19: =D19*E19 -> 200223.56 | G19: ='Raw Comp_val.'!I6 -> 3966.3 | H19: =F19+G19 -> 204189.86 | J19: ='Raw Comp_val.'!K6 -> 90891.9 | K19: ='Raw Comp_val.'!M6 -> 21885.301 | L19: ='Raw Comp_val.'!N6 -> 13332 | N19: =$H$16/J19 -> 5.4312726 | O19: =$H$16/K19 -> 22.556632 | P19: =F19/L19 -> 15.018269
B20: ='Raw Comp_val.'!C7 -> Tech Mahindra | C20: TECHM | D20: ='Raw Comp_val.'!D7 -> 1384.8 | E20: ='Raw Comp_val.'!E7 -> 97.98 | F20: =D20*E20 -> 135682.7 | G20: ='Raw Comp_val.'!I7 -> -2587.8 | H20: =F20+G20 -> 133094.9 | J20: ='Raw Comp_val.'!K7 -> 55123.3 | K20: ='Raw Comp_val.'!M7 -> 8699.0133 | L20: ='Raw Comp_val.'!N7 -> 4591 | N20: =$H$16/J20 -> 8.9555358 | O20: =$H$16/K20 -> 56.748814 | P20: =F20/L20 -> 29.554063
B21: ='Raw Comp_val.'!C8 -> LTIMindtree | C21: LTM | D21: ='Raw Comp_val.'!D8 -> 4298.8 | E21: ='Raw Comp_val.'!E8 -> 29.65 | F21: =D21*E21 -> 127459.42 | G21: ='Raw Comp_val.'!I8 -> -1205.6 | H21: =F21+G21 -> 126253.82 | J21: ='Raw Comp_val.'!K8 -> 40787.6 | K21: ='Raw Comp_val.'!M8 -> 8311.6406 | L21: ='Raw Comp_val.'!N8 -> 4724 | N21: =$H$16/J21 -> 12.103156 | O21: =$H$16/K21 -> 59.393652 | P21: =F21/L21 -> 26.981249
B22: ='Raw Comp_val.'!C9 -> Persistent Systems | C22: PERSISTENT | D22: ='Raw Comp_val.'!D9 -> 4716.7 | E22: ='Raw Comp_val.'!E9 -> 15.78 | F22: =D22*E22 -> 74429.526 | G22: ='Raw Comp_val.'!I9 -> -621.53 | H22: =F22+G22 -> 73807.996 | J22: ='Raw Comp_val.'!K9 -> 13934.63 | K22: ='Raw Comp_val.'!M9 -> 2785.2074 | L22: ='Raw Comp_val.'!N9 -> 1731.62 | N22: =$H$16/J22 -> 35.426752 | O22: =$H$16/K22 -> 177.24306 | P22: =F22/L22 -> 42.982598
B24: High | N24: =MAX(N16:N22) -> 35.426752 | O24: =MAX(O16:O22) -> 177.24306 | P24: =MAX(P16:P22) -> 42.982598
B25: 75th Percentile | N25: =QUARTILE(N16:N22,) -> 1.8928485 | O25: =QUARTILE(O16:O22,) -> 6.609564 | P25: =QUARTILE(P16:P22,) -> 15.018269
B26: Average | N26: =AVERAGE(N16:N22) -> 10.080783 | O26: =AVERAGE(O16:O22) -> 50.133431 | P26: =AVERAGE(P16:P22) -> 24.67589
B27: Median | N27: =MEDIAN(N16:N22) -> 5.4312726 | O27: =MEDIAN(O16:O22) -> 22.556632 | P27: =MEDIAN(P16:P22) -> 21.973539
B28: 25th Percentile | N28: =QUARTILE(N16:N22,1) -> 3.3779586 | O28: =QUARTILE(O16:O22,1) -> 14.191148 | P28: =QUARTILE(P16:P22,1) -> 18.110758
B29: Low | N29: =MIN(N16:N22) -> 1.8928485 | O29: =MIN(O16:O22) -> 6.609564 | P29: =MIN(P16:P22) -> 15.018269
B31: Infosys Comparable Valuation | N31: EV/Revenue | O31: EV/EBITDA | P31: P/E
B33: Implied Enterprise value | N33: =N27*J16 -> 940549.77 | O33: =O27*K16 -> 1013219.1 | P33: =P34+P35 -> 599666.03
B34: Net Debt | N34: =$G$16 -> -15659 | O34: =$G$16 -> -15659 | P34: =$G$16 -> -15659
B35: Implied Market value | N35: =N33-N34 -> 956208.77 | O35: =O33-O34 -> 1028878.1 | P35: =P27*L16 -> 615325.03
B36: Share Outstanding | N36: =$E$16 -> 405.54 | O36: =$E$16 -> 405.54 | P36: =$E$16 -> 405.54
B38: Implied Value per Share | N38: =N35/N36 -> 2357.8655 | O38: =O35/O36 -> 2537.0569 | P38: =P35/P36 -> 1517.298
N40: =IF(N38>$D$16, "Undervalued","Overvalued") -> Undervalued | O40: =IF(O38>$D$16, "Undervalued","Overvalued") -> Undervalued | P40: =IF(P38>$D$16, "Undervalued","Overvalued") -> Undervalued
B44: Source: Screener.in

Sheet VAR
B4: ='Data Sheet'!$B$1 -> INFOSYS LTD
B5: ( NSE: INFY | BSE: 500209)
B6: 1250
B7: 52 Week (High 1728 & Low 1215)
B10: Value at Risk
B12: Date | C12: Price | D12: Returns | E12: Sorted Returns | G12: Replication | H12: Simulated Returns | J12: Historical Approach (3Y)
B13: 45474 | C13: 1868.25 | D13: =C13/C14-1 -> 0.19243657 | E13: 0.19243657 | G13: 1 | H13: =_xlfn.NORM.INV(RAND(),N$13,N$14) -> -0.074219351 | J13: Mean | N13: =AVERAGE(E13:E47) -> 0.0022391814
B14: 45444 | C14: 1566.75 | D14: =C14/C15-1 -> -0.051368681 | E14: 0.11361859 | G14: 2 | H14: =_xlfn.NORM.INV(RAND(),N$13,N$14) -> -0.11432756 | J14: Standard deviation | N14: =_xlfn.STDEV.S(E13:E47) -> 0.070432302
B15: 45292 | C15: 1651.59 | D15: =C15/C16-1 -> 0.14139697 | E15: 0.076480365 | G15: 3 | H15: =_xlfn.NORM.INV(RAND(),N$13,N$14) -> -0.015491517 | J15: Min. | N15: =MIN(E13:E47) -> -0.20773918
B16: 45231 | C16: 1446.99 | D16: =C16/C17-1 -> -0.056874694 | E16: 0.063392444 | G16: 4 | H16: =_xlfn.NORM.INV(RAND(),N$13,N$14) -> 0.082527366 | J16: Max. | N16: =MAX(E13:E47) -> 0.19243657
B17: 45261 | C17: 1534.25 | D17: =C17/C18-1 -> 0.074848852 | E17: 0.060304494 | G17: 5 | H17: =_xlfn.NORM.INV(RAND(),N$13,N$14) -> -0.081649744 | J17: CMP | N17: 1300.8
B18: 45139 | C18: 1427.41 | D18: =C18/C19-1 -> -0.23168717 | E18: 0.058830947 | G18: 6 | H18: =_xlfn.NORM.INV(RAND(),N$13,N$14) -> 0.060144681
B19: 45597 | C19: 1857.85 | D19: =C19/C20-1 -> 0.19085315 | E19: 0.057248542 | G19: 7 | H19: =_xlfn.NORM.INV(RAND(),N$13,N$14) -> -0.030420137 | J19: Monte Carlo Simulation
B20: 45962 | C20: 1560.1 | D20: =C20/C21-1 -> -0.001663787 | E20: 0.052486001 | G20: 8 | H20: =_xlfn.NORM.INV(RAND(),N$13,N$14) -> -0.048435705 | J20: Mean | N20: =AVERAGE(H13:H5012) -> 0.0026887793
B21: 45778 | C21: 1562.7 | D21: =C21/C22-1 -> -0.1960179 | E21: 0.041730551 | G21: 9 | H21: =_xlfn.NORM.INV(RAND(),N$13,N$14) -> -0.13608487 | J21: Standard deviation | N21: =_xlfn.STDEV.S(H13:H5012) -> 0.06950355
B22: 45505 | C22: 1943.7 | D22: =C22/C23-1 -> 0.49423432 | E22: 0.040385387 | G22: 10 | H22: =_xlfn.NORM.INV(RAND(),N$13,N$14) -> -0.019893312 | J22: Min. | N22: =MIN(H13:H5012) -> -0.22430755
B23: 46113 | C23: 1300.8 | D23: =C23/C24-1 -> -0.19475053 | E23: 0.040140732 | G23: 11 | H23: =_xlfn.NORM.INV(RAND(),N$13,N$14) -> 0.029808443 | J23: Max. | N23: =MAX(H13:H5012) -> 0.24288055
B24: 45992 | C24: 1615.4 | D24: =C24/C25-1 -> 0.089792889 | E24: 0.035446446 | G24: 12 | H24: =_xlfn.NORM.INV(RAND(),N$13,N$14) -> 0.11893874 | J24: CMP | N24: 1300.8
B25: 45931 | C25: 1482.3 | D25: =C25/C26-1 -> -0.074603571 | E25: 0.028089888 | G25: 13 | H25: =_xlfn.NORM.INV(RAND(),N$13,N$14) -> 0.033269479
B26: 45809 | C26: 1601.8 | D26: =C26/C27-1 -> -0.023887873 | E26: 0.025020797 | G26: 14 | H26: =_xlfn.NORM.INV(RAND(),N$13,N$14) -> -0.048837735 | J26: Percentile | K26: Confidence | L26: Var % | M26: Stock Price | N26: Var Price
B27: 46023 | C27: 1641 | D27: =C27/C28-1 -> 0.21726875 | E27: 0.015847468 | G27: 15 | H27: =_xlfn.NORM.INV(RAND(),N$13,N$14) -> 0.084715424 | J27: 0.05 | K27: =100%-J27 -> 0.95 | L27: =_xlfn.PERCENTILE.INC($H$13:$H$5012,J27) -> -0.11153257 | M27: =$N$17*(1-L27) -> 1445.8816 | N27: =$N$17-M27 -> -145.08157
B28: 45108 | C28: 1348.1 | D28: =C28/C29-1 -> 0.015120254 | E28: 0.015120254 | G28: 16 | H28: =_xlfn.NORM.INV(RAND(),N$13,N$14) -> -0.021466719 | J28: 0.01 | K28: =100%-J28 -> 0.99 | L28: =_xlfn.PERCENTILE.INC($H$13:$H$5012,J28) -> -0.15733138 | M28: =$N$17*(1-L28) -> 1505.4567 | N28: =$N$17-M28 -> -204.65666
B29: 45078 | C29: 1328.02 | D29: =C29/C30-1 -> -0.29360638 | E29: 0.013052002 | G29: 17 | H29: =_xlfn.NORM.INV(RAND(),N$13,N$14) -> -0.1407948 | J29: 0.005 | K29: =100%-J29 -> 0.995 | L29: =_xlfn.PERCENTILE.INC($H$13:$H$5012,J29) -> -0.1757291 | M29: =$N$17*(1-L29) -> 1529.3884 | N29: =$N$17-M29 -> -228.58841
B30: 45627 | C30: 1880 | D30: =C30/C31-1 -> 0.12945474 | E30: 0.011922383 | G30: 18 | H30: =_xlfn.NORM.INV(RAND(),N$13,N$14) -> -0.046275175 | J30: 0.1 | K30: =100%-J30 -> 0.9 | L30: =_xlfn.PERCENTILE.INC($H$13:$H$5012,J30) -> -0.085488793 | M30: =$N$17*(1-L30) -> 1412.0038 | N30: =$N$17-M30 -> -111.20382
B31: 45323 | C31: 1664.52 | D31: =C31/C32-1 -> 0.16611205 | E31: 0.0078288195 | G31: 19 | H31: =_xlfn.NORM.INV(RAND(),N$13,N$14) -> 0.0058584898
B32: 45170 | C32: 1427.41 | D32: =C32/C33-1 -> -0.24065858 | E32: 0 | G32: 20 | H32: =_xlfn.NORM.INV(RAND(),N$13,N$14) -> 0.036433082
B33: 45658 | C33: 1879.8 | D33: =C33/C34-1 -> 0.33612908 | E33: -0.00010638298 | G33: 21 | H33: =_xlfn.NORM.INV(RAND(),N$13,N$14) -> 0.083726285
B34: 45413 | C34: 1406.9 | D34: =C34/C35-1 -> -0.024205854 | E34: -0.0040280619 | G34: 22 | H34: =_xlfn.NORM.INV(RAND(),N$13,N$14) -> -0.12740363
B35: 45901 | C35: 1441.8 | D35: =C35/C36-1 -> -0.018916712 | E35: -0.018916712 | G35: 23 | H35: =_xlfn.NORM.INV(RAND(),N$13,N$14) -> 0.041183411
B36: 45870 | C36: 1469.6 | D36: =C36/C37-1 -> -0.21646406 | E36: -0.026110007 | G36: 24 | H36: =_xlfn.NORM.INV(RAND(),N$13,N$14) -> 0.032728205
B37: 45536 | C37: 1875.6 | D37: =C37/C38-1 -> 0.49976012 | E37: -0.035036271 | G37: 25 | H37: =_xlfn.NORM.INV(RAND(),N$13,N$14) -> 0.064124205
B38: 46082 | C38: 1250.6 | D38: =C38/C39-1 -> -0.16632225 | E38: -0.038073994 | G38: 26 | H38: =_xlfn.NORM.INV(RAND(),N$13,N$14) -> -0.057865814
B39: 45748 | C39: 1500.1 | D39: =C39/C40-1 -> 0.10242296 | E39: -0.044917709 | G39: 27 | H39: =_xlfn.NORM.INV(RAND(),N$13,N$14) -> 0.082851497
B40: 45200 | C40: 1360.73 | D40: =C40/C41-1 -> -0.036712705 | E40: -0.046713978 | G40: 28 | H40: =_xlfn.NORM.INV(RAND(),N$13,N$14) -> -0.067805796
B41: 45383 | C41: 1412.59 | D41: =C41/C42-1 -> -0.063889993 | E41: -0.051736638 | G41: 29 | H41: =_xlfn.NORM.INV(RAND(),N$13,N$14) -> -0.021904125
B42: 45839 | C42: 1509 | D42: =C42/C43-1 -> -0.14127187 | E42: -0.057934823 | G42: 30 | H42: =_xlfn.NORM.INV(RAND(),N$13,N$14) -> 0.12859802
... B47: 46054 | C47: 1300.1 | D47: =C47/C48-1 -> #DIV/0! | E47: -0.20773918 | G47: 35 | H47: =_xlfn.NORM.INV(RAND(),N$13,N$14) -> 0.082940731
G48: 36 | H48: =_xlfn.NORM.INV(RAND(),N$13,N$14) -> -0.0059682517
G49: 37 | H49: =_xlfn.NORM.INV(RAND(),N$13,N$14) -> 0.11828315
G50: 38 | H50: =_xlfn.NORM.INV(RAND(),N$13,N$14) -> -0.071006974
G51: 39 | H51: =_xlfn.NORM.INV(RAND(),N$13,N$14) -> -0.11711573
G52: 40 | H52: =_xlfn.NORM.INV(RAND(),N$13,N$14) -> 0.060990244
G53: 41 | H53: =_xlfn.NORM.INV(RAND(),N$13,N$14) -> -0.09998761
G54: 42 | H54: =_xlfn.NORM.INV(RAND(),N$13,N$14) -> 0.066477314
G55: 43 | H55: =_xlfn.NORM.INV(RAND(),N$13,N$14) -> -0.0037770756
G56: 44 | H56: =_xlfn.NORM.INV(RAND(),N$13,N$14) -> 0.089712194
G57: 45 | H57: =_xlfn.NORM.INV(RAND(),N$13,N$14) -> -0.049588682
G58: 46 | H58: =_xlfn.NORM.INV(RAND(),N$13,N$14) -> -0.060006751
G59: 47 | H59: =_xlfn.NORM.INV(RAND(),N$13,N$14) -> 0.044998029
... G5012: 5000 | H5012: =_xlfn.NORM.INV(RAND(),N$13,N$14) -> -0.05976595

Sheet Football Field
B4: ='Data Sheet'!$B$1 -> INFOSYS LTD
B5: ( NSE: INFY | BSE: 500209)
B6: 1250
B7: 52 Week (High 1728 & Low 1215)
B10: ="Football Field Analysis" -> Football Field Analysis
L12: Data - FDA
M13: OpenLow | N13: Low | O13: OpenHigh | P13: High
L14: Comps. | M14: 1517 | N14: 1517 | O14: 2537 | P14: 2537
L15: DCF Bear | M15: 654 | N15: 654 | O15: 859 | P15: 859
L16: DCF Base | M16: 701 | N16: 701 | O16: 962 | P16: 962
L17: DCF Bull | M17: 793 | N17: 793 | O17: 1193 | P17: 1193
L18: 52W H/L | M18: 1215 | N18: 1215 | O18: 1728 | P18: 1728

Sheet Dupont
B4: ='Data Sheet'!$B$1 -> INFOSYS LTD
B5: ( NSE: INFY | BSE: 500209)
B6: 1250
B7: 52 Week (High 1728 & Low 1215)
B9: About the Company
B11: Infosys Limited is an Indian multinational technology company that offers information technology, business consulting, and outsourcing services. Founded in 1981 by seven engineers, the company is headquartered in Bengaluru and considered one of the Big Six Indian IT companies.Infosys offers Software development, maintenance, and the independent validation services across industries Such as finance, insurance, manufacturing and among others.
B13: Financial Summary
B36: Recent Updates:
B51: Dupont Analysis - Return on Equity & Return on Assets
B53: Return on Equity (ROE)
C54: ='Data Sheet'!E56 -> 43555 | D54: ='Data Sheet'!F56 -> 43921 | E54: ='Data Sheet'!G56 -> 44286 | F54: ='Data Sheet'!H56 -> 44651 | G54: ='Data Sheet'!I56 -> 45016 | H54: ='Data Sheet'!J56 -> 45382 | I54: ='Data Sheet'!K56 -> 45747
B55: Net Profit | C55: ='Historical FS'!F47 -> 15410 | D55: ='Historical FS'!G47 -> 16639 | E55: ='Historical FS'!H47 -> 19423 | F55: ='Historical FS'!I47 -> 22146 | G55: ='Historical FS'!J47 -> 24108 | H55: ='Historical FS'!K47 -> 26248 | I55: ='Historical FS'!L47 -> 26750
B56: Average Shareholder Equity | C56: =(('Historical FS'!F64+'Historical FS'!F65)+('Historical FS'!E64+'Historical FS'!E65))/2 -> 64935.5 | D56: =(('Historical FS'!G64+'Historical FS'!G65)+('Historical FS'!F64+'Historical FS'!F65))/2 -> 65199 | E56: =(('Historical FS'!H64+'Historical FS'!H65)+('Historical FS'!G64+'Historical FS'!G65))/2 -> 70900.5 | F56: =(('Historical FS'!I64+'Historical FS'!I65)+('Historical FS'!H64+'Historical FS'!H65))/2 -> 75850.5 | G56: =(('Historical FS'!J64+'Historical FS'!J65)+('Historical FS'!I64+'Historical FS'!I65))/2 -> 75378.5 | H56: =(('Historical FS'!K64+'Historical FS'!K65)+('Historical FS'!J64+'Historical FS'!J65))/2 -> 81761.5 | I56: =(('Historical FS'!L64+'Historical FS'!L65)+('Historical FS'!K64+'Historical FS'!K65))/2 -> 91967
B57: Return on Equity | C57: =C55/C56 -> 0.23731241 | D57: =D55/D56 -> 0.2552033 | E57: =E55/E56 -> 0.27394729 | F57: =F55/F56 -> 0.29196907 | G57: =G55/G56 -> 0.31982595 | H57: =H55/H56 -> 0.32103129 | I57: =I55/I56 -> 0.2908652
B59: ROE - Dupont Equation
C60: =C54 -> 43555 | D60: =D54 -> 43921 | E60: =E54 -> 44286 | F60: =F54 -> 44651 | G60: =G54 -> 45016 | H60: =H54 -> 45382 | I60: =I54 -> 45747
B61: =B55 -> Net Profit | C61: =C55 -> 15410 | D61: =D55 -> 16639 | E61: =E55 -> 19423 | F61: =F55 -> 22146 | G61: =G55 -> 24108 | H61: =H55 -> 26248 | I61: =I55 -> 26750
B62: Revenue | C62: ='Historical FS'!F14 -> 82675 | D62: ='Historical FS'!G14 -> 90791 | E62: ='Historical FS'!H14 -> 100472 | F62: ='Historical FS'!I14 -> 121641 | G62: ='Historical FS'!J14 -> 146767 | H62: ='Historical FS'!K14 -> 153670 | I62: ='Historical FS'!L14 -> 162990
B63: Net Profit Margin (A) | C63: =C61/C62 -> 0.1863925 | D63: =D61/D62 -> 0.18326706 | E63: =E61/E62 -> 0.19331754 | F63: =F61/F62 -> 0.18206033 | G63: =G61/G62 -> 0.16426036 | H63: =H61/H62 -> 0.17080757 | I63: =I61/I62 -> 0.1641205
B65: Revenue | C65: =C62 -> 82675 | D65: =D62 -> 90791 | E65: =E62 -> 100472 | F65: =F62 -> 121641 | G65: =G62 -> 146767 | H65: =H62 -> 153670 | I65: =I62 -> 162990
B66: Average Total Assets | C66: =('Historical FS'!F81+'Historical FS'!E81)/2 -> 81707.5 | D66: =('Historical FS'!G81+'Historical FS'!F81)/2 -> 87933 | E66: =('Historical FS'!H81+'Historical FS'!G81)/2 -> 99655.5 | F66: =('Historical FS'!I81+'Historical FS'!H81)/2 -> 112120 | G66: =('Historical FS'!J81+'Historical FS'!I81)/2 -> 120662.5 | H66: =('Historical FS'!K81+'Historical FS'!J81)/2 -> 130978 | I66: =('Historical FS'!L81+'Historical FS'!K81)/2 -> 142577.5
B67: Assets Turnover Ratio (B) | C67: =C65/C66 -> 1.011841 | D67: =D65/D66 -> 1.032502 | E67: =E65/E66 -> 1.0081932 | F67: =F65/F66 -> 1.0849179 | G67: =G65/G66 -> 1.2163431 | H67: =H65/H66 -> 1.1732505 | I67: =I65/I66 -> 1.1431678
B69: =B66 -> Average Total Assets | C69: =C66 -> 81707.5 | D69: =D66 -> 87933 | E69: =E66 -> 99655.5 | F69: =F66 -> 112120 | G69: =G66 -> 120662.5 | H69: =H66 -> 130978 | I69: =I66 -> 142577.5
B70: =B56 -> Average Shareholder Equity | C70: =C56 -> 64935.5 | D70: =D56 -> 65199 | E70: =E56 -> 70900.5 | F70: =F56 -> 75850.5 | G70: =G56 -> 75378.5 | H70: =H56 -> 81761.5 | I70: =I56 -> 91967
B71: Equity Multiplier (C) | C71: =C69/C70 -> 1.2582871 | D71: =D69/D70 -> 1.3486863 | E71: =E69/E70 -> 1.4055684 | F71: =F69/F70 -> 1.4781709 | G71: =G69/G70 -> 1.6007549 | H71: =H69/H70 -> 1.601952 | I71: =I69/I70 -> 1.5503115
B73: Return on Equity ( A*B*C) | C73: =C63*C67*C71 -> 0.23731241 | D73: =D63*D67*D71 -> 0.2552033 | E73: =E63*E67*E71 -> 0.27394729 | F73: =F63*F67*F71 -> 0.29196907 | G73: =G63*G67*G71 -> 0.31982595 | H73: =H63*H67*H71 -> 0.32103129 | I73: =I63*I67*I71 -> 0.2908652
B75: Return on Assets (ROA)
C76: =C54 -> 43555 | D76: =D54 -> 43921 | E76: =E54 -> 44286 | F76: =F54 -> 44651 | G76: =G54 -> 45016 | H76: =H54 -> 45382 | I76: =I54 -> 45747
B77: =B55 -> Net Profit | C77: =C55 -> 15410 | D77: =D55 -> 16639 | E77: =E55 -> 19423 | F77: =F55 -> 22146 | G77: =G55 -> 24108 | H77: =H55 -> 26248 | I77: =I55 -> 26750
B78: =B66 -> Average Total Assets | C78: =C66 -> 81707.5 | D78: =D66 -> 87933 | E78: =E66 -> 99655.5 | F78: =F66 -> 112120 | G78: =G66 -> 120662.5 | H78: =H66 -> 130978 | I78: =I66 -> 142577.5
B79: Return on Assets | C79: =C77/C78 -> 0.18859958 | D79: =D77/D78 -> 0.18922361 | E79: =E77/E78 -> 0.19490144 | F79: =F77/F78 -> 0.19752051 | G79: =G77/G78 -> 0.19979695 | H79: =H77/H78 -> 0.20040007 | I79: =I77/I78 -> 0.18761726
B81: ROA - Dupont Equation
C82: =C76 -> 43555 | D82: =D76 -> 43921 | E82: =E76 -> 44286 | F82: =F76 -> 44651 | G82: =G76 -> 45016 | H82: =H76 -> 45382 | I82: =I76 -> 45747
B83: =B77 -> Net Profit | C83: =C77 -> 15410 | D83: =D77 -> 16639 | E83: =E77 -> 19423 | F83: =F77 -> 22146 | G83: =G77 -> 24108 | H83: =H77 -> 26248 | I83: =I77 -> 26750
B84: Revenue | C84: =C65 -> 82675 | D84: =D65 -> 90791 | E84: =E65 -> 100472 | F84: =F65 -> 121641 | G84: =G65 -> 146767 | H84: =H65 -> 153670 | I84: =I65 -> 162990
B85: Net Profit Margin (A) | C85: =C83/C84 -> 0.1863925 | D85: =D83/D84 -> 0.18326706 | E85: =E83/E84 -> 0.19331754 | F85: =F83/F84 -> 0.18206033 | G85: =G83/G84 -> 0.16426036 | H85: =H83/H84 -> 0.17080757 | I85: =I83/I84 -> 0.1641205
B87: Revenue | C87: =C65 -> 82675 | D87: =D65 -> 90791 | E87: =E65 -> 100472 | F87: =F65 -> 121641 | G87: =G65 -> 146767 | H87: =H65 -> 153670 | I87: =I65 -> 162990
B88: Average Total Assets | C88: =C66 -> 81707.5 | D88: =D66 -> 87933 | E88: =E66 -> 99655.5 | F88: =F66 -> 112120 | G88: =G66 -> 120662.5 | H88: =H66 -> 130978 | I88: =I66 -> 142577.5
B89: Assets Turnover Ratio (B) | C89: =C87/C88 -> 1.011841 | D89: =D87/D88 -> 1.032502 | E89: =E87/E88 -> 1.0081932 | F89: =F87/F88 -> 1.0849179 | G89: =G87/G88 -> 1.2163431 | H89: =H87/H88 -> 1.1732505 | I89: =I87/I88 -> 1.1431678
B91: Return on Assets (A*B) | C91: =C85*C89 -> 0.18859958 | D91: =D85*D89 -> 0.18922361 | E91: =E85*E89 -> 0.19490144 | F91: =F85*F89 -> 0.19752051 | G91: =G85*G89 -> 0.19979695 | H91: =H85*H89 -> 0.20040007 | I91: =I85*I89 -> 0.18761726
B94: Dupont Analysis - Summary

Sheet Altman's Z score
B4: ='Data Sheet'!$B$1 -> INFOSYS LTD
B5: ( NSE: INFY | BSE: 500209)
B6: 1250
B7: 52 Week (High 1728 & Low 1215)
B9: Altman's Z Score Analysis
B11: Infosys Limited is an Indian multinational technology company that offers information technology, business consulting, and outsourcing services. Founded in 1981 by seven engineers, the company is headquartered in Bengaluru and considered one of the Big Six Indian IT companies.Infosys offers Software development, maintenance, and the independent validation services across industries Such as finance, insurance, manufacturing and among others.
B13: Financial Summary
B36: Recent Updates:
B51: Altman's Z Score Analysis Calculation
B53: Liqudity Ratio
C54: ='Data Sheet'!E56 -> 43555 | D54: ='Data Sheet'!F56 -> 43921 | E54: ='Data Sheet'!G56 -> 44286 | F54: ='Data Sheet'!H56 -> 44651 | G54: ='Data Sheet'!I56 -> 45016 | H54: ='Data Sheet'!J56 -> 45382 | I54: ='Data Sheet'!K56 -> 45747
B55: Working Capital | C55: ='Historical FS'!F79-'Historical FS'!F67 -> 36589 | D55: ='Historical FS'!G79-'Historical FS'!G67 -> 36548 | E55: ='Historical FS'!H79-'Historical FS'!H67 -> 41044 | F55: ='Historical FS'!I79-'Historical FS'!I67 -> 34284 | G55: ='Historical FS'!J79-'Historical FS'!J67 -> 34715 | H55: ='Historical FS'!K79-'Historical FS'!K67 -> 43937 | I55: ='Historical FS'!L79-'Historical FS'!L67 -> 48729
B56: Total Assets | C56: ='Historical FS'!F81 -> 84066 | D56: ='Historical FS'!G81 -> 91800 | E56: ='Historical FS'!H81 -> 107511 | F56: ='Historical FS'!I81 -> 116729 | G56: ='Historical FS'!J81 -> 124596 | H56: ='Historical FS'!K81 -> 137360 | I56: ='Historical FS'!L81 -> 147795
B57: Working Capital / Total Assets (A) | C57: =C55/C56 -> 0.43524136 | D57: =D55/D56 -> 0.39812636 | E57: =E55/E56 -> 0.38176559 | F57: =F55/F56 -> 0.29370593 | G57: =G55/G56 -> 0.2786205 | H57: =H55/H56 -> 0.3198675 | I57: =I55/I56 -> 0.32970669
B59: Solvency Ratio
C60: =C54 -> 43555 | D60: =D54 -> 43921 | E60: =E54 -> 44286 | F60: =F54 -> 44651 | G60: =G54 -> 45016 | H60: =H54 -> 45382 | I60: =I54 -> 45747
B61: Retained Earning | C61: =('Historical FS'!F50*'Historical FS'!F52*'Historical FS'!F58) -> 6187.5 | D61: ='Historical FS'!G50*'Historical FS'!G52*'Historical FS'!G58 -> 9212 | E61: ='Historical FS'!H50*'Historical FS'!H52*'Historical FS'!H58 -> 7953.4 | F61: ='Historical FS'!I50*'Historical FS'!I52*'Historical FS'!I58 -> 9138.4 | G61: ='Historical FS'!J50*'Historical FS'!J52*'Historical FS'!J58 -> 10038.8 | H61: ='Historical FS'!K50*'Historical FS'!K52*'Historical FS'!K58 -> 7194.8 | I61: ='Historical FS'!L50*'Historical FS'!L52*'Historical FS'!L58 -> 8922.2
B62: Total Assets | C62: =C56 -> 84066 | D62: =D56 -> 91800 | E62: =E56 -> 107511 | F62: =F56 -> 116729 | G62: =G56 -> 124596 | H62: =H56 -> 137360 | I62: =I56 -> 147795
B63: Retained Earning / Total Assets (B) | C63: =C61/C62 -> 0.073602883 | D63: =D61/D62 -> 0.10034858 | E63: =E61/E62 -> 0.073977546 | F63: =F61/F62 -> 0.078287315 | G63: =G61/G62 -> 0.080570805 | H63: =H61/H62 -> 0.05237915 | I63: =I61/I62 -> 0.060368754
B65: Profitability Ratio
C66: =C60 -> 43555 | D66: =D60 -> 43921 | E66: =E60 -> 44286 | F66: =F60 -> 44651 | G66: =G60 -> 45016 | H66: =H60 -> 45382 | I66: =I60 -> 45747
B67: EBIT | C67: ='Historical FS'!F32 -> 18159 | D67: ='Historical FS'!G32 -> 19374 | E67: ='Historical FS'!H32 -> 24622 | F67: ='Historical FS'!I32 -> 28015 | G67: ='Historical FS'!J32 -> 30905 | H67: ='Historical FS'!K32 -> 31747 | I67: ='Historical FS'!L32 -> 34424
B68: Total Assets | C68: =C62 -> 84066 | D68: =D62 -> 91800 | E68: =E62 -> 107511 | F68: =F62 -> 116729 | G68: =G62 -> 124596 | H68: =H62 -> 137360 | I68: =I62 -> 147795
B69: EBIT / Total Assets (C) | C69: =C67/C68 -> 0.21600885 | D69: =D67/D68 -> 0.21104575 | E69: =E67/E68 -> 0.22901843 | F69: =F67/F68 -> 0.24000034 | G69: =G67/G68 -> 0.24804167 | H69: =H67/H68 -> 0.2311226 | I69: =I67/I68 -> 0.23291722
B71: Solvency Ratio
C72: =C66 -> 43555 | D72: =D66 -> 43921 | E72: =E66 -> 44286 | F72: =F66 -> 44651 | G72: =G66 -> 45016 | H72: =H66 -> 45382 | I72: =I66 -> 45747
B73: Market Cap | C73: =('Data Sheet'!E70*'Data Sheet'!E90)/10000000 -> 322529.97 | D73: =('Data Sheet'!F70*'Data Sheet'!F90)/10000000 -> 272044.32 | E73: =('Data Sheet'!G70*'Data Sheet'!G90)/10000000 -> 580757.21 | F73: =('Data Sheet'!H70*'Data Sheet'!H90)/10000000 -> 799544.67 | G73: =('Data Sheet'!I70*'Data Sheet'!I90)/10000000 -> 590655.51 | H73: =('Data Sheet'!J70*'Data Sheet'!J90)/10000000 -> 620185.3 | I73: =('Data Sheet'!K70*'Data Sheet'!K90)/10000000 -> 650815.72
B74: Long term Liabilities | C74: =C68 -> 84066 | D74: =D68 -> 91800 | E74: =E68 -> 107511 | F74: =F68 -> 116729 | G74: =G68 -> 124596 | H74: =H68 -> 137360 | I74: =I68 -> 147795
B75: Market Cap / Total Liabilities (D) | C75: =C73/C74 -> 3.836628 | D75: =D73/D74 -> 2.9634457 | E75: =E73/E74 -> 5.4018399 | F75: =F73/F74 -> 6.8495804 | G75: =G73/G74 -> 4.7405656 | H75: =H73/H74 -> 4.5150357 | I75: =I73/I74 -> 4.4035029
B77: Activity Ratio
C78: =C54 -> 43555 | D78: =D54 -> 43921 | E78: =E54 -> 44286 | F78: =F54 -> 44651 | G78: =G54 -> 45016 | H78: =H54 -> 45382 | I78: =I54 -> 45747
B79: Sales | C79: ='Historical FS'!F14 -> 82675 | D79: ='Historical FS'!G14 -> 90791 | E79: ='Historical FS'!H14 -> 100472 | F79: ='Historical FS'!I14 -> 121641 | G79: ='Historical FS'!J14 -> 146767 | H79: ='Historical FS'!K14 -> 153670 | I79: ='Historical FS'!L14 -> 162990
B80: =B68 -> Total Assets | C80: =C68 -> 84066 | D80: =D68 -> 91800 | E80: =E68 -> 107511 | F80: =F68 -> 116729 | G80: =G68 -> 124596 | H80: =H68 -> 137360 | I80: =I68 -> 147795
B81: Sales / Total Assets (E) | C81: =C79/C80 -> 0.98345348 | D81: =D79/D80 -> 0.98900871 | E81: =E79/E80 -> 0.93452763 | F81: =F79/F80 -> 1.0420804 | G81: =G79/G80 -> 1.1779431 | H81: =H79/H80 -> 1.1187391 | I81: =I79/I80 -> 1.1028113
B83: Altman's Z Score
C84: =C78 -> 43555 | D84: =D78 -> 43921 | E84: =E78 -> 44286 | F84: =F78 -> 44651 | G84: =G78 -> 45016 | H84: =H78 -> 45382 | I84: =I78 -> 45747
B85: Final Score | C85: =(C57*1.2)+(C63*1.4)+(C69*3.3)+(C75*0.6)+(C81*1) -> 4.6235932 | D85: =(D57*1.2)+(D63*1.4)+(D69*3.3)+(D75*0.6)+(D81*1) -> 4.0817668 | E85: =(E57*1.2)+(E63*1.4)+(E69*3.3)+(E75*0.6)+(E81*1) -> 5.4930797 | F85: =(F57*1.2)+(F63*1.4)+(F69*3.3)+(F75*0.6)+(F81*1) -> 6.4058791 | G85: =(G57*1.2)+(G63*1.4)+(G69*3.3)+(G75*0.6)+(G81*1) -> 5.2879637 | H85: =(H57*1.2)+(H63*1.4)+(H69*3.3)+(H75*0.6)+(H81*1) -> 5.0476369 | I85: =(I57*1.2)+(I63*1.4)+(I69*3.3)+(I75*0.6)+(I81*1) -> 4.9937042
B86: Financial Health | C86: =IF(C85<1.81,"Distressed Zone",IF(C85>2.99,"Safe Zone","Grey Zone")) -> Safe Zone | D86: =IF(D85<1.81,"Distressed Zone",IF(D85>2.99,"Safe Zone","Grey Zone")) -> Safe Zone | E86: =IF(E85<1.81,"Distressed Zone",IF(E85>2.99,"Safe Zone","Grey Zone")) -> Safe Zone | F86: =IF(F85<1.81,"Distressed Zone",IF(F85>2.99,"Safe Zone","Grey Zone")) -> Safe Zone | G86: =IF(G85<1.81,"Distressed Zone",IF(G85>2.99,"Safe Zone","Grey Zone")) -> Safe Zone | H86: =IF(H85<1.81,"Distressed Zone",IF(H85>2.99,"Safe Zone","Grey Zone")) -> Safe Zone | I86: =IF(I85<1.81,"Distressed Zone",IF(I85>2.99,"Safe Zone","Grey Zone")) -> Safe Zone
B88: Altman's Z Score - Summary
B98: Notes:
B99: 1. All data presented in this sheet has been derived from historical income statement, based on previously reported data sourced from screener.in.
B100: 2. Altman's Z score defined as follows - safe zone >2.99, Grey zone 1.81-2.99, Distress Zone < 1.81.

Sheet Data>

Sheet Data Sheet
A1: COMPANY NAME | B1: INFOSYS LTD | E1: =IF(B2<>B3, "A NEW VERSION OF THE WORKSHEET IS AVAILABLE", "")
A2: LATEST VERSION | B2: 2.1 | E2: PLEASE DO NOT MAKE ANY CHANGES TO THIS SHEET
A3: CURRENT VERSION | B3: 2.1
A5: META
A6: Number of shares | B6: =IF(B9>0, B9/B8, 0) -> 405.53911
A7: Face Value | B7: 5
A8: Current Price | B8: 1308.4
A9: Market Capitalization | B9: 530607.37
A15: PROFIT & LOSS
A16: Report Date | B16: 42460 | C16: 42825 | D16: 43190 | E16: 43555 | F16: 43921 | G16: 44286 | H16: 44651 | I16: 45016 | J16: 45382 | K16: 45747
A17: Sales | B17: 62441 | C17: 68484 | D17: 70522 | E17: 82675 | F17: 90791 | G17: 100472 | H17: 121641 | I17: 146767 | J17: 153670 | K17: 162990
A18: Raw Material Cost
A19: Change in Inventory
A20: Power and Fuel | B20: 217 | C20: 228 | D20: 207 | E20: 221 | F20: 229 | G20: 143 | H20: 132 | I20: 176 | J20: 199 | K20: 222
A21: Other Mfr. Exp | B21: 5860 | C21: 6712 | D21: 7286 | E21: 9902 | F21: 11086 | G21: 12800 | H21: 20690 | I21: 26330 | J21: 27195 | K21: 30395
A22: Employee Cost | B22: 34415 | C22: 37669 | D22: 38902 | E22: 45323 | F22: 50895 | G22: 55547 | H22: 63997 | I22: 78374 | J22: 82636 | K22: 85968
A23: Selling and admin | B23: 4441 | C23: 4584 | D23: 4585 | E23: 5553 | F23: 5375 | G23: 3194 | H23: 4305 | I23: 5300 | J23: 5705 | K23: 6039
A24: Other Expenses | B24: 429 | C24: 687 | D24: 720 | E24: 1506 | F24: 939 | G24: 899 | H24: 1026 | I24: 1457 | J24: 1510 | K24: 1130
A25: Other Income | B25: 3120 | C25: 3050 | D25: 3311 | E25: 2882 | F25: 2803 | G25: 2201 | H25: 2295 | I25: 2701 | J25: 4711 | K25: 3600
A26: Depreciation | B26: 1459 | C26: 1703 | D26: 1863 | E26: 2011 | F26: 2893 | G26: 3267 | H26: 3476 | I26: 4225 | J26: 4678 | K26: 4812
A27: Interest | F27: 170 | G27: 195 | H27: 200 | I27: 284 | J27: 470 | K27: 416
A28: Profit before tax | B28: 18740 | C28: 19951 | D28: 20270 | E28: 21041 | F28: 22007 | G28: 26628 | H28: 30110 | I28: 33322 | J28: 35988 | K28: 37608
A29: Tax | B29: 5251 | C29: 5598 | D29: 4241 | E29: 5631 | F29: 5368 | G29: 7205 | H29: 7964 | I29: 9214 | J29: 9740 | K29: 10858
A30: Net profit | B30: 13489 | C30: 14353 | D30: 16029 | E30: 15404 | F30: 16594 | G30: 19351 | H30: 22110 | I30: 24095 | J30: 26233 | K30: 26713
A31: Dividend Amount | B31: 5548.4 | C31: 5891.6 | D31: 9465.6 | E31: 9222.5 | F31: 7427 | G31: 11469.6 | H31: 13007.6 | I31: 14069.2 | J31: 19053.2 | K31: 17827.8
A32: EBITDA | B32: =IFERROR(B17-SUM(B20:B24),0) -> 17079 | C32: =IFERROR(C17-SUM(C20:C24),0) -> 18604 | D32: =IFERROR(D17-SUM(D20:D24),0) -> 18822 | E32: =IFERROR(E17-SUM(E20:E24),0) -> 20170 | F32: =IFERROR(F17-SUM(F20:F24),0) -> 22267 | G32: =IFERROR(G17-SUM(G20:G24),0) -> 27889 | H32: =IFERROR(H17-SUM(H20:H24),0) -> 31491 | I32: =IFERROR(I17-SUM(I20:I24),0) -> 35130 | ... K32: =IFERROR(K17-SUM(K20:K24),0) -> 39236
A40: Quarters
A41: Report Date | B41: 45199 | C41: 45291 | D41: 45382 | E41: 45473 | F41: 45565 | G41: 45657 | H41: 45747 | I41: 45838 | J41: 45930 | K41: 46022
A42: Sales | B42: 38994 | C42: 38821 | D42: 37923 | E42: 39315 | F42: 40986 | G42: 41764 | H42: 40925 | I42: 42279 | J42: 44490 | K42: 45479
A43: Expenses | B43: 29554 | C43: 29684 | D43: 29139 | E43: 29878 | F43: 31177 | G43: 31649 | H43: 31051 | I43: 32336 | J43: 33955 | K43: 34845
A44: Other Income | B44: 632 | C44: 789 | D44: 2729 | E44: 838 | F44: 712 | G44: 859 | H44: 1190 | I44: 1042 | J44: 982 | K44: -150
A45: Depreciation | B45: 1166 | C45: 1176 | D45: 1163 | E45: 1149 | F45: 1160 | G45: 1203 | H45: 1299 | I45: 1140 | J45: 1182 | K45: 1155
A46: Interest | B46: 138 | C46: 131 | D46: 110 | E46: 105 | F46: 108 | G46: 101 | H46: 102 | I46: 105 | J46: 106 | K46: 100
A47: Profit before tax | B47: 8768 | C47: 8619 | D47: 10240 | E47: 9021 | F47: 9253 | G47: 9670 | H47: 9663 | I47: 9740 | J47: 10229 | K47: 9229
A48: Tax | B48: 2553 | C48: 2506 | D48: 2265 | E48: 2647 | F48: 2737 | G48: 2848 | H48: 2625 | I48: 2816 | J48: 2854 | K48: 2563
A49: Net profit | B49: 6212 | C49: 6106 | D49: 7969 | E49: 6368 | F49: 6506 | G49: 6806 | H49: 7033 | I49: 6921 | J49: 7364 | K49: 6654
A50: Operating Profit | B50: 9440 | C50: 9137 | D50: 8784 | E50: 9437 | F50: 9809 | G50: 10115 | H50: 9874 | I50: 9943 | J50: 10535 | K50: 10634
A55: BALANCE SHEET
A56: Report Date | B56: 42460 | C56: 42825 | D56: 43190 | E56: 43555 | F56: 43921 | G56: 44286 | H56: 44651 | I56: 45016 | J56: 45382 | K56: 45747
A57: Equity Share Capital | B57: 1144 | C57: 1144 | D57: 1088 | E57: 2170 | F57: 2122 | G57: 2124 | H57: 2098 | I57: 2069 | J57: 2071 | K57: 2073
A58: Reserves | B58: 60600 | C58: 67838 | D58: 63835 | E58: 62778 | F58: 63328 | G58: 74227 | H58: 73252 | I58: 73338 | J58: 86045 | K58: 93745
A59: Borrowings | F59: 4633 | G59: 5325 | H59: 5474 | I59: 8299 | J59: 8359 | K59: 8227
A60: Other Liabilities | B60: 13354 | C60: 14166 | D60: 14426 | E60: 19118 | F60: 21717 | G60: 25835 | H60: 35905 | I60: 40890 | J60: 40885 | K60: 43750
A61: Total | B61: 75098 | C61: 83148 | D61: 79349 | E61: 84066 | F61: 91800 | G61: 107511 | H61: 116729 | I61: 124596 | J61: 137360 | K61: 147795
A62: Net Block | B62: 13386 | C62: 14179 | D62: 12574 | E62: 15710 | F62: 23789 | G62: 25505 | H62: 25800 | I62: 29225 | J62: 27622 | K62: 30961
A63: Capital Work in Progress | B63: 960 | C63: 1365 | D63: 1606 | E63: 1388 | F63: 954 | G63: 922 | H63: 416 | I63: 288 | J63: 293 | K63: 814
A64: Investments | B64: 1892 | C64: 16423 | D64: 12163 | E64: 11261 | F64: 8792 | G64: 14205 | H64: 20324 | I64: 19478 | J64: 24623 | K64: 23541
A65: Other Assets | B65: 58860 | C65: 51181 | D65: 53006 | E65: 55707 | F65: 58265 | G65: 66879 | H65: 70189 | I65: 75605 | J65: 84822 | K65: 92479
A66: Total | B66: 75098 | C66: 83148 | D66: 79349 | E66: 84066 | F66: 91800 | G66: 107511 | H66: 116729 | I66: 124596 | J66: 137360 | K66: 147795
A67: Receivables | B67: 11330 | C67: 12322 | D67: 13142 | E67: 14827 | F67: 18487 | G67: 19294 | H67: 22698 | I67: 25424 | J67: 30193 | K67: 31158
A68: Inventory
A69: Cash & Bank | B69: 32697 | C69: 22625 | D69: 19818 | E69: 19568 | F69: 18649 | G69: 24714 | H69: 17472 | I69: 12173 | J69: 14786 | K69: 24455
A70: No. of Equity Shares | B70: 2285621088 | C70: 2285655150 | D70: 2173312301 | E70: 4335954462 | F70: 4240753210 | G70: 4245146114 | H70: 4193012929 | I70: 4136387925 | J70: 4139950635 | K70: 4143607528
A71: New Bonus Shares | B71: 1148472332 | E71: 2184191490
A72: Face value | B72: 5 | C72: 5 | D72: 5 | E72: 5 | F72: 5 | G72: 5 | H72: 5 | I72: 5 | J72: 5 | K72: 5
A74: Other Assets | B74: 14833 | C74: 16234 | D74: 20046 | E74: 21312 | F74: 21129 | G74: 22871 | H74: 30019 | I74: 38008 | J74: 39843 | K74: 36866
A80: CASH FLOW:
A81: Report Date | B81: 42460 | C81: 42825 | D81: 43190 | E81: 43555 | F81: 43921 | G81: 44286 | H81: 44651 | I81: 45016 | J81: 45382 | K81: 45747
A82: Cash from Operating Activity | B82: 10028 | C82: 11531 | D82: 13218 | E82: 14841 | F82: 17003 | G82: 23224 | H82: 23885 | I82: 22467 | J82: 25210 | K82: 35694
A83: Cash from Investing Activity | B83: -885 | C83: -14664 | D83: 4533 | E83: -632 | F83: -331 | G83: -7373 | H83: -6485 | I83: -1071 | J83: -5093 | K83: -1864
A84: Cash from Financing Activity | B84: -6813 | C84: -6939 | D84: -20505 | E84: -14512 | F84: -17591 | G84: -9786 | H84: -24642 | I84: -26695 | J84: -17504 | K84: -24161
A85: Net Cash Flow | B85: 2330 | C85: -10072 | D85: -2754 | E85: -303 | F85: -919 | G85: 6065 | H85: -7242 | I85: -5299 | J85: 2613 | K85: 9669
A90: PRICE: | B90: 609.15 | C90: 511.13 | D90: 565.9 | E90: 743.85 | F90: 641.5 | G90: 1368.05 | H90: 1906.85 | I90: 1427.95 | J90: 1498.05 | K90: 1570.65
A92: DERIVED:
A93: Adjusted Equity Shares in Cr | B93: 459.39 | C93: 459.39 | D93: 436.82 | E93: 436.89 | F93: 425.9 | G93: 426.07 | H93: 420.67 | I93: 414.86 | J93: 415.09 | K93: 415.33
A96: Market Cap | B96: =B93*B90 -> 279837.42 | C96: =C93*C90 -> 234808.01 | D96: =D93*D90 -> 247196.44 | E96: =E93*E90 -> 324980.63 | F96: =F93*F90 -> 273214.85 | G96: =G93*G90 -> 582885.06 | H96: =H93*H90 -> 802154.59 | I96: =I93*I90 -> 592399.34 | ... K96: =K93*K90 -> 652338.06
A97: Debt | B97: =B59 -> 0 | C97: =C59 -> 0 | D97: =D59 -> 0 | E97: =E59 -> 0 | F97: =F59 -> 4633 | G97: =G59 -> 5325 | H97: =H59 -> 5474 | I97: =I59 -> 8299 | ... K97: =K59 -> 8227
A98: cash | B98: =B69 -> 32697 | C98: =C69 -> 22625 | D98: =D69 -> 19818 | E98: =E69 -> 19568 | F98: =F69 -> 18649 | G98: =G69 -> 24714 | H98: =H69 -> 17472 | I98: =I69 -> 12173 | ... K98: =K69 -> 24455
A99: EV | B99: =(B96+B97)-B98 -> 247140.42 | C99: =(C96+C97)-C98 -> 212183.01 | D99: =(D96+D97)-D98 -> 227378.44 | E99: =(E96+E97)-E98 -> 305412.63 | F99: =(F96+F97)-F98 -> 259198.85 | G99: =(G96+G97)-G98 -> 563496.06 | H99: =(H96+H97)-H98 -> 790156.59 | I99: =(I96+I97)-I98 -> 588525.34 | ... K99: =(K96+K97)-K98 -> 636110.06
A101: EV/Ebitda | B101: =B99/B32 -> 14.470427 | C101: =C99/C32 -> 11.405236 | D101: =D99/D32 -> 12.080461 | E101: =E99/E32 -> 15.141925 | F101: =F99/F32 -> 11.640493 | G101: =G99/G32 -> 20.204958 | H101: =H99/H32 -> 25.091505 | I101: =I99/I32 -> 16.752785 | ... K101: =K99/K32 -> 16.212409
A102: EV/Sales | B102: =B99/B17 -> 3.957983 | C102: =C99/C17 -> 3.0982859 | D102: =D99/D17 -> 3.2242199 | E102: =E99/E17 -> 3.6941352 | F102: =F99/F17 -> 2.8548959 | G102: =G99/G17 -> 5.6084886 | H102: =H99/H17 -> 6.4958081 | I102: =I99/I17 -> 4.0099296 | ... K102: =K99/K17 -> 3.9027552
A103: Book value | B103: =B57+B58 -> 61744 | C103: =C57+C58 -> 68982 | D103: =D57+D58 -> 64923 | E103: =E57+E58 -> 64948 | F103: =F57+F58 -> 65450 | G103: =G57+G58 -> 76351 | H103: =H57+H58 -> 75350 | I103: =I57+I58 -> 75407 | ... K103: =K57+K58 -> 95818
A105: P/B | B105: =B96/B103 -> 4.5322204 | C105: =C96/C103 -> 3.4039026 | D105: =D96/D103 -> 3.8075326 | E105: =E96/E103 -> 5.0037049 | F105: =F96/F103 -> 4.1744057 | G105: =G96/G103 -> 7.634282 | H105: =H96/H103 -> 10.645715 | I105: =I96/I103 -> 7.8560258 | ... K105: =K96/K103 -> 6.8080952

Sheet P&L
A1: ='[1]Data Sheet'!B1 -> INFOSYS LTD | H1: =UPDATE | M1: SCREENER.IN
A3: Narration | B3: ='[1]Data Sheet'!B16 -> 42460 | C3: ='[1]Data Sheet'!C16 -> 42825 | D3: ='[1]Data Sheet'!D16 -> 43190 | E3: ='[1]Data Sheet'!E16 -> 43555 | F3: ='[1]Data Sheet'!F16 -> 43921 | G3: ='[1]Data Sheet'!G16 -> 44286 | H3: ='[1]Data Sheet'!H16 -> 44651 | I3: ='[1]Data Sheet'!I16 -> 45016 | ... K3: ='[1]Data Sheet'!K16 -> 45747 | L3: Trailing | M3: Best Case | N3: Worst Case
A4: Sales | B4: ='[1]Data Sheet'!B17 -> 62441 | C4: ='[1]Data Sheet'!C17 -> 68484 | D4: ='[1]Data Sheet'!D17 -> 70522 | E4: ='[1]Data Sheet'!E17 -> 82675 | F4: ='[1]Data Sheet'!F17 -> 90791 | G4: ='[1]Data Sheet'!G17 -> 100472 | H4: ='[1]Data Sheet'!H17 -> 121641 | I4: ='[1]Data Sheet'!I17 -> 146767 | ... K4: ='[1]Data Sheet'!K17 -> 162990 | L4: =SUM([1]Quarters!H4:K4) -> 0 | M4: =$K4+M23*K4 -> 179688.91 | N4: =$K4+N23*L4 -> 162990
A5: Expenses | B5: =SUM('[1]Data Sheet'!B18,'[1]Data Sheet'!B20:B24, -1*'[1]Data Sheet'!B19) -> 45362 | C5: =SUM('[1]Data Sheet'!C18,'[1]Data Sheet'!C20:C24, -1*'[1]Data Sheet'!C19) -> 49880 | D5: =SUM('[1]Data Sheet'!D18,'[1]Data Sheet'!D20:D24, -1*'[1]Data Sheet'!D19) -> 51700 | E5: =SUM('[1]Data Sheet'!E18,'[1]Data Sheet'!E20:E24, -1*'[1]Data Sheet'!E19) -> 62505 | F5: =SUM('[1]Data Sheet'!F18,'[1]Data Sheet'!F20:F24, -1*'[1]Data Sheet'!F19) -> 68524 | G5: =SUM('[1]Data Sheet'!G18,'[1]Data Sheet'!G20:G24, -1*'[1]Data Sheet'!G19) -> 72583 | H5: =SUM('[1]Data Sheet'!H18,'[1]Data Sheet'!H20:H24, -1*'[1]Data Sheet'!H19) -> 90150 | I5: =SUM('[1]Data Sheet'!I18,'[1]Data Sheet'!I20:I24, -1*'[1]Data Sheet'!I19) -> 111637 | ... K5: =SUM('[1]Data Sheet'!K18,'[1]Data Sheet'!K20:K24, -1*'[1]Data Sheet'!K19) -> 123754 | L5: =SUM([1]Quarters!H5:K5) -> 0 | M5: =M4-M6 -> 136730.88 | N5: =N4-N6 -> 162990
A6: Operating Profit | B6: =B4-B5 -> 17079 | C6: =C4-C5 -> 18604 | D6: =D4-D5 -> 18822 | E6: =E4-E5 -> 20170 | F6: =F4-F5 -> 22267 | G6: =G4-G5 -> 27889 | H6: =H4-H5 -> 31491 | I6: =I4-I5 -> 35130 | ... K6: =K4-K5 -> 39236 | L6: =SUM([1]Quarters!H6:K6) -> 0 | M6: =M4*M24 -> 42958.038 | N6: =N4*N24 -> 0
A7: Other Income | B7: ='[1]Data Sheet'!B25 -> 3120 | C7: ='[1]Data Sheet'!C25 -> 3050 | D7: ='[1]Data Sheet'!D25 -> 3311 | E7: ='[1]Data Sheet'!E25 -> 2882 | F7: ='[1]Data Sheet'!F25 -> 2803 | G7: ='[1]Data Sheet'!G25 -> 2201 | H7: ='[1]Data Sheet'!H25 -> 2295 | I7: ='[1]Data Sheet'!I25 -> 2701 | ... K7: ='[1]Data Sheet'!K25 -> 3600 | L7: =SUM([1]Quarters!H7:K7) -> 0 | M7: 0 | N7: 0
A8: Depreciation | B8: ='[1]Data Sheet'!B26 -> 1459 | C8: ='[1]Data Sheet'!C26 -> 1703 | D8: ='[1]Data Sheet'!D26 -> 1863 | E8: ='[1]Data Sheet'!E26 -> 2011 | F8: ='[1]Data Sheet'!F26 -> 2893 | G8: ='[1]Data Sheet'!G26 -> 3267 | H8: ='[1]Data Sheet'!H26 -> 3476 | I8: ='[1]Data Sheet'!I26 -> 4225 | ... K8: ='[1]Data Sheet'!K26 -> 4812 | L8: =SUM([1]Quarters!H8:K8) -> 0 | M8: =+$L8 -> 0 | N8: =+$L8 -> 0
A9: Interest | B9: ='[1]Data Sheet'!B27 -> 0 | C9: ='[1]Data Sheet'!C27 -> 0 | D9: ='[1]Data Sheet'!D27 -> 0 | E9: ='[1]Data Sheet'!E27 -> 0 | F9: ='[1]Data Sheet'!F27 -> 170 | G9: ='[1]Data Sheet'!G27 -> 195 | H9: ='[1]Data Sheet'!H27 -> 200 | I9: ='[1]Data Sheet'!I27 -> 284 | ... K9: ='[1]Data Sheet'!K27 -> 416 | L9: =SUM([1]Quarters!H9:K9) -> 0 | M9: =+$L9 -> 0 | N9: =+$L9 -> 0
A10: Profit before tax | B10: ='[1]Data Sheet'!B28 -> 18740 | C10: ='[1]Data Sheet'!C28 -> 19951 | D10: ='[1]Data Sheet'!D28 -> 20270 | E10: ='[1]Data Sheet'!E28 -> 21041 | F10: ='[1]Data Sheet'!F28 -> 22007 | G10: ='[1]Data Sheet'!G28 -> 26628 | H10: ='[1]Data Sheet'!H28 -> 30110 | I10: ='[1]Data Sheet'!I28 -> 33322 | ... K10: ='[1]Data Sheet'!K28 -> 37608 | L10: =SUM([1]Quarters!H10:K10) -> 0 | M10: =M6+M7-SUM(M8:M9) -> 42958.038 | N10: =N6+N7-SUM(N8:N9) -> 0
A11: Tax | B11: ='[1]Data Sheet'!B29 -> 5251 | C11: ='[1]Data Sheet'!C29 -> 5598 | D11: ='[1]Data Sheet'!D29 -> 4241 | E11: ='[1]Data Sheet'!E29 -> 5631 | F11: ='[1]Data Sheet'!F29 -> 5368 | G11: ='[1]Data Sheet'!G29 -> 7205 | H11: ='[1]Data Sheet'!H29 -> 7964 | I11: ='[1]Data Sheet'!I29 -> 9214 | ... K11: ='[1]Data Sheet'!K29 -> 10858 | L11: =SUM([1]Quarters!H11:K11) -> 0 | M11: =IF($L10>0,$L11/$L10,0) -> 0 | N11: =IF($L10>0,$L11/$L10,0) -> 0
A12: Net profit | B12: ='[1]Data Sheet'!B30 -> 13489 | C12: ='[1]Data Sheet'!C30 -> 14353 | D12: ='[1]Data Sheet'!D30 -> 16029 | E12: ='[1]Data Sheet'!E30 -> 15404 | F12: ='[1]Data Sheet'!F30 -> 16594 | G12: ='[1]Data Sheet'!G30 -> 19351 | H12: ='[1]Data Sheet'!H30 -> 22110 | I12: ='[1]Data Sheet'!I30 -> 24095 | ... K12: ='[1]Data Sheet'!K30 -> 26713 | L12: =SUM([1]Quarters!H12:K12) -> 0 | M12: =M10-M11*M10 -> 42958.038 | N12: =N10-N11*N10 -> 0
A13: EPS | B13: =IF('[1]Data Sheet'!B93>0,B12/'[1]Data Sheet'!B93,0) -> 29.362851 | C13: =IF('[1]Data Sheet'!C93>0,C12/'[1]Data Sheet'!C93,0) -> 31.243606 | D13: =IF('[1]Data Sheet'!D93>0,D12/'[1]Data Sheet'!D93,0) -> 36.694748 | E13: =IF('[1]Data Sheet'!E93>0,E12/'[1]Data Sheet'!E93,0) -> 35.258303 | F13: =IF('[1]Data Sheet'!F93>0,F12/'[1]Data Sheet'!F93,0) -> 38.962198 | G13: =IF('[1]Data Sheet'!G93>0,G12/'[1]Data Sheet'!G93,0) -> 45.41742 | H13: =IF('[1]Data Sheet'!H93>0,H12/'[1]Data Sheet'!H93,0) -> 52.559013 | I13: =IF('[1]Data Sheet'!I93>0,I12/'[1]Data Sheet'!I93,0) -> 58.079834 | ... K13: =IF('[1]Data Sheet'!K93>0,K12/'[1]Data Sheet'!K93,0) -> 64.317531 | L13: =IF('[1]Data Sheet'!$B6>0,'[1]Profit & Loss'!L12/'[1]Data Sheet'!$B6,0) -> 0 | M13: =IF('[1]Data Sheet'!$B6>0,'[1]Profit & Loss'!M12/'[1]Data Sheet'!$B6,0) -> 0 | N13: =IF('[1]Data Sheet'!$B6>0,'[1]Profit & Loss'!N12/'[1]Data Sheet'!$B6,0) -> 0
A14: Price to earning | B14: =IF(B15>0,B15/B13,"") -> 20.745601 | C14: =IF(C15>0,C15/C13,"") -> 16.359507 | D14: =IF(D15>0,D15/D13,"") -> 15.421825 | E14: =IF(E15>0,E15/E13,"") -> 21.097158 | F14: =IF(F15>0,F15/F13,"") -> 16.464677 | G14: =IF(G15>0,G15/G13,"") -> 30.121702 | H14: =IF(H15>0,H15/H13,"") -> 36.280171 | I14: =IF(I15>0,I15/I13,"") -> 24.585986 | ... K14: =IF(K15>0,K15/K13,"") -> 24.420247 | L14: =IF(L13>0,L15/L13,0) -> 0 | M14: =M25 -> 24.236726 | N14: =N25 -> 0
A15: Price | B15: ='[1]Data Sheet'!B90 -> 609.15 | C15: ='[1]Data Sheet'!C90 -> 511.13 | D15: ='[1]Data Sheet'!D90 -> 565.9 | E15: ='[1]Data Sheet'!E90 -> 743.85 | F15: ='[1]Data Sheet'!F90 -> 641.5 | G15: ='[1]Data Sheet'!G90 -> 1368.05 | H15: ='[1]Data Sheet'!H90 -> 1906.85 | I15: ='[1]Data Sheet'!I90 -> 1427.95 | ... K15: ='[1]Data Sheet'!K90 -> 1570.65 | L15: ='[1]Data Sheet'!B8 -> 1300.8 | M15: =M13*M14 -> 0 | N15: =N13*N14 -> 0
A17: RATIOS:
A18: Dividend Payout | B18: =IF('[1]Data Sheet'!B30>0, '[1]Data Sheet'!B31/'[1]Data Sheet'!B30, 0) -> 0.41132775 | C18: =IF('[1]Data Sheet'!C30>0, '[1]Data Sheet'!C31/'[1]Data Sheet'!C30, 0) -> 0.41047865 | D18: =IF('[1]Data Sheet'!D30>0, '[1]Data Sheet'!D31/'[1]Data Sheet'!D30, 0) -> 0.59052966 | E18: =IF('[1]Data Sheet'!E30>0, '[1]Data Sheet'!E31/'[1]Data Sheet'!E30, 0) -> 0.59870813 | F18: =IF('[1]Data Sheet'!F30>0, '[1]Data Sheet'!F31/'[1]Data Sheet'!F30, 0) -> 0.44757141 | G18: =IF('[1]Data Sheet'!G30>0, '[1]Data Sheet'!G31/'[1]Data Sheet'!G30, 0) -> 0.59271355 | H18: =IF('[1]Data Sheet'!H30>0, '[1]Data Sheet'!H31/'[1]Data Sheet'!H30, 0) -> 0.58831298 | I18: =IF('[1]Data Sheet'!I30>0, '[1]Data Sheet'!I31/'[1]Data Sheet'!I30, 0) -> 0.58390537 | ... K18: =IF('[1]Data Sheet'!K30>0, '[1]Data Sheet'!K31/'[1]Data Sheet'!K30, 0) -> 0.66738292
A19: OPM | B19: =IF(B6>0,B6/B4,0) -> 0.2735222 | C19: =IF(C6>0,C6/C4,0) -> 0.27165469 | D19: =IF(D6>0,D6/D4,0) -> 0.26689544 | E19: =IF(E6>0,E6/E4,0) -> 0.24396734 | F19: =IF(F6>0,F6/F4,0) -> 0.24525559 | G19: =IF(G6>0,G6/G4,0) -> 0.27757982 | H19: =IF(H6>0,H6/H4,0) -> 0.25888475 | I19: =IF(I6>0,I6/I4,0) -> 0.23935898 | ... L19: =IF(L6>0,L6/L4,0) -> 0
G22: TRENDS: | H22: 10 YEARS | I22: 7 YEARS | J22: 5 YEARS | K22: 3 YEARS | L22: RECENT | M22: BEST | N22: WORST
G23: Sales Growth | H23: =IF(B4=0,"",POWER($K4/B4,1/9)-1) -> 0.11249742 | I23: =IF(D4=0,"",POWER($K4/D4,1/7)-1) -> 0.12713678 | J23: =IF(F4=0,"",POWER($K4/F4,1/5)-1) -> 0.12414836 | K23: =IF(H4=0,"",POWER($K4/H4, 1/3)-1) -> 0.10245362 | L23: =IF(ISERROR(MAX(IF(J4=0,"",(K4-J4)/J4),IF(K4=0,"",(L4-K4)/K4))),"",MAX(IF(J4=0,"",(K4-J4)/J4),IF(K4=0,"",(L4-K4)/K4))) -> 0.060649444 | M23: =MAX(K23:L23) -> 0.10245362 | N23: =MIN(H23:L23) -> 0.060649444
G24: OPM | H24: =IF(SUM(B4:$K$4)=0,"",SUMPRODUCT(B19:$K$19,B4:$K$4)/SUM(B4:$K$4)) -> 0.25188575 | I24: =IF(SUM(E4:$K$4)=0,"",SUMPRODUCT(E19:$K$19,E4:$K$4)/SUM(E4:$K$4)) -> 0.24750467 | J24: =IF(SUM(G4:$K$4)=0,"",SUMPRODUCT(G19:$K$19,G4:$K$4)/SUM(G4:$K$4)) -> 0.24822913 | K24: =IF(SUM(I4:$K$4)=0, "", SUMPRODUCT(I19:$K$19,I4:$K$4)/SUM(I4:$K$4)) -> 0.23906894 | L24: =L19 -> 0 | M24: =MAX(K24:L24) -> 0.23906894 | N24: =MIN(H24:L24) -> 0
G25: Price to Earning | H25: =IF(ISERROR(AVERAGEIF(B14:$L14,">0")),"",AVERAGEIF(B14:$L14,">0")) -> 22.920082 | I25: =IF(ISERROR(AVERAGEIF(E14:$L14,">0")),"",AVERAGEIF(E14:$L14,">0")) -> 25.239127 | J25: =IF(ISERROR(AVERAGEIF(G14:$L14,">0")),"",AVERAGEIF(G14:$L14,">0")) -> 27.82241 | K25: =IF(ISERROR(AVERAGEIF(I14:$L14,">0")),"",AVERAGEIF(I14:$L14,">0")) -> 24.236726 | L25: =L14 -> 0 | M25: =MAX(K25:L25) -> 24.236726 | N25: =MIN(H25:L25) -> 0

Sheet Raw CF
C2: 41699 | D2: 42064 | E2: 42430 | F2: 42795 | G2: 43160 | H2: 43525 | I2: 43891 | J2: 44256 | K2: 44621 | L2: 44986 | M2: 45352 | N2: 45717
B3: Cash from Operating Activity - | C3: 9825 | D3: 8353 | E3: 10028 | F3: 11531 | G3: 13218 | H3: 14841 | I3: 17003 | J3: 23224 | K3: 23885 | L3: 22467 | M3: 25210 | N3: 35694
B4: Profit from operations | C4: 14172 | D4: 15946 | E4: 17839 | F4: 19340 | G4: 19963 | H4: 22126 | I4: 23920 | J4: 28845 | K4: 32921 | L4: 37605 | M4: 39523 | N4: 41591
B5: Receivables | C5: -1406 | D5: -1475 | E5: -1654 | F5: -1743 | G5: -1523 | H5: -2881 | I5: -3861 | J5: -1835 | K5: -7937 | L5: -7076 | M5: -2667 | N5: -1769
B6: Payables | C6: 0 | D6: 0 | E6: 242 | F6: -19 | G6: 328 | H6: 916 | I6: -373 | J6: -245 | K6: 1489 | L6: -279 | M6: 91 | N6: 176
B7: Loans Advances | C7: -1060 | D7: -221 | E7: -1134 | F7: 0 | G7: 0 | H7: 0 | I7: 0 | J7: -534 | K7: -1914 | L7: -3108 | M7: -1172 | N7: -1024
B8: Other WC items | C8: 1993 | D8: 854 | E8: 600 | F8: -394 | G8: 1279 | H8: 1512 | I8: 1867 | J8: 3382 | K8: 6938 | L8: 4119 | M8: -1334 | N8: 2322
B9: Working capital changes | C9: -473 | D9: -842 | E9: -1946 | F9: -2156 | G9: 84 | H9: -453 | I9: -2367 | J9: 768 | K9: -1424 | L9: -6344 | M9: -5082 | N9: -295
B10: Direct taxes | C10: -3874 | D10: -6751 | E10: -5865 | F10: -5653 | G10: -6829 | H10: -6832 | I10: -4550 | J10: -6389 | K10: -7612 | L10: -8794 | M10: -9231 | N10: -5602
B11: Cash from Investing Activity - | C11: -2563 | D11: 999 | E11: -885 | F11: -14664 | G11: 4533 | H11: -632 | I11: -331 | J11: -7373 | K11: -6485 | L11: -1071 | M11: -5093 | N11: -1864
B12: Fixed assets purchased | C12: -2748 | D12: -2247 | E12: -2723 | F12: -2760 | G12: -1998 | H12: -2445 | I12: -3307 | J12: -2107 | K12: -2161 | L12: -2579 | M12: -2201 | N12: -2237
B13: Fixed assets sold | C13: 3 | D13: 0 | E13: 0 | F13: 0 | G13: 0 | H13: 0 | I13: 0 | J13: 0 | K13: 0 | L13: 0 | M13: 0 | N13: 0
B14: Investments purchased | C14: -25046 | D14: -23923 | E14: -24577 | F14: -66410 | G14: -69159 | H14: -79410 | I14: -37482 | J14: -46738 | K14: -59951 | L14: -75800 | M14: -78118 | N14: -82753
... B27: Net Cash Flow | C27: 4118 | D27: 4417 | E27: 2330 | F27: -10072 | G27: -2754 | H27: -303 | I27: -919 | J27: 6065 | K27: -7242 | L27: -5299 | M27: 2613 | N27: 9669
D30: Shareholder's name | E30: Total Shares Held | F30: Shareholding (%) | G30: Market Value | I30: 10000000
D31: LIFE INSURANCE CORPORATION OF INDIA - ULIF00220091 | E31: 41.930862 | F31: 0.1128 | G31: =1297.5*E31 -> 54405.293 | I31: 1297.5
D32: SBI MUTUAL FUND | E32: 17.329272 | F32: 0.0466 | G32: =1297.5*E32 -> 22484.73 | I32: 100
D33: ICICI PRUDENTIAL MUTUAL FUND | E33: 15.288944 | F33: 0.0411 | G33: =1297.5*E33 -> 19837.405
D34: National Pension System Trust | E34: 10.006455 | F34: 0.0269 | G34: =1297.5*E34 -> 12983.375
D35: SUDHA GOPALAKRISHNAN | E35: 9.5357 | F35: 0.0257 | G35: =1297.5*E35 -> 12372.571
D36: HDFC MUTUAL FUND | E36: 6.8989087 | F36: 0.0186 | G36: =1297.5*E36 -> 8951.334
D37: UTI MUTUAL FUND | E37: 6.7112909 | F37: 0.0181 | G37: =1297.5*E37 -> 8707.8999
D38: NIPPON LIFE INDIA TRUSTEE | E38: 6.5708729 | F38: 0.0177 | G38: =1297.5*E38 -> 8525.7076
D39: ROHAN MURTY | E39: 6.0812892 | F39: 0.0164 | G39: =1297.5*E39 -> 7890.4727
D40: VANGUARD TOTAL INTERNATIONAL STOCK INDEX FUND | E40: 5.139239 | F40: 0.0138 | G40: =1297.5*E40 -> 6668.1626
D43: Promotors | E43: 0.1452
D44: FII | E44: 0.3027
D45: DII | E45: 0.4108
D46: Government, Public & Others | E46: 0.1413

Sheet Raw BS
C3: 42430 | D3: 42795 | E3: 43160 | F3: 43525 | G3: 43891 | H3: 44256 | I3: 44621 | J3: 44986 | K3: 45352 | L3: 45717
B5: Equity Capital | C5: 1144 | D5: 1144 | E5: 1088 | F5: 2170 | G5: 2122 | H5: 2124 | I5: 2098 | J5: 2069 | K5: 2071 | L5: 2073
B6: Reserves | C6: 60600 | D6: 67838 | E6: 63835 | F6: 62778 | G6: 63328 | H6: 74227 | I6: 73252 | J6: 73338 | K6: 86045 | L6: 93745
B8: Borrowings -
B9: Lease Liabilities | C9: 0 | D9: 0 | E9: 0 | F9: 0 | G9: 4633 | H9: 5325 | I9: 5474 | J9: 8299 | K9: 8359 | L9: 8227
B11: Other Liabilities -
B12: Non controlling int | C12: 0 | D12: 0 | E12: 1 | F12: 58 | G12: 394 | H12: 431 | I12: 386 | J12: 388 | K12: 345 | L12: 385
B13: Trade Payables | C13: 386 | D13: 367 | E13: 694 | F13: 1655 | G13: 2852 | H13: 2645 | I13: 4134 | J13: 3865 | K13: 3956 | L13: 4164
B14: Advance from Customers | C14: 28 | D14: 0 | E14: 0 | F14: 0 | G14: 0 | H14: 0 | I14: 0 | J14: 0 | K14: 0 | L14: 0
B15: Other liability items | C15: 12940 | D15: 13799 | E15: 13731 | F15: 17405 | G15: 18471 | H15: 22759 | I15: 31385 | J15: 36637 | K15: 36584 | L15: 39201
B16: Total Liabilities | C16: 75098 | D16: 83148 | E16: 79349 | F16: 84066 | G16: 91800 | H16: 107511 | I16: 116729 | J16: 124596 | K16: 137360 | L16: 147795
B18: Fixed Assets -
B19: Land | C19: 1622 | D19: 1095 | E19: 1229 | F19: 1307 | G19: 1950 | H19: 2036 | I19: 2065 | J19: 2054 | K19: 2037 | L19: 2079
B20: Building | C20: 6325 | D20: 8419 | E20: 9334 | F20: 10270 | G20: 15104 | H20: 16328 | I20: 16761 | J20: 16903 | K20: 16515 | L20: 16376
B21: Plant Machinery | C21: 1759 | D21: 2048 | E21: 2306 | F21: 2709 | G21: 3185 | H21: 3296 | I21: 3210 | J21: 3302 | K21: 3428 | L21: 3461
B22: Equipments | C22: 839 | D22: 922 | E22: 1002 | F22: 1101 | G22: 1265 | H22: 1371 | I22: 1427 | J22: 1482 | K22: 1528 | L22: 1628
B23: Computers | C23: 4486 | D23: 4945 | E23: 4903 | F23: 6287 | G23: 7423 | H23: 8650 | I23: 9936 | J23: 11898 | K23: 12353 | L23: 12925
B24: Furniture n fittings | C24: 1444 | D24: 1277 | E24: 1393 | F24: 1620 | G24: 2073 | H24: 2149 | I24: 2279 | J24: 2303 | K24: 2326 | L24: 2340
B25: Vehicles | C25: 29 | D25: 31 | E25: 31 | F25: 38 | G25: 69 | H25: 74 | I25: 71 | J25: 60 | K25: 62 | L25: 72
B26: Intangible Assets | C26: 3858 | D26: 3743 | E26: 2237 | F26: 3640 | G26: 5527 | H26: 6372 | I26: 6495 | J26: 7594 | K26: 7653 | L26: 10626
B27: Other fixed assets | C27: 931 | D27: 899 | E27: 545 | F27: 1093 | G27: 2289 | H27: 2730 | I27: 2766 | J27: 3281 | K27: 3294 | L27: 5184
B29: Gross Block | C29: 21293 | D29: 23379 | E29: 22980 | F29: 28065 | G29: 38885 | H29: 43006 | I29: 45010 | J29: 48877 | K29: 49196 | L29: 54691
B31: Accumulated Depreciation | C31: 7907 | D31: 9200 | E31: 10406 | F31: 12355 | G31: 15096 | H31: 17501 | I31: 19210 | J31: 19652 | K31: 21574 | L31: 23730
B33: CWIP | C33: 960 | D33: 1365 | E33: 1606 | F33: 1388 | G33: 954 | H33: 922 | I33: 416 | J33: 288 | K33: 293 | L33: 814
B34: Investments | C34: 1892 | D34: 16423 | E34: 12163 | F34: 11261 | G34: 8792 | H34: 14205 | I34: 20324 | J34: 19478 | K34: 24623 | L34: 23541
B36: Other Assets -
B37: Trade receivables | C37: 11330 | D37: 12322 | E37: 13142 | F37: 14827 | G37: 18487 | H37: 19294 | I37: 22698 | J37: 25424 | K37: 30193 | L37: 31158
B38: Cash Equivalents | C38: 32697 | D38: 22625 | E38: 19818 | F38: 19568 | G38: 18649 | H38: 24714 | I38: 17472 | J38: 12173 | K38: 14786 | L38: 24455
B39: Loans n Advances | C39: 614 | D39: 844 | E39: 830 | F39: 1524 | G39: 1359 | H39: 1460 | I39: 2491 | J39: 3242 | K39: 10330 | L39: 6717
B40: Other asset items | C40: 14219 | D40: 15390 | E40: 19216 | F40: 19788 | G40: 19770 | H40: wvg | I40: 27528 | J40: 34766 | K40: 29513 | L40: 30149
B41: Total Assets | C41: 75098 | D41: 83148 | E41: 79349 | F41: 84066 | G41: 91800 | H41: 107511 | I41: 116729 | J41: 124596 | K41: 137360 | L41: 147795
E43: =10545-13386 -> -2841

Sheet Raw Comp_val.
B2: S.No. | C2: Name | D2: CMP Rs. | E2: No. Eq. Shares Cr. | F2: Market Cap | G2: Debt Rs.Cr. | H2: Cash End Rs.Cr. | I2: Net debt | J2: EV | K2: Sales Rs.Cr. | L2: EV / EBITDA | M2: EBITDA | N2: NP 12M Rs.Cr.
B3: 1 | C3: TCS | D3: 2390.6 | E3: 361.81 | F3: =D3*E3 -> 864942.99 | G3: 10932 | H3: 15463 | I3: =G3-H3 -> -4531 | J3: =F3+G3-H3 -> 860411.99 | K3: 260802 | L3: 11.52 | M3: =J3/L3 -> 74688.54 | N3: 47963
B4: 2 | C4: Infosys | D4: 1255.9 | E4: 405.54 | F4: =D4*E4 -> 509317.69 | G4: 8796 | H4: 24455 | I4: =G4-H4 -> -15659 | J4: =F4+G4-H4 -> 493658.69 | K4: 173173 | L4: 10.99 | M4: =J4/L4 -> 44918.898 | N4: 28003
B5: 3 | C5: HCL Technologies | D5: 1333.7 | E5: 271.37 | F5: =D5*E5 -> 361926.17 | G5: 6780 | H5: 21289 | I5: =G5-H5 -> -14509 | J5: =F5+G5-H5 -> 347417.17 | K5: 126409 | L5: 12.24 | M5: =J5/L5 -> 28383.756 | N5: 16471
B6: 4 | C6: Wipro | D6: 190.9 | E6: 1048.84 | F6: =D6*E6 -> 200223.56 | G6: 16163.7 | H6: 12197.4 | I6: =G6-H6 -> 3966.3 | J6: =F6+G6-H6 -> 204189.86 | K6: 90891.9 | L6: 9.33 | M6: =J6/L6 -> 21885.301 | N6: 13332
B7: 5 | C7: Tech Mahindra | D7: 1384.8 | E7: 97.98 | F7: =D7*E7 -> 135682.7 | G7: 1954.4 | H7: 4542.2 | I7: =G7-H7 -> -2587.8 | J7: =F7+G7-H7 -> 133094.9 | K7: 55123.3 | L7: 15.3 | M7: =J7/L7 -> 8699.0133 | N7: 4591
B8: 6 | C8: LTIMindtree | D8: 4298.8 | E8: 29.65 | F8: =D8*E8 -> 127459.42 | G8: 2382.6 | H8: 3588.2 | I8: =G8-H8 -> -1205.6 | J8: =F8+G8-H8 -> 126253.82 | K8: 40787.6 | L8: 15.19 | M8: =J8/L8 -> 8311.6406 | N8: 4724
B9: 7 | C9: Persistent Systems | D9: 4716.7 | E9: 15.78 | F9: =D9*E9 -> 74429.526 | G9: 403.94 | H9: 1025.47 | I9: =G9-H9 -> -621.53 | J9: =F9+G9-H9 -> 73807.996 | K9: 13934.63 | L9: 26.5 | M9: =J9/L9 -> 2785.2074 | N9: 1731.62

Sheet share Price
B2: Date | C2: Price | D2: Vol. | E2: volume
B3: 46111 | C3: 1250.6 | D3: 14.11M | E3: =(VALUE(LEFT(D3,LEN(D3)-1)*1000000))/100000 -> 141.1 | F3: 100000
B4: 46108 | C4: 1269.7 | D4: 13.09M | E4: =(VALUE(LEFT(D4,LEN(D4)-1)*1000000))/100000 -> 130.9
B5: 46106 | C5: 1279.1 | D5: 10.82M | E5: =(VALUE(LEFT(D5,LEN(D5)-1)*1000000))/100000 -> 108.2
B6: 46105 | C6: 1278.3 | D6: 13.61M | E6: =(VALUE(LEFT(D6,LEN(D6)-1)*1000000))/100000 -> 136.1
B7: 46104 | C7: 1256.8 | D7: 12.42M | E7: =(VALUE(LEFT(D7,LEN(D7)-1)*1000000))/100000 -> 124.2
B8: 46101 | C8: 1255.9 | D8: 27.30M | E8: =(VALUE(LEFT(D8,LEN(D8)-1)*1000000))/100000 -> 273
B9: 46100 | C9: 1220.8 | D9: 9.16M | E9: =(VALUE(LEFT(D9,LEN(D9)-1)*1000000))/100000 -> 91.6
B10: 46099 | C10: 1267.1 | D10: 12.37M | E10: =(VALUE(LEFT(D10,LEN(D10)-1)*1000000))/100000 -> 123.7
B11: 46098 | C11: 1232.9 | D11: 11.22M | E11: =(VALUE(LEFT(D11,LEN(D11)-1)*1000000))/100000 -> 112.2
B12: 46097 | C12: 1249.8 | D12: 12.31M | E12: =(VALUE(LEFT(D12,LEN(D12)-1)*1000000))/100000 -> 123.1
B13: 46094 | C13: 1248.3 | D13: 7.37M | E13: =(VALUE(LEFT(D13,LEN(D13)-1)*1000000))/100000 -> 73.7
B14: 46093 | C14: 1265.8 | D14: 7.60M | E14: =(VALUE(LEFT(D14,LEN(D14)-1)*1000000))/100000 -> 76
B15: 46092 | C15: 1276.3 | D15: 7.87M | E15: =(VALUE(LEFT(D15,LEN(D15)-1)*1000000))/100000 -> 78.7
... B350: 45600 | C350: 1763.65 | D350: 7.34M | E350: =(VALUE(LEFT(D350,LEN(D350)-1)*1000000))/100000 -> 73.4
B351: 45597 | C351: 1760.85 | D351: 371.97K | E351: =(VALUE(LEFT(D351,LEN(D351)-1)*1000))/100000 -> 3.7197
B352: 45596 | C352: 1757.25 | D352: 7.40M | E352: =(VALUE(LEFT(D352,LEN(D352)-1)*1000000))/100000 -> 74
B353: 45595 | C353: 1802.1 | D353: 5.92M | E353: =(VALUE(LEFT(D353,LEN(D353)-1)*1000000))/100000 -> 59.2
B354: 45594 | C354: 1839.3 | D354: 4.62M | E354: =(VALUE(LEFT(D354,LEN(D354)-1)*1000000))/100000 -> 46.2
B355: 45593 | C355: 1865.35 | D355: 7.02M | E355: =(VALUE(LEFT(D355,LEN(D355)-1)*1000000))/100000 -> 70.2
B356: 45590 | C356: 1862.05 | D356: 4.69M | E356: =(VALUE(LEFT(D356,LEN(D356)-1)*1000000))/100000 -> 46.9
B357: 45589 | C357: 1863.35 | D357: 2.91M | E357: =(VALUE(LEFT(D357,LEN(D357)-1)*1000000))/100000 -> 29.1
B358: 45588 | C358: 1873.4 | D358: 4.31M | E358: =(VALUE(LEFT(D358,LEN(D358)-1)*1000000))/100000 -> 43.1
B359: 45587 | C359: 1851.6 | D359: 4.13M | E359: =(VALUE(LEFT(D359,LEN(D359)-1)*1000000))/100000 -> 41.3
B360: 45586 | C360: 1852.75 | D360: 4.65M | E360: =(VALUE(LEFT(D360,LEN(D360)-1)*1000000))/100000 -> 46.5
B361: 45583 | C361: 1879.6 | D361: 10.53M | E361: =(VALUE(LEFT(D361,LEN(D361)-1)*1000000))/100000 -> 105.3
B362: 45582 | C362: 1968.1 | D362: 8.16M | E362: =(VALUE(LEFT(D362,LEN(D362)-1)*1000000))/100000 -> 81.6
B363: 45581 | C363: 1920.1 | D363: 3.11M | E363: =(VALUE(LEFT(D363,LEN(D363)-1)*1000000))/100000 -> 31.1
... B465: 45433 | C465: 1426.11 | D465: 6.75M | E465: =(VALUE(LEFT(D465,LEN(D465)-1)*1000000))/100000 -> 67.5
B466: 45430 | C466: 1443.65 | D466: 318.28K | E466: =(VALUE(LEFT(D466,LEN(D466)-1)*1000))/100000 -> 3.1828
B467: 45429 | C467: 1436.21 | D467: 7.54M | E467: =(VALUE(LEFT(D467,LEN(D467)-1)*1000000))/100000 -> 75.4
B468: 45428 | C468: 1445.2 | D468: 9.25M | E468: =(VALUE(LEFT(D468,LEN(D468)-1)*1000000))/100000 -> 92.5
B469: 45427 | C469: 1411.99 | D469: 4.33M | E469: =(VALUE(LEFT(D469,LEN(D469)-1)*1000000))/100000 -> 43.3
B470: 45426 | C470: 1416.72 | D470: 3.46M | E470: =(VALUE(LEFT(D470,LEN(D470)-1)*1000000))/100000 -> 34.6
B471: 45425 | C471: 1415.47 | D471: 3.74M | E471: =(VALUE(LEFT(D471,LEN(D471)-1)*1000000))/100000 -> 37.4
B472: 45422 | C472: 1416.92 | D472: 8.78M | E472: =(VALUE(LEFT(D472,LEN(D472)-1)*1000000))/100000 -> 87.8
B473: 45421 | C473: 1431.48 | D473: 6.09M | E473: =(VALUE(LEFT(D473,LEN(D473)-1)*1000000))/100000 -> 60.9
B474: 45420 | C474: 1419.3 | D474: 6.23M | E474: =(VALUE(LEFT(D474,LEN(D474)-1)*1000000))/100000 -> 62.3
B475: 45419 | C475: 1432.88 | D475: 6.08M | E475: =(VALUE(LEFT(D475,LEN(D475)-1)*1000000))/100000 -> 60.8
B476: 45418 | C476: 1417.91 | D476: 6.45M | E476: =(VALUE(LEFT(D476,LEN(D476)-1)*1000000))/100000 -> 64.5
B477: 45415 | C477: 1408.36 | D477: 8.84M | E477: =(VALUE(LEFT(D477,LEN(D477)-1)*1000000))/100000 -> 88.4
B478: 45414 | C478: 1406.52 | D478: 10.08M | E478: =(VALUE(LEFT(D478,LEN(D478)-1)*1000000))/100000 -> 100.8
... B515: 45355 | C515: 1628.03 | D515: 4.45M | E515: =(VALUE(LEFT(D515,LEN(D515)-1)*1000000))/100000 -> 44.5
B516: 45353 | C516: 1656.3 | D516: 292.15K | E516: =(VALUE(LEFT(D516,LEN(D516)-1)*1000))/100000 -> 2.9215
B517: 45352 | C517: 1645.43 | D517: 6.39M | E517: =(VALUE(LEFT(D517,LEN(D517)-1)*1000000))/100000 -> 63.9
B518: 45351 | C518: 1664.52 | D518: 7.81M | E518: =(VALUE(LEFT(D518,LEN(D518)-1)*1000000))/100000 -> 78.1
B519: 45350 | C519: 1661.88 | D519: 3.19M | E519: =(VALUE(LEFT(D519,LEN(D519)-1)*1000000))/100000 -> 31.9
B520: 45349 | C520: 1654.28 | D520: 5.16M | E520: =(VALUE(LEFT(D520,LEN(D520)-1)*1000000))/100000 -> 51.6
B521: 45348 | C521: 1650.85 | D521: 2.78M | E521: =(VALUE(LEFT(D521,LEN(D521)-1)*1000000))/100000 -> 27.8
B522: 45345 | C522: 1667.45 | D522: 5.37M | E522: =(VALUE(LEFT(D522,LEN(D522)-1)*1000000))/100000 -> 53.7
B523: 45344 | C523: 1671.93 | D523: 5.84M | E523: =(VALUE(LEFT(D523,LEN(D523)-1)*1000000))/100000 -> 58.4
B524: 45343 | C524: 1646.27 | D524: 4.30M | E524: =(VALUE(LEFT(D524,LEN(D524)-1)*1000000))/100000 -> 43
B525: 45342 | C525: 1675.81 | D525: 3.71M | E525: =(VALUE(LEFT(D525,LEN(D525)-1)*1000000))/100000 -> 37.1
B526: 45341 | C526: 1690.22 | D526: 3.69M | E526: =(VALUE(LEFT(D526,LEN(D526)-1)*1000000))/100000 -> 36.9
B527: 45338 | C527: 1692.11 | D527: 4.88M | E527: =(VALUE(LEFT(D527,LEN(D527)-1)*1000000))/100000 -> 48.8
B528: 45337 | C528: 1666.96 | D528: 4.83M | E528: =(VALUE(LEFT(D528,LEN(D528)-1)*1000000))/100000 -> 48.3
... B592: 45243 | C592: 1365.85 | D592: 3.46M | E592: =(VALUE(LEFT(D592,LEN(D592)-1)*1000000))/100000 -> 34.6
B593: 45242 | C593: 1388.2 | D593: 572.24K | E593: =(VALUE(LEFT(D593,LEN(D593)-1)*1000))/100000 -> 5.7224
B594: 45240 | C594: 1361.18 | D594: 2.94M | E594: =(VALUE(LEFT(D594,LEN(D594)-1)*1000000))/100000 -> 29.4
B595: 45239 | C595: 1367.1 | D595: 5.50M | E595: =(VALUE(LEFT(D595,LEN(D595)-1)*1000000))/100000 -> 55
B596: 45238 | C596: 1383.2 | D596: 3.55M | E596: =(VALUE(LEFT(D596,LEN(D596)-1)*1000000))/100000 -> 35.5
B597: 45237 | C597: 1396.43 | D597: 2.27M | E597: =(VALUE(LEFT(D597,LEN(D597)-1)*1000000))/100000 -> 22.7
B598: 45236 | C598: 1395.44 | D598: 2.74M | E598: =(VALUE(LEFT(D598,LEN(D598)-1)*1000000))/100000 -> 27.4
B599: 45233 | C599: 1381.27 | D599: 3.35M | E599: =(VALUE(LEFT(D599,LEN(D599)-1)*1000000))/100000 -> 33.5
B600: 45232 | C600: 1362.47 | D600: 3.76M | E600: =(VALUE(LEFT(D600,LEN(D600)-1)*1000000))/100000 -> 37.6
B601: 45231 | C601: 1346.56 | D601: 3.09M | E601: =(VALUE(LEFT(D601,LEN(D601)-1)*1000000))/100000 -> 30.9
B602: 45230 | C602: 1360.73 | D602: 3.45M | E602: =(VALUE(LEFT(D602,LEN(D602)-1)*1000000))/100000 -> 34.5
B603: 45229 | C603: 1369.33 | D603: 2.67M | E603: =(VALUE(LEFT(D603,LEN(D603)-1)*1000000))/100000 -> 26.7
B604: 45226 | C604: 1372.61 | D604: 4.63M | E604: =(VALUE(LEFT(D604,LEN(D604)-1)*1000000))/100000 -> 46.3
B605: 45225 | C605: 1351.83 | D605: 6.36M | E605: =(VALUE(LEFT(D605,LEN(D605)-1)*1000000))/100000 -> 63.6
... B853: 44859 | C853: 1517.75 | D853: 3.91M | E853: =(VALUE(LEFT(D853,LEN(D853)-1)*1000000))/100000 -> 39.1
B854: 44858 | C854: 1509.34 | D854: 982.84K | E854: =(VALUE(LEFT(D854,LEN(D854)-1)*1000))/100000 -> 9.8284
B855: 44855 | C855: 1492.09 | D855: 3.59M | E855: =(VALUE(LEFT(D855,LEN(D855)-1)*1000000))/100000 -> 35.9
B856: 44854 | C856: 1492.49 | D856: 4.58M | E856: =(VALUE(LEFT(D856,LEN(D856)-1)*1000000))/100000 -> 45.8
B857: 44853 | C857: 1477.13 | D857: 3.55M | E857: =(VALUE(LEFT(D857,LEN(D857)-1)*1000000))/100000 -> 35.5
B858: 44852 | C858: 1495.27 | D858: 4.69M | E858: =(VALUE(LEFT(D858,LEN(D858)-1)*1000000))/100000 -> 46.9
B859: 44851 | C859: 1481.6 | D859: 4.29M | E859: =(VALUE(LEFT(D859,LEN(D859)-1)*1000000))/100000 -> 42.9
B860: 44848 | C860: 1465.99 | D860: 14.99M | E860: =(VALUE(LEFT(D860,LEN(D860)-1)*1000000))/100000 -> 149.9
B861: 44847 | C861: 1411.94 | D861: 4.82M | E861: =(VALUE(LEFT(D861,LEN(D861)-1)*1000000))/100000 -> 48.2
B862: 44846 | C862: 1420.69 | D862: 5.48M | E862: =(VALUE(LEFT(D862,LEN(D862)-1)*1000000))/100000 -> 54.8
B863: 44845 | C863: 1415.82 | D863: 12.82M | E863: =(VALUE(LEFT(D863,LEN(D863)-1)*1000000))/100000 -> 128.2
B864: 44844 | C864: 1454.45 | D864: 5.27M | E864: =(VALUE(LEFT(D864,LEN(D864)-1)*1000000))/100000 -> 52.7
B865: 44841 | C865: 1443.07 | D865: 3.99M | E865: =(VALUE(LEFT(D865,LEN(D865)-1)*1000000))/100000 -> 39.9
B866: 44840 | C866: 1446.99 | D866: 6.18M | E866: =(VALUE(LEFT(D866,LEN(D866)-1)*1000000))/100000 -> 61.8
... B1093: 44508 | C1093: 1737.5 | D1093: 5.25M | E1093: =(VALUE(LEFT(D1093,LEN(D1093)-1)*1000000))/100000 -> 52.5
B1094: 44504 | C1094: 1708.7 | D1094: 483.41K | E1094: =(VALUE(LEFT(D1094,LEN(D1094)-1)*1000))/100000 -> 4.8341
B1095: 44503 | C1095: 1702.5 | D1095: 3.53M | E1095: =(VALUE(LEFT(D1095,LEN(D1095)-1)*1000000))/100000 -> 35.3
B1096: 44502 | C1096: 1697.9 | D1096: 3.47M | E1096: =(VALUE(LEFT(D1096,LEN(D1096)-1)*1000000))/100000 -> 34.7
B1097: 44501 | C1097: 1700.05 | D1097: 3.64M | E1097: =(VALUE(LEFT(D1097,LEN(D1097)-1)*1000000))/100000 -> 36.4
B1098: 44498 | C1098: 1667.75 | D1098: 5.88M | E1098: =(VALUE(LEFT(D1098,LEN(D1098)-1)*1000000))/100000 -> 58.8
B1099: 44497 | C1099: 1703.9 | D1099: 5.33M | E1099: =(VALUE(LEFT(D1099,LEN(D1099)-1)*1000000))/100000 -> 53.3
B1100: 44496 | C1100: 1728.95 | D1100: 5.09M | E1100: =(VALUE(LEFT(D1100,LEN(D1100)-1)*1000000))/100000 -> 50.9
B1101: 44495 | C1101: 1703.7 | D1101: 5.87M | E1101: =(VALUE(LEFT(D1101,LEN(D1101)-1)*1000000))/100000 -> 58.7
B1102: 44494 | C1102: 1707.55 | D1102: 5.91M | E1102: =(VALUE(LEFT(D1102,LEN(D1102)-1)*1000000))/100000 -> 59.1
B1103: 44491 | C1103: 1719.8 | D1103: 7.37M | E1103: =(VALUE(LEFT(D1103,LEN(D1103)-1)*1000000))/100000 -> 73.7
B1104: 44490 | C1104: 1753.65 | D1104: 8.78M | E1104: =(VALUE(LEFT(D1104,LEN(D1104)-1)*1000000))/100000 -> 87.8
B1105: 44489 | C1105: 1802.35 | D1105: 5.88M | E1105: =(VALUE(LEFT(D1105,LEN(D1105)-1)*1000000))/100000 -> 58.8
B1106: 44488 | C1106: 1822.15 | D1106: 10.32M | E1106: =(VALUE(LEFT(D1106,LEN(D1106)-1)*1000000))/100000 -> 103.2
... B1241: 44287 | C1241: 1385.2 | D1241: 5.68M | E1241: =(VALUE(LEFT(D1241,LEN(D1241)-1)*1000000))/100000 -> 56.8
